Workbook

Sheet Dashboard
B2: BLACK-SCHOLES OPTIONS PRICING DASHBOARD
B3: Option Pricing · Greeks Analysis · Sensitivity Tables · Payoff Diagrams
B4: Arsh Gulia | FRM Certified | B.A. (Hons.) Business Economics, University of Delhi
B6: MODEL NAVIGATION
B7: 1. Assumptions | C7: Input all parameters: Stock Price, Strike, Vol, Rate, Time. START HERE.
B8: 2. Option Pricer | C8: Live Black-Scholes Call & Put prices with all 5 Greeks calculated.
B9: 3. Sensitivity Tables | C9: How option price and Greeks change across spot prices and volatilities.
B10: 4. Payoff Analysis | C10: P&L diagrams at expiry for long/short call and put strategies.
B11: 5. Greeks Deep-Dive | C11: Individual Greek profiles across strike range with interpretations.
B13: COLOUR CODING CONVENTION
B14: Blue text | C14: Hardcoded inputs — values you change
B15: Black text | C15: Formulas & calculations — do not edit
B16: Green text | C16: Cross-sheet links from Assumptions
B17: Yellow bg | C17: Key input cells requiring your attention
B19: BLACK-SCHOLES MODEL — FORMULAE
B20: Call Price | C20: C = S·N(d₁) − K·e^(−rT)·N(d₂)
B21: Put Price | C21: P = K·e^(−rT)·N(−d₂) − S·N(−d₁)
B22: d₁ | C22: d₁ = [ln(S/K) + (r + σ²/2)·T] / (σ·√T)
B23: d₂ | C23: d₂ = d₁ − σ·√T
B24: Delta (Δ) | C24: Call: N(d₁) | Put: N(d₁) − 1
B25: Gamma (Γ) | C25: N'(d₁) / (S·σ·√T) [same for call and put]
B26: Vega (ν) | C26: S·N'(d₁)·√T [same for call and put, per 1% vol move ÷100]
B27: Theta (Θ) | C27: −[S·N'(d₁)·σ/(2√T)] − r·K·e^(−rT)·N(d₂) [call, per day ÷365]
B28: Rho (ρ) | C28: Call: K·T·e^(−rT)·N(d₂)·0.01 | Put: −K·T·e^(−rT)·N(−d₂)·0.01

Sheet Assumptions
B2: INPUT PARAMETERS — BLACK-SCHOLES MODEL
B3: Change the BLUE cells below. All other sheets update automatically.
B5: A. OPTION PARAMETERS
B6: S — Current Stock Price (₹) | C6: 2500 | D6: e.g. RELIANCE at ₹2,500
B7: K — Strike Price (₹) | C7: 2500 | D7: At-the-money option
B8: σ — Annual Volatility (%) | C8: 0.25 | D8: 25% vol — typical mid-cap India
B9: r — Risk-Free Rate (% p.a.) | C9: 0.065 | D9: ~RBI repo rate proxy
B10: T — Time to Expiry (Years) | C10: 0.25 | D10: 3 months = 0.25 years
B11: q — Dividend Yield (% p.a.) | C11: 0.01 | D11: Set to 0 if no dividend
B13: B. DERIVED INTERMEDIATE VALUES (for transparency)
B14: ln(S/K) | C14: =LN(C6/C7) -> 0 | D14: Natural log of moneyness
B15: σ·√T | C15: =C8*SQRT(C10) -> 0.125 | D15: Volatility scaled to time
B16: d₁ | C16: =(LN(C6/C7)+(C9-C11+C8^2/2)*C10)/(C8*SQRT(C10)) -> 0.1725 | D16: d1 parameter
B17: d₂ = d₁ − σ√T | C17: =C16-C8*SQRT(C10) -> 0.0475 | D17: d2 parameter
B18: N(d₁) [Cumulative] | C18: =NORMSDIST(C16) -> 0.56847777 | D18: Probability d1
B19: N(d₂) [Cumulative] | C19: =NORMSDIST(C17) -> 0.51894263 | D19: Probability d2
B20: N(−d₁) | C20: =1-C18 -> 0.43152223 | D20: 1 - N(d1)
B21: N(−d₂) | C21: =1-C19 -> 0.48105737 | D21: 1 - N(d2)
B22: N'(d₁) [PDF] | C22: =NORMDIST(C16,0,1,FALSE()) -> 0.3930507 | D22: Standard normal density at d1
B23: e^(−rT) | C23: =EXP(-(C9-C11)*C10) -> 0.9863441 | D23: Discount factor
B25: C. SENSITIVITY TABLE RANGES (used in Sensitivity Tables sheet)
B26: Spot Price Min (₹) | C26: =C6*0.7 -> 1750 | D26: 70% of current spot
B27: Spot Price Max (₹) | C27: =C6*1.3 -> 3250 | D27: 130% of current spot
B28: Spot Price Step (₹) | C28: 50 | D28: Increment between spot prices
B29: Volatility Min (%) | C29: 0.1 | D29: 10% vol lower bound
B30: Volatility Max (%) | C30: 0.5 | D30: 50% vol upper bound
B31: Volatility Step (%) | C31: 0.05 | D31: 5% increments

Sheet Option Pricer
B2: OPTION PRICER — BLACK-SCHOLES LIVE PRICING & GREEKS
B3: All values update automatically when Assumptions sheet inputs are changed
B5: A. OPTION PRICES
B6: Metric | C6: CALL Option | D6: Interpretation | F6: PUT Option | G6: Interpretation
B7: Option Price (₹) | C7: =Assumptions!C6*Assumptions!C18*EXP(-Assumptions!C11*Assumptions!C10)-Assumptions!C7*Assumptions!C23*Assumptions!C19 -> 138.00586 | D7: Max amount CALL buyer should pay | E7: =Assumptions!C7*Assumptions!C23*Assumptions!C21-Assumptions!C6*EXP(-Assumptions!C11*Assumptions!C10)*Assumptions!C20 -> 110.1083 | F7: Max amount PUT buyer should pay
B8: Intrinsic Value (₹) | C8: =MAX(Assumptions!C6-Assumptions!C7,0) -> 0 | D8: In-the-money amount (floor = 0) | E8: =MAX(Assumptions!C7-Assumptions!C6,0) -> 0 | F8: In-the-money amount (floor = 0)
B9: Time Value (₹) | C9: =C7-C8 -> 138.00586 | D9: Premium above intrinsic value | E9: =E7-E8 -> 110.1083 | F9: Premium above intrinsic value
B10: Moneyness | C10: =IF(Assumptions!C6>Assumptions!C7,"In-the-Money (ITM)",IF(Assumptions!C6=Assumptions!C7,"At-the-Money (ATM)","Out-of-the-Money (OTM)")) -> At-the-Money (ATM) | D10: Relationship of spot to strike | E10: =IF(Assumptions!C6<Assumptions!C7,"In-the-Money (ITM)",IF(Assumptions!C6=Assumptions!C7,"At-the-Money (ATM)","Out-of-the-Money (OTM)")) -> At-the-Money (ATM) | F10: Relationship of spot to strike
B12: B. THE GREEKS — RISK SENSITIVITIES
B13: Greek | C13: Symbol | D13: CALL Value | E13: PUT Value | F13: Unit | G13: What it Measures | H13: Risk Management Use
B14: Delta | C14: Δ | D14: =Assumptions!C18 -> 0.56847777 | E14: =Assumptions!C18-1 -> -0.43152223 | F14: ₹ per ₹1 move in S | G14: Change in option price per ₹1 rise in stock | J14: Hedge ratio — units of stock to hold per option sold
B15: Gamma | C15: Γ | D15: =Assumptions!C22/(Assumptions!C6*Assumptions!C8*SQRT(Assumptions!C10)) -> 0.0012577623 | E15: =Assumptions!C22/(Assumptions!C6*Assumptions!C8*SQRT(Assumptions!C10)) -> 0.0012577623 | F15: Δ per ₹1 move in S | G15: Rate of change of Delta; acceleration of option value | J15: High Gamma = Delta hedges need frequent rebalancing
B16: Vega | C16: ν | D16: =Assumptions!C6*Assumptions!C22*SQRT(Assumptions!C10)/100 -> 4.9131338 | E16: =Assumptions!C6*Assumptions!C22*SQRT(Assumptions!C10)/100 -> 4.9131338 | F16: ₹ per 1% vol move | G16: Sensitivity to implied volatility (per 1% change) | J16: Long options have positive Vega — profit from vol spikes
B17: Theta | C17: Θ | D17: =(-(Assumptions!C6*Assumptions!C22*Assumptions!C8)/(2*SQRT(Assumptions!C10))-(Assumptions!C9-Assumptions!C11)*Assumptions!C7*Assumptions!C23*Assumptions!C19)/365 -> -0.86585449 | E17: =(-(Assumptions!C6*Assumptions!C22*Assumptions!C8)/(2*SQRT(Assumptions!C10))+(Assumptions!C9-Assumptions!C11)*Assumptions!C7*Assumptions!C23*Assumptions!C21)/365 -> -0.49428651 | F17: ₹ per calendar day | G17: Time decay — option loses this value each day | J17: Theta is negative for buyers — time erodes option value
B18: Rho | C18: ρ | D18: =Assumptions!C7*Assumptions!C10*Assumptions!C23*Assumptions!C19*0.01 -> 3.1991 | E18: =-Assumptions!C7*Assumptions!C10*Assumptions!C23*Assumptions!C21*0.01 -> -2.9655506 | F18: ₹ per 1% rate move | G18: Sensitivity to risk-free interest rate | J18: Least important Greek in short-dated equity options
B20: C. PUT-CALL PARITY VERIFICATION
B21: C + K·e^(−rT) | E21: = | F21: P + S·e^(−qT) | I21: Difference
B22: Left Side (C + Ke^-rT) | C22: =C7+Assumptions!C7*Assumptions!C23 -> 2603.8661 | E22: vs | F22: Right Side (P + Se^-qT) | G22: =E7+Assumptions!C6*EXP(-Assumptions!C11*Assumptions!C10) -> 2603.8661 | I22: =ABS(C22-G22) -> 0 | J22: Difference should be ~₹0.00 — confirms model accuracy

Sheet Sensitivity Tables
B2: SENSITIVITY ANALYSIS — OPTION PRICES & DELTA ACROSS SPOT AND VOLATILITY
B3: Shows how Call/Put prices and Delta change as Spot Price (rows) and Volatility (columns) vary simultaneously
B5: CALL OPTION PRICE (₹) — Spot vs Volatility
B6: Spot ↓ Vol → | C6: 10% | D6: 15% | E6: 20% | F6: 25% | G6: 30% | H6: 35% | I6: 40% | J6: 45% | K6: 50%
B7: 1750 | C7: =1750*EXP(-Assumptions!$C$11*Assumptions!$C$10)*NORMSDIST((LN(1750/Assumptions!$C$7)+(Assumptions!$C$9-Assumptions!$C$11+0.1^2/2)*Assumptions!$C$10)/(0.1*SQRT(Assumptions!$C$10)))-Assumptions!$C$7*EXP(-Assumptions!$C$9*Assumptions!$C$10)*NORMSDIST(((LN(1750/Assumptions!$C$7)+(Assumptions!$C$9-Assumptions!$C$11+0.1^2/2)*Assumptions!$C$10)/(0.1*SQRT(Assumptions!$C$10)))-0.1*SQRT(Assumptions!$C$10)) -> 5.0517131e-11 | D7: =1750*EXP(-Assumptions!$C$11*Assumptions!$C$10)*NORMSDIST((LN(1750/Assumptions!$C$7)+(Assumptions!$C$9-Assumptions!$C$11+0.15^2/2)*Assumptions!$C$10)/(0.15*SQRT(Assumptions!$C$10)))-Assumptions!$C$7*EXP(-Assumptions!$C$9*Assumptions!$C$10)*NORMSDIST(((LN(1750/Assumptions!$C$7)+(Assumptions!$C$9-Assumptions!$C$11+0.15^2/2)*Assumptions!$C$10)/(0.15*SQRT(Assumptions!$C$10)))-0.15*SQRT(Assumptions!$C$10)) -> 7.5488997e-05 | E7: =1750*EXP(-Assumptions!$C$11*Assumptions!$C$10)*NORMSDIST((LN(1750/Assumptions!$C$7)+(Assumptions!$C$9-Assumptions!$C$11+0.2^2/2)*Assumptions!$C$10)/(0.2*SQRT(Assumptions!$C$10)))-Assumptions!$C$7*EXP(-Assumptions!$C$9*Assumptions!$C$10)*NORMSDIST(((LN(1750/Assumptions!$C$7)+(Assumptions!$C$9-Assumptions!$C$11+0.2^2/2)*Assumptions!$C$10)/(0.2*SQRT(Assumptions!$C$10)))-0.2*SQRT(Assumptions!$C$10)) -> 0.016002861 | F7: =1750*EXP(-Assumptions!$C$11*Assumptions!$C$10)*NORMSDIST((LN(1750/Assumptions!$C$7)+(Assumptions!$C$9-Assumptions!$C$11+0.25^2/2)*Assumptions!$C$10)/(0.25*SQRT(Assumptions!$C$10)))-Assumptions!$C$7*EXP(-Assumptions!$C$9*Assumptions!$C$10)*NORMSDIST(((LN(1750/Assumptions!$C$7)+(Assumptions!$C$9-Assumptions!$C$11+0.25^2/2)*Assumptions!$C$10)/(0.25*SQRT(Assumptions!$C$10)))-0.25*SQRT(Assumptions!$C$10)) -> 0.23766239 | G7: =1750*EXP(-Assumptions!$C$11*Assumptions!$C$10)*NORMSDIST((LN(1750/Assumptions!$C$7)+(Assumptions!$C$9-Assumptions!$C$11+0.3^2/2)*Assumptions!$C$10)/(0.3*SQRT(Assumptions!$C$10)))-Assumptions!$C$7*EXP(-Assumptions!$C$9*Assumptions!$C$10)*NORMSDIST(((LN(1750/Assumptions!$C$7)+(Assumptions!$C$9-Assumptions!$C$11+0.3^2/2)*Assumptions!$C$10)/(0.3*SQRT(Assumptions!$C$10)))-0.3*SQRT(Assumptions!$C$10)) -> 1.1823457 | H7: =1750*EXP(-Assumptions!$C$11*Assumptions!$C$10)*NORMSDIST((LN(1750/Assumptions!$C$7)+(Assumptions!$C$9-Assumptions!$C$11+0.35^2/2)*Assumptions!$C$10)/(0.35*SQRT(Assumptions!$C$10)))-Assumptions!$C$7*EXP(-Assumptions!$C$9*Assumptions!$C$10)*NORMSDIST(((LN(1750/Assumptions!$C$7)+(Assumptions!$C$9-Assumptions!$C$11+0.35^2/2)*Assumptions!$C$10)/(0.35*SQRT(Assumptions!$C$10)))-0.35*SQRT(Assumptions!$C$10)) -> 3.4186436 | I7: =1750*EXP(-Assumptions!$C$11*Assumptions!$C$10)*NORMSDIST((LN(1750/Assumptions!$C$7)+(Assumptions!$C$9-Assumptions!$C$11+0.4^2/2)*Assumptions!$C$10)/(0.4*SQRT(Assumptions!$C$10)))-Assumptions!$C$7*EXP(-Assumptions!$C$9*Assumptions!$C$10)*NORMSDIST(((LN(1750/Assumptions!$C$7)+(Assumptions!$C$9-Assumptions!$C$11+0.4^2/2)*Assumptions!$C$10)/(0.4*SQRT(Assumptions!$C$10)))-0.4*SQRT(Assumptions!$C$10)) -> 7.2855018 | J7: =1750*EXP(-Assumptions!$C$11*Assumptions!$C$10)*NORMSDIST((LN(1750/Assumptions!$C$7)+(Assumptions!$C$9-Assumptions!$C$11+0.45^2/2)*Assumptions!$C$10)/(0.45*SQRT(Assumptions!$C$10)))-Assumptions!$C$7*EXP(-Assumptions!$C$9*Assumptions!$C$10)*NORMSDIST(((LN(1750/Assumptions!$C$7)+(Assumptions!$C$9-Assumptions!$C$11+0.45^2/2)*Assumptions!$C$10)/(0.45*SQRT(Assumptions!$C$10)))-0.45*SQRT(Assumptions!$C$10)) -> 12.870736 | K7: =1750*EXP(-Assumptions!$C$11*Assumptions!$C$10)*NORMSDIST((LN(1750/Assumptions!$C$7)+(Assumptions!$C$9-Assumptions!$C$11+0.5^2/2)*Assumptions!$C$10)/(0.5*SQRT(Assumptions!$C$10)))-Assumptions!$C$7*EXP(-Assumptions!$C$9*Assumptions!$C$10)*NORMSDIST(((LN(1750/Assumptions!$C$7)+(Assumptions!$C$9-Assumptions!$C$11+0.5^2/2)*Assumptions!$C$10)/(0.5*SQRT(Assumptions!$C$10)))-0.5*SQRT(Assumptions!$C$10)) -> 20.100005
B8: 1800 | C8: =1800*EXP(-Assumptions!$C$11*Assumptions!$C$10)*NORMSDIST((LN(1800/Assumptions!$C$7)+(Assumptions!$C$9-Assumptions!$C$11+0.1^2/2)*Assumptions!$C$10)/(0.1*SQRT(Assumptions!$C$10)))-Assumptions!$C$7*EXP(-Assumptions!$C$9*Assumptions!$C$10)*NORMSDIST(((LN(1800/Assumptions!$C$7)+(Assumptions!$C$9-Assumptions!$C$11+0.1^2/2)*Assumptions!$C$10)/(0.1*SQRT(Assumptions!$C$10)))-0.1*SQRT(Assumptions!$C$10)) -> 2.4478926e-09 | D8: =1800*EXP(-Assumptions!$C$11*Assumptions!$C$10)*NORMSDIST((LN(1800/Assumptions!$C$7)+(Assumptions!$C$9-Assumptions!$C$11+0.15^2/2)*Assumptions!$C$10)/(0.15*SQRT(Assumptions!$C$10)))-Assumptions!$C$7*EXP(-Assumptions!$C$9*Assumptions!$C$10)*NORMSDIST(((LN(1800/Assumptions!$C$7)+(Assumptions!$C$9-Assumptions!$C$11+0.15^2/2)*Assumptions!$C$10)/(0.15*SQRT(Assumptions!$C$10)))-0.15*SQRT(Assumptions!$C$10)) -> 0.00046230084 | E8: =1800*EXP(-Assumptions!$C$11*Assumptions!$C$10)*NORMSDIST((LN(1800/Assumptions!$C$7)+(Assumptions!$C$9-Assumptions!$C$11+0.2^2/2)*Assumptions!$C$10)/(0.2*SQRT(Assumptions!$C$10)))-Assumptions!$C$7*EXP(-Assumptions!$C$9*Assumptions!$C$10)*NORMSDIST(((LN(1800/Assumptions!$C$7)+(Assumptions!$C$9-Assumptions!$C$11+0.2^2/2)*Assumptions!$C$10)/(0.2*SQRT(Assumptions!$C$10)))-0.2*SQRT(Assumptions!$C$10)) -> 0.047183334 | F8: =1800*EXP(-Assumptions!$C$11*Assumptions!$C$10)*NORMSDIST((LN(1800/Assumptions!$C$7)+(Assumptions!$C$9-Assumptions!$C$11+0.25^2/2)*Assumptions!$C$10)/(0.25*SQRT(Assumptions!$C$10)))-Assumptions!$C$7*EXP(-Assumptions!$C$9*Assumptions!$C$10)*NORMSDIST(((LN(1800/Assumptions!$C$7)+(Assumptions!$C$9-Assumptions!$C$11+0.25^2/2)*Assumptions!$C$10)/(0.25*SQRT(Assumptions!$C$10)))-0.25*SQRT(Assumptions!$C$10)) -> 0.49698109 | G8: =1800*EXP(-Assumptions!$C$11*Assumptions!$C$10)*NORMSDIST((LN(1800/Assumptions!$C$7)+(Assumptions!$C$9-Assumptions!$C$11+0.3^2/2)*Assumptions!$C$10)/(0.3*SQRT(Assumptions!$C$10)))-Assumptions!$C$7*EXP(-Assumptions!$C$9*Assumptions!$C$10)*NORMSDIST(((LN(1800/Assumptions!$C$7)+(Assumptions!$C$9-Assumptions!$C$11+0.3^2/2)*Assumptions!$C$10)/(0.3*SQRT(Assumptions!$C$10)))-0.3*SQRT(Assumptions!$C$10)) -> 2.0436678 | H8: =1800*EXP(-Assumptions!$C$11*Assumptions!$C$10)*NORMSDIST((LN(1800/Assumptions!$C$7)+(Assumptions!$C$9-Assumptions!$C$11+0.35^2/2)*Assumptions!$C$10)/(0.35*SQRT(Assumptions!$C$10)))-Assumptions!$C$7*EXP(-Assumptions!$C$9*Assumptions!$C$10)*NORMSDIST(((LN(1800/Assumptions!$C$7)+(Assumptions!$C$9-Assumptions!$C$11+0.35^2/2)*Assumptions!$C$10)/(0.35*SQRT(Assumptions!$C$10)))-0.35*SQRT(Assumptions!$C$10)) -> 5.2533161 | I8: =1800*EXP(-Assumptions!$C$11*Assumptions!$C$10)*NORMSDIST((LN(1800/Assumptions!$C$7)+(Assumptions!$C$9-Assumptions!$C$11+0.4^2/2)*Assumptions!$C$10)/(0.4*SQRT(Assumptions!$C$10)))-Assumptions!$C$7*EXP(-Assumptions!$C$9*Assumptions!$C$10)*NORMSDIST(((LN(1800/Assumptions!$C$7)+(Assumptions!$C$9-Assumptions!$C$11+0.4^2/2)*Assumptions!$C$10)/(0.4*SQRT(Assumptions!$C$10)))-0.4*SQRT(Assumptions!$C$10)) -> 10.351072 | J8: =1800*EXP(-Assumptions!$C$11*Assumptions!$C$10)*NORMSDIST((LN(1800/Assumptions!$C$7)+(Assumptions!$C$9-Assumptions!$C$11+0.45^2/2)*Assumptions!$C$10)/(0.45*SQRT(Assumptions!$C$10)))-Assumptions!$C$7*EXP(-Assumptions!$C$9*Assumptions!$C$10)*NORMSDIST(((LN(1800/Assumptions!$C$7)+(Assumptions!$C$9-Assumptions!$C$11+0.45^2/2)*Assumptions!$C$10)/(0.45*SQRT(Assumptions!$C$10)))-0.45*SQRT(Assumptions!$C$10)) -> 17.30243 | K8: =1800*EXP(-Assumptions!$C$11*Assumptions!$C$10)*NORMSDIST((LN(1800/Assumptions!$C$7)+(Assumptions!$C$9-Assumptions!$C$11+0.5^2/2)*Assumptions!$C$10)/(0.5*SQRT(Assumptions!$C$10)))-Assumptions!$C$7*EXP(-Assumptions!$C$9*Assumptions!$C$10)*NORMSDIST(((LN(1800/Assumptions!$C$7)+(Assumptions!$C$9-Assumptions!$C$11+0.5^2/2)*Assumptions!$C$10)/(0.5*SQRT(Assumptions!$C$10)))-0.5*SQRT(Assumptions!$C$10)) -> 25.941807
B9: 1850 | C9: =1850*EXP(-Assumptions!$C$11*Assumptions!$C$10)*NORMSDIST((LN(1850/Assumptions!$C$7)+(Assumptions!$C$9-Assumptions!$C$11+0.1^2/2)*Assumptions!$C$10)/(0.1*SQRT(Assumptions!$C$10)))-Assumptions!$C$7*EXP(-Assumptions!$C$9*Assumptions!$C$10)*NORMSDIST(((LN(1850/Assumptions!$C$7)+(Assumptions!$C$9-Assumptions!$C$11+0.1^2/2)*Assumptions!$C$10)/(0.1*SQRT(Assumptions!$C$10)))-0.1*SQRT(Assumptions!$C$10)) -> 7.9655865e-08 | D9: =1850*EXP(-Assumptions!$C$11*Assumptions!$C$10)*NORMSDIST((LN(1850/Assumptions!$C$7)+(Assumptions!$C$9-Assumptions!$C$11+0.15^2/2)*Assumptions!$C$10)/(0.15*SQRT(Assumptions!$C$10)))-Assumptions!$C$7*EXP(-Assumptions!$C$9*Assumptions!$C$10)*NORMSDIST(((LN(1850/Assumptions!$C$7)+(Assumptions!$C$9-Assumptions!$C$11+0.15^2/2)*Assumptions!$C$10)/(0.15*SQRT(Assumptions!$C$10)))-0.15*SQRT(Assumptions!$C$10)) -> 0.0023778842 | E9: =1850*EXP(-Assumptions!$C$11*Assumptions!$C$10)*NORMSDIST((LN(1850/Assumptions!$C$7)+(Assumptions!$C$9-Assumptions!$C$11+0.2^2/2)*Assumptions!$C$10)/(0.2*SQRT(Assumptions!$C$10)))-Assumptions!$C$7*EXP(-Assumptions!$C$9*Assumptions!$C$10)*NORMSDIST(((LN(1850/Assumptions!$C$7)+(Assumptions!$C$9-Assumptions!$C$11+0.2^2/2)*Assumptions!$C$10)/(0.2*SQRT(Assumptions!$C$10)))-0.2*SQRT(Assumptions!$C$10)) -> 0.12623789 | F9: =1850*EXP(-Assumptions!$C$11*Assumptions!$C$10)*NORMSDIST((LN(1850/Assumptions!$C$7)+(Assumptions!$C$9-Assumptions!$C$11+0.25^2/2)*Assumptions!$C$10)/(0.25*SQRT(Assumptions!$C$10)))-Assumptions!$C$7*EXP(-Assumptions!$C$9*Assumptions!$C$10)*NORMSDIST(((LN(1850/Assumptions!$C$7)+(Assumptions!$C$9-Assumptions!$C$11+0.25^2/2)*Assumptions!$C$10)/(0.25*SQRT(Assumptions!$C$10)))-0.25*SQRT(Assumptions!$C$10)) -> 0.97689116 | G9: =1850*EXP(-Assumptions!$C$11*Assumptions!$C$10)*NORMSDIST((LN(1850/Assumptions!$C$7)+(Assumptions!$C$9-Assumptions!$C$11+0.3^2/2)*Assumptions!$C$10)/(0.3*SQRT(Assumptions!$C$10)))-Assumptions!$C$7*EXP(-Assumptions!$C$9*Assumptions!$C$10)*NORMSDIST(((LN(1850/Assumptions!$C$7)+(Assumptions!$C$9-Assumptions!$C$11+0.3^2/2)*Assumptions!$C$10)/(0.3*SQRT(Assumptions!$C$10)))-0.3*SQRT(Assumptions!$C$10)) -> 3.3837866 | H9: =1850*EXP(-Assumptions!$C$11*Assumptions!$C$10)*NORMSDIST((LN(1850/Assumptions!$C$7)+(Assumptions!$C$9-Assumptions!$C$11+0.35^2/2)*Assumptions!$C$10)/(0.35*SQRT(Assumptions!$C$10)))-Assumptions!$C$7*EXP(-Assumptions!$C$9*Assumptions!$C$10)*NORMSDIST(((LN(1850/Assumptions!$C$7)+(Assumptions!$C$9-Assumptions!$C$11+0.35^2/2)*Assumptions!$C$10)/(0.35*SQRT(Assumptions!$C$10)))-0.35*SQRT(Assumptions!$C$10)) -> 7.8202577 | I9: =1850*EXP(-Assumptions!$C$11*Assumptions!$C$10)*NORMSDIST((LN(1850/Assumptions!$C$7)+(Assumptions!$C$9-Assumptions!$C$11+0.4^2/2)*Assumptions!$C$10)/(0.4*SQRT(Assumptions!$C$10)))-Assumptions!$C$7*EXP(-Assumptions!$C$9*Assumptions!$C$10)*NORMSDIST(((LN(1850/Assumptions!$C$7)+(Assumptions!$C$9-Assumptions!$C$11+0.4^2/2)*Assumptions!$C$10)/(0.4*SQRT(Assumptions!$C$10)))-0.4*SQRT(Assumptions!$C$10)) -> 14.350055 | J9: =1850*EXP(-Assumptions!$C$11*Assumptions!$C$10)*NORMSDIST((LN(1850/Assumptions!$C$7)+(Assumptions!$C$9-Assumptions!$C$11+0.45^2/2)*Assumptions!$C$10)/(0.45*SQRT(Assumptions!$C$10)))-Assumptions!$C$7*EXP(-Assumptions!$C$9*Assumptions!$C$10)*NORMSDIST(((LN(1850/Assumptions!$C$7)+(Assumptions!$C$9-Assumptions!$C$11+0.45^2/2)*Assumptions!$C$10)/(0.45*SQRT(Assumptions!$C$10)))-0.45*SQRT(Assumptions!$C$10)) -> 22.807874 | K9: =1850*EXP(-Assumptions!$C$11*Assumptions!$C$10)*NORMSDIST((LN(1850/Assumptions!$C$7)+(Assumptions!$C$9-Assumptions!$C$11+0.5^2/2)*Assumptions!$C$10)/(0.5*SQRT(Assumptions!$C$10)))-Assumptions!$C$7*EXP(-Assumptions!$C$9*Assumptions!$C$10)*NORMSDIST(((LN(1850/Assumptions!$C$7)+(Assumptions!$C$9-Assumptions!$C$11+0.5^2/2)*Assumptions!$C$10)/(0.5*SQRT(Assumptions!$C$10)))-0.5*SQRT(Assumptions!$C$10)) -> 32.945342
B10: 1900 | C10: =1900*EXP(-Assumptions!$C$11*Assumptions!$C$10)*NORMSDIST((LN(1900/Assumptions!$C$7)+(Assumptions!$C$9-Assumptions!$C$11+0.1^2/2)*Assumptions!$C$10)/(0.1*SQRT(Assumptions!$C$10)))-Assumptions!$C$7*EXP(-Assumptions!$C$9*Assumptions!$C$10)*NORMSDIST(((LN(1900/Assumptions!$C$7)+(Assumptions!$C$9-Assumptions!$C$11+0.1^2/2)*Assumptions!$C$10)/(0.1*SQRT(Assumptions!$C$10)))-0.1*SQRT(Assumptions!$C$10)) -> 1.7952019e-06 | D10: =1900*EXP(-Assumptions!$C$11*Assumptions!$C$10)*NORMSDIST((LN(1900/Assumptions!$C$7)+(Assumptions!$C$9-Assumptions!$C$11+0.15^2/2)*Assumptions!$C$10)/(0.15*SQRT(Assumptions!$C$10)))-Assumptions!$C$7*EXP(-Assumptions!$C$9*Assumptions!$C$10)*NORMSDIST(((LN(1900/Assumptions!$C$7)+(Assumptions!$C$9-Assumptions!$C$11+0.15^2/2)*Assumptions!$C$10)/(0.15*SQRT(Assumptions!$C$10)))-0.15*SQRT(Assumptions!$C$10)) -> 0.010416679 | E10: =1900*EXP(-Assumptions!$C$11*Assumptions!$C$10)*NORMSDIST((LN(1900/Assumptions!$C$7)+(Assumptions!$C$9-Assumptions!$C$11+0.2^2/2)*Assumptions!$C$10)/(0.2*SQRT(Assumptions!$C$10)))-Assumptions!$C$7*EXP(-Assumptions!$C$9*Assumptions!$C$10)*NORMSDIST(((LN(1900/Assumptions!$C$7)+(Assumptions!$C$9-Assumptions!$C$11+0.2^2/2)*Assumptions!$C$10)/(0.2*SQRT(Assumptions!$C$10)))-0.2*SQRT(Assumptions!$C$10)) -> 0.30890004 | F10: =1900*EXP(-Assumptions!$C$11*Assumptions!$C$10)*NORMSDIST((LN(1900/Assumptions!$C$7)+(Assumptions!$C$9-Assumptions!$C$11+0.25^2/2)*Assumptions!$C$10)/(0.25*SQRT(Assumptions!$C$10)))-Assumptions!$C$7*EXP(-Assumptions!$C$9*Assumptions!$C$10)*NORMSDIST(((LN(1900/Assumptions!$C$7)+(Assumptions!$C$9-Assumptions!$C$11+0.25^2/2)*Assumptions!$C$10)/(0.25*SQRT(Assumptions!$C$10)))-0.25*SQRT(Assumptions!$C$10)) -> 1.8141047 | G10: =1900*EXP(-Assumptions!$C$11*Assumptions!$C$10)*NORMSDIST((LN(1900/Assumptions!$C$7)+(Assumptions!$C$9-Assumptions!$C$11+0.3^2/2)*Assumptions!$C$10)/(0.3*SQRT(Assumptions!$C$10)))-Assumptions!$C$7*EXP(-Assumptions!$C$9*Assumptions!$C$10)*NORMSDIST(((LN(1900/Assumptions!$C$7)+(Assumptions!$C$9-Assumptions!$C$11+0.3^2/2)*Assumptions!$C$10)/(0.3*SQRT(Assumptions!$C$10)))-0.3*SQRT(Assumptions!$C$10)) -> 5.3855769 | H10: =1900*EXP(-Assumptions!$C$11*Assumptions!$C$10)*NORMSDIST((LN(1900/Assumptions!$C$7)+(Assumptions!$C$9-Assumptions!$C$11+0.35^2/2)*Assumptions!$C$10)/(0.35*SQRT(Assumptions!$C$10)))-Assumptions!$C$7*EXP(-Assumptions!$C$9*Assumptions!$C$10)*NORMSDIST(((LN(1900/Assumptions!$C$7)+(Assumptions!$C$9-Assumptions!$C$11+0.35^2/2)*Assumptions!$C$10)/(0.35*SQRT(Assumptions!$C$10)))-0.35*SQRT(Assumptions!$C$10)) -> 11.306323 | I10: =1900*EXP(-Assumptions!$C$11*Assumptions!$C$10)*NORMSDIST((LN(1900/Assumptions!$C$7)+(Assumptions!$C$9-Assumptions!$C$11+0.4^2/2)*Assumptions!$C$10)/(0.4*SQRT(Assumptions!$C$10)))-Assumptions!$C$7*EXP(-Assumptions!$C$9*Assumptions!$C$10)*NORMSDIST(((LN(1900/Assumptions!$C$7)+(Assumptions!$C$9-Assumptions!$C$11+0.4^2/2)*Assumptions!$C$10)/(0.4*SQRT(Assumptions!$C$10)))-0.4*SQRT(Assumptions!$C$10)) -> 19.449488 | J10: =1900*EXP(-Assumptions!$C$11*Assumptions!$C$10)*NORMSDIST((LN(1900/Assumptions!$C$7)+(Assumptions!$C$9-Assumptions!$C$11+0.45^2/2)*Assumptions!$C$10)/(0.45*SQRT(Assumptions!$C$10)))-Assumptions!$C$7*EXP(-Assumptions!$C$9*Assumptions!$C$10)*NORMSDIST(((LN(1900/Assumptions!$C$7)+(Assumptions!$C$9-Assumptions!$C$11+0.45^2/2)*Assumptions!$C$10)/(0.45*SQRT(Assumptions!$C$10)))-0.45*SQRT(Assumptions!$C$10)) -> 29.525886 | K10: =1900*EXP(-Assumptions!$C$11*Assumptions!$C$10)*NORMSDIST((LN(1900/Assumptions!$C$7)+(Assumptions!$C$9-Assumptions!$C$11+0.5^2/2)*Assumptions!$C$10)/(0.5*SQRT(Assumptions!$C$10)))-Assumptions!$C$7*EXP(-Assumptions!$C$9*Assumptions!$C$10)*NORMSDIST(((LN(1900/Assumptions!$C$7)+(Assumptions!$C$9-Assumptions!$C$11+0.5^2/2)*Assumptions!$C$10)/(0.5*SQRT(Assumptions!$C$10)))-0.5*SQRT(Assumptions!$C$10)) -> 41.22097
B11: 1950 | C11: =1950*EXP(-Assumptions!$C$11*Assumptions!$C$10)*NORMSDIST((LN(1950/Assumptions!$C$7)+(Assumptions!$C$9-Assumptions!$C$11+0.1^2/2)*Assumptions!$C$10)/(0.1*SQRT(Assumptions!$C$10)))-Assumptions!$C$7*EXP(-Assumptions!$C$9*Assumptions!$C$10)*NORMSDIST(((LN(1950/Assumptions!$C$7)+(Assumptions!$C$9-Assumptions!$C$11+0.1^2/2)*Assumptions!$C$10)/(0.1*SQRT(Assumptions!$C$10)))-0.1*SQRT(Assumptions!$C$10)) -> 2.8825826e-05 | D11: =1950*EXP(-Assumptions!$C$11*Assumptions!$C$10)*NORMSDIST((LN(1950/Assumptions!$C$7)+(Assumptions!$C$9-Assumptions!$C$11+0.15^2/2)*Assumptions!$C$10)/(0.15*SQRT(Assumptions!$C$10)))-Assumptions!$C$7*EXP(-Assumptions!$C$9*Assumptions!$C$10)*NORMSDIST(((LN(1950/Assumptions!$C$7)+(Assumptions!$C$9-Assumptions!$C$11+0.15^2/2)*Assumptions!$C$10)/(0.15*SQRT(Assumptions!$C$10)))-0.15*SQRT(Assumptions!$C$10)) -> 0.039363843 | E11: =1950*EXP(-Assumptions!$C$11*Assumptions!$C$10)*NORMSDIST((LN(1950/Assumptions!$C$7)+(Assumptions!$C$9-Assumptions!$C$11+0.2^2/2)*Assumptions!$C$10)/(0.2*SQRT(Assumptions!$C$10)))-Assumptions!$C$7*EXP(-Assumptions!$C$9*Assumptions!$C$10)*NORMSDIST(((LN(1950/Assumptions!$C$7)+(Assumptions!$C$9-Assumptions!$C$11+0.2^2/2)*Assumptions!$C$10)/(0.2*SQRT(Assumptions!$C$10)))-0.2*SQRT(Assumptions!$C$10)) -> 0.69631666 | F11: =1950*EXP(-Assumptions!$C$11*Assumptions!$C$10)*NORMSDIST((LN(1950/Assumptions!$C$7)+(Assumptions!$C$9-Assumptions!$C$11+0.25^2/2)*Assumptions!$C$10)/(0.25*SQRT(Assumptions!$C$10)))-Assumptions!$C$7*EXP(-Assumptions!$C$9*Assumptions!$C$10)*NORMSDIST(((LN(1950/Assumptions!$C$7)+(Assumptions!$C$9-Assumptions!$C$11+0.25^2/2)*Assumptions!$C$10)/(0.25*SQRT(Assumptions!$C$10)))-0.25*SQRT(Assumptions!$C$10)) -> 3.1973113 | G11: =1950*EXP(-Assumptions!$C$11*Assumptions!$C$10)*NORMSDIST((LN(1950/Assumptions!$C$7)+(Assumptions!$C$9-Assumptions!$C$11+0.3^2/2)*Assumptions!$C$10)/(0.3*SQRT(Assumptions!$C$10)))-Assumptions!$C$7*EXP(-Assumptions!$C$9*Assumptions!$C$10)*NORMSDIST(((LN(1950/Assumptions!$C$7)+(Assumptions!$C$9-Assumptions!$C$11+0.3^2/2)*Assumptions!$C$10)/(0.3*SQRT(Assumptions!$C$10)))-0.3*SQRT(Assumptions!$C$10)) -> 8.2656283 | H11: =1950*EXP(-Assumptions!$C$11*Assumptions!$C$10)*NORMSDIST((LN(1950/Assumptions!$C$7)+(Assumptions!$C$9-Assumptions!$C$11+0.35^2/2)*Assumptions!$C$10)/(0.35*SQRT(Assumptions!$C$10)))-Assumptions!$C$7*EXP(-Assumptions!$C$9*Assumptions!$C$10)*NORMSDIST(((LN(1950/Assumptions!$C$7)+(Assumptions!$C$9-Assumptions!$C$11+0.35^2/2)*Assumptions!$C$10)/(0.35*SQRT(Assumptions!$C$10)))-0.35*SQRT(Assumptions!$C$10)) -> 15.912598 | I11: =1950*EXP(-Assumptions!$C$11*Assumptions!$C$10)*NORMSDIST((LN(1950/Assumptions!$C$7)+(Assumptions!$C$9-Assumptions!$C$11+0.4^2/2)*Assumptions!$C$10)/(0.4*SQRT(Assumptions!$C$10)))-Assumptions!$C$7*EXP(-Assumptions!$C$9*Assumptions!$C$10)*NORMSDIST(((LN(1950/Assumptions!$C$7)+(Assumptions!$C$9-Assumptions!$C$11+0.4^2/2)*Assumptions!$C$10)/(0.4*SQRT(Assumptions!$C$10)))-0.4*SQRT(Assumptions!$C$10)) -> 25.817667 | J11: =1950*EXP(-Assumptions!$C$11*Assumptions!$C$10)*NORMSDIST((LN(1950/Assumptions!$C$7)+(Assumptions!$C$9-Assumptions!$C$11+0.45^2/2)*Assumptions!$C$10)/(0.45*SQRT(Assumptions!$C$10)))-Assumptions!$C$7*EXP(-Assumptions!$C$9*Assumptions!$C$10)*NORMSDIST(((LN(1950/Assumptions!$C$7)+(Assumptions!$C$9-Assumptions!$C$11+0.45^2/2)*Assumptions!$C$10)/(0.45*SQRT(Assumptions!$C$10)))-0.45*SQRT(Assumptions!$C$10)) -> 37.58958 | K11: =1950*EXP(-Assumptions!$C$11*Assumptions!$C$10)*NORMSDIST((LN(1950/Assumptions!$C$7)+(Assumptions!$C$9-Assumptions!$C$11+0.5^2/2)*Assumptions!$C$10)/(0.5*SQRT(Assumptions!$C$10)))-Assumptions!$C$7*EXP(-Assumptions!$C$9*Assumptions!$C$10)*NORMSDIST(((LN(1950/Assumptions!$C$7)+(Assumptions!$C$9-Assumptions!$C$11+0.5^2/2)*Assumptions!$C$10)/(0.5*SQRT(Assumptions!$C$10)))-0.5*SQRT(Assumptions!$C$10)) -> 50.870285
B12: 2000 | C12: =2000*EXP(-Assumptions!$C$11*Assumptions!$C$10)*NORMSDIST((LN(2000/Assumptions!$C$7)+(Assumptions!$C$9-Assumptions!$C$11+0.1^2/2)*Assumptions!$C$10)/(0.1*SQRT(Assumptions!$C$10)))-Assumptions!$C$7*EXP(-Assumptions!$C$9*Assumptions!$C$10)*NORMSDIST(((LN(2000/Assumptions!$C$7)+(Assumptions!$C$9-Assumptions!$C$11+0.1^2/2)*Assumptions!$C$10)/(0.1*SQRT(Assumptions!$C$10)))-0.1*SQRT(Assumptions!$C$10)) -> 0.00033851924 | D12: =2000*EXP(-Assumptions!$C$11*Assumptions!$C$10)*NORMSDIST((LN(2000/Assumptions!$C$7)+(Assumptions!$C$9-Assumptions!$C$11+0.15^2/2)*Assumptions!$C$10)/(0.15*SQRT(Assumptions!$C$10)))-Assumptions!$C$7*EXP(-Assumptions!$C$9*Assumptions!$C$10)*NORMSDIST(((LN(2000/Assumptions!$C$7)+(Assumptions!$C$9-Assumptions!$C$11+0.15^2/2)*Assumptions!$C$10)/(0.15*SQRT(Assumptions!$C$10)))-0.15*SQRT(Assumptions!$C$10)) -> 0.12984511 | E12: =2000*EXP(-Assumptions!$C$11*Assumptions!$C$10)*NORMSDIST((LN(2000/Assumptions!$C$7)+(Assumptions!$C$9-Assumptions!$C$11+0.2^2/2)*Assumptions!$C$10)/(0.2*SQRT(Assumptions!$C$10)))-Assumptions!$C$7*EXP(-Assumptions!$C$9*Assumptions!$C$10)*NORMSDIST(((LN(2000/Assumptions!$C$7)+(Assumptions!$C$9-Assumptions!$C$11+0.2^2/2)*Assumptions!$C$10)/(0.2*SQRT(Assumptions!$C$10)))-0.2*SQRT(Assumptions!$C$10)) -> 1.4555925 | F12: =2000*EXP(-Assumptions!$C$11*Assumptions!$C$10)*NORMSDIST((LN(2000/Assumptions!$C$7)+(Assumptions!$C$9-Assumptions!$C$11+0.25^2/2)*Assumptions!$C$10)/(0.25*SQRT(Assumptions!$C$10)))-Assumptions!$C$7*EXP(-Assumptions!$C$9*Assumptions!$C$10)*NORMSDIST(((LN(2000/Assumptions!$C$7)+(Assumptions!$C$9-Assumptions!$C$11+0.25^2/2)*Assumptions!$C$10)/(0.25*SQRT(Assumptions!$C$10)))-0.25*SQRT(Assumptions!$C$10)) -> 5.3708766 | G12: =2000*EXP(-Assumptions!$C$11*Assumptions!$C$10)*NORMSDIST((LN(2000/Assumptions!$C$7)+(Assumptions!$C$9-Assumptions!$C$11+0.3^2/2)*Assumptions!$C$10)/(0.3*SQRT(Assumptions!$C$10)))-Assumptions!$C$7*EXP(-Assumptions!$C$9*Assumptions!$C$10)*NORMSDIST(((LN(2000/Assumptions!$C$7)+(Assumptions!$C$9-Assumptions!$C$11+0.3^2/2)*Assumptions!$C$10)/(0.3*SQRT(Assumptions!$C$10)))-0.3*SQRT(Assumptions!$C$10)) -> 12.26858 | H12: =2000*EXP(-Assumptions!$C$11*Assumptions!$C$10)*NORMSDIST((LN(2000/Assumptions!$C$7)+(Assumptions!$C$9-Assumptions!$C$11+0.35^2/2)*Assumptions!$C$10)/(0.35*SQRT(Assumptions!$C$10)))-Assumptions!$C$7*EXP(-Assumptions!$C$9*Assumptions!$C$10)*NORMSDIST(((LN(2000/Assumptions!$C$7)+(Assumptions!$C$9-Assumptions!$C$11+0.35^2/2)*Assumptions!$C$10)/(0.35*SQRT(Assumptions!$C$10)))-0.35*SQRT(Assumptions!$C$10)) -> 21.847379 | I12: =2000*EXP(-Assumptions!$C$11*Assumptions!$C$10)*NORMSDIST((LN(2000/Assumptions!$C$7)+(Assumptions!$C$9-Assumptions!$C$11+0.4^2/2)*Assumptions!$C$10)/(0.4*SQRT(Assumptions!$C$10)))-Assumptions!$C$7*EXP(-Assumptions!$C$9*Assumptions!$C$10)*NORMSDIST(((LN(2000/Assumptions!$C$7)+(Assumptions!$C$9-Assumptions!$C$11+0.4^2/2)*Assumptions!$C$10)/(0.4*SQRT(Assumptions!$C$10)))-0.4*SQRT(Assumptions!$C$10)) -> 33.618654 | J12: =2000*EXP(-Assumptions!$C$11*Assumptions!$C$10)*NORMSDIST((LN(2000/Assumptions!$C$7)+(Assumptions!$C$9-Assumptions!$C$11+0.45^2/2)*Assumptions!$C$10)/(0.45*SQRT(Assumptions!$C$10)))-Assumptions!$C$7*EXP(-Assumptions!$C$9*Assumptions!$C$10)*NORMSDIST(((LN(2000/Assumptions!$C$7)+(Assumptions!$C$9-Assumptions!$C$11+0.45^2/2)*Assumptions!$C$10)/(0.45*SQRT(Assumptions!$C$10)))-0.45*SQRT(Assumptions!$C$10)) -> 47.122739 | K12: =2000*EXP(-Assumptions!$C$11*Assumptions!$C$10)*NORMSDIST((LN(2000/Assumptions!$C$7)+(Assumptions!$C$9-Assumptions!$C$11+0.5^2/2)*Assumptions!$C$10)/(0.5*SQRT(Assumptions!$C$10)))-Assumptions!$C$7*EXP(-Assumptions!$C$9*Assumptions!$C$10)*NORMSDIST(((LN(2000/Assumptions!$C$7)+(Assumptions!$C$9-Assumptions!$C$11+0.5^2/2)*Assumptions!$C$10)/(0.5*SQRT(Assumptions!$C$10)))-0.5*SQRT(Assumptions!$C$10)) -> 61.983968
B13: 2050 | C13: =2050*EXP(-Assumptions!$C$11*Assumptions!$C$10)*NORMSDIST((LN(2050/Assumptions!$C$7)+(Assumptions!$C$9-Assumptions!$C$11+0.1^2/2)*Assumptions!$C$10)/(0.1*SQRT(Assumptions!$C$10)))-Assumptions!$C$7*EXP(-Assumptions!$C$9*Assumptions!$C$10)*NORMSDIST(((LN(2050/Assumptions!$C$7)+(Assumptions!$C$9-Assumptions!$C$11+0.1^2/2)*Assumptions!$C$10)/(0.1*SQRT(Assumptions!$C$10)))-0.1*SQRT(Assumptions!$C$10)) -> 0.0029790324 | D13: =2050*EXP(-Assumptions!$C$11*Assumptions!$C$10)*NORMSDIST((LN(2050/Assumptions!$C$7)+(Assumptions!$C$9-Assumptions!$C$11+0.15^2/2)*Assumptions!$C$10)/(0.15*SQRT(Assumptions!$C$10)))-Assumptions!$C$7*EXP(-Assumptions!$C$9*Assumptions!$C$10)*NORMSDIST(((LN(2050/Assumptions!$C$7)+(Assumptions!$C$9-Assumptions!$C$11+0.15^2/2)*Assumptions!$C$10)/(0.15*SQRT(Assumptions!$C$10)))-0.15*SQRT(Assumptions!$C$10)) -> 0.37798345 | E13: =2050*EXP(-Assumptions!$C$11*Assumptions!$C$10)*NORMSDIST((LN(2050/Assumptions!$C$7)+(Assumptions!$C$9-Assumptions!$C$11+0.2^2/2)*Assumptions!$C$10)/(0.2*SQRT(Assumptions!$C$10)))-Assumptions!$C$7*EXP(-Assumptions!$C$9*Assumptions!$C$10)*NORMSDIST(((LN(2050/Assumptions!$C$7)+(Assumptions!$C$9-Assumptions!$C$11+0.2^2/2)*Assumptions!$C$10)/(0.2*SQRT(Assumptions!$C$10)))-0.2*SQRT(Assumptions!$C$10)) -> 2.8390967 | F13: =2050*EXP(-Assumptions!$C$11*Assumptions!$C$10)*NORMSDIST((LN(2050/Assumptions!$C$7)+(Assumptions!$C$9-Assumptions!$C$11+0.25^2/2)*Assumptions!$C$10)/(0.25*SQRT(Assumptions!$C$10)))-Assumptions!$C$7*EXP(-Assumptions!$C$9*Assumptions!$C$10)*NORMSDIST(((LN(2050/Assumptions!$C$7)+(Assumptions!$C$9-Assumptions!$C$11+0.25^2/2)*Assumptions!$C$10)/(0.25*SQRT(Assumptions!$C$10)))-0.25*SQRT(Assumptions!$C$10)) -> 8.6323189 | G13: =2050*EXP(-Assumptions!$C$11*Assumptions!$C$10)*NORMSDIST((LN(2050/Assumptions!$C$7)+(Assumptions!$C$9-Assumptions!$C$11+0.3^2/2)*Assumptions!$C$10)/(0.3*SQRT(Assumptions!$C$10)))-Assumptions!$C$7*EXP(-Assumptions!$C$9*Assumptions!$C$10)*NORMSDIST(((LN(2050/Assumptions!$C$7)+(Assumptions!$C$9-Assumptions!$C$11+0.3^2/2)*Assumptions!$C$10)/(0.3*SQRT(Assumptions!$C$10)))-0.3*SQRT(Assumptions!$C$10)) -> 17.658071 | H13: =2050*EXP(-Assumptions!$C$11*Assumptions!$C$10)*NORMSDIST((LN(2050/Assumptions!$C$7)+(Assumptions!$C$9-Assumptions!$C$11+0.35^2/2)*Assumptions!$C$10)/(0.35*SQRT(Assumptions!$C$10)))-Assumptions!$C$7*EXP(-Assumptions!$C$9*Assumptions!$C$10)*NORMSDIST(((LN(2050/Assumptions!$C$7)+(Assumptions!$C$9-Assumptions!$C$11+0.35^2/2)*Assumptions!$C$10)/(0.35*SQRT(Assumptions!$C$10)))-0.35*SQRT(Assumptions!$C$10)) -> 29.31819 | I13: =2050*EXP(-Assumptions!$C$11*Assumptions!$C$10)*NORMSDIST((LN(2050/Assumptions!$C$7)+(Assumptions!$C$9-Assumptions!$C$11+0.4^2/2)*Assumptions!$C$10)/(0.4*SQRT(Assumptions!$C$10)))-Assumptions!$C$7*EXP(-Assumptions!$C$9*Assumptions!$C$10)*NORMSDIST(((LN(2050/Assumptions!$C$7)+(Assumptions!$C$9-Assumptions!$C$11+0.4^2/2)*Assumptions!$C$10)/(0.4*SQRT(Assumptions!$C$10)))-0.4*SQRT(Assumptions!$C$10)) -> 43.006886 | J13: =2050*EXP(-Assumptions!$C$11*Assumptions!$C$10)*NORMSDIST((LN(2050/Assumptions!$C$7)+(Assumptions!$C$9-Assumptions!$C$11+0.45^2/2)*Assumptions!$C$10)/(0.45*SQRT(Assumptions!$C$10)))-Assumptions!$C$7*EXP(-Assumptions!$C$9*Assumptions!$C$10)*NORMSDIST(((LN(2050/Assumptions!$C$7)+(Assumptions!$C$9-Assumptions!$C$11+0.45^2/2)*Assumptions!$C$10)/(0.45*SQRT(Assumptions!$C$10)))-0.45*SQRT(Assumptions!$C$10)) -> 58.236619 | K13: =2050*EXP(-Assumptions!$C$11*Assumptions!$C$10)*NORMSDIST((LN(2050/Assumptions!$C$7)+(Assumptions!$C$9-Assumptions!$C$11+0.5^2/2)*Assumptions!$C$10)/(0.5*SQRT(Assumptions!$C$10)))-Assumptions!$C$7*EXP(-Assumptions!$C$9*Assumptions!$C$10)*NORMSDIST(((LN(2050/Assumptions!$C$7)+(Assumptions!$C$9-Assumptions!$C$11+0.5^2/2)*Assumptions!$C$10)/(0.5*SQRT(Assumptions!$C$10)))-0.5*SQRT(Assumptions!$C$10)) -> 74.640094
B14: 2100 | C14: =2100*EXP(-Assumptions!$C$11*Assumptions!$C$10)*NORMSDIST((LN(2100/Assumptions!$C$7)+(Assumptions!$C$9-Assumptions!$C$11+0.1^2/2)*Assumptions!$C$10)/(0.1*SQRT(Assumptions!$C$10)))-Assumptions!$C$7*EXP(-Assumptions!$C$9*Assumptions!$C$10)*NORMSDIST(((LN(2100/Assumptions!$C$7)+(Assumptions!$C$9-Assumptions!$C$11+0.1^2/2)*Assumptions!$C$10)/(0.1*SQRT(Assumptions!$C$10)))-0.1*SQRT(Assumptions!$C$10)) -> 0.020097468 | D14: =2100*EXP(-Assumptions!$C$11*Assumptions!$C$10)*NORMSDIST((LN(2100/Assumptions!$C$7)+(Assumptions!$C$9-Assumptions!$C$11+0.15^2/2)*Assumptions!$C$10)/(0.15*SQRT(Assumptions!$C$10)))-Assumptions!$C$7*EXP(-Assumptions!$C$9*Assumptions!$C$10)*NORMSDIST(((LN(2100/Assumptions!$C$7)+(Assumptions!$C$9-Assumptions!$C$11+0.15^2/2)*Assumptions!$C$10)/(0.15*SQRT(Assumptions!$C$10)))-0.15*SQRT(Assumptions!$C$10)) -> 0.98101646 | E14: =2100*EXP(-Assumptions!$C$11*Assumptions!$C$10)*NORMSDIST((LN(2100/Assumptions!$C$7)+(Assumptions!$C$9-Assumptions!$C$11+0.2^2/2)*Assumptions!$C$10)/(0.2*SQRT(Assumptions!$C$10)))-Assumptions!$C$7*EXP(-Assumptions!$C$9*Assumptions!$C$10)*NORMSDIST(((LN(2100/Assumptions!$C$7)+(Assumptions!$C$9-Assumptions!$C$11+0.2^2/2)*Assumptions!$C$10)/(0.2*SQRT(Assumptions!$C$10)))-0.2*SQRT(Assumptions!$C$10)) -> 5.1963157 | F14: =2100*EXP(-Assumptions!$C$11*Assumptions!$C$10)*NORMSDIST((LN(2100/Assumptions!$C$7)+(Assumptions!$C$9-Assumptions!$C$11+0.25^2/2)*Assumptions!$C$10)/(0.25*SQRT(Assumptions!$C$10)))-Assumptions!$C$7*EXP(-Assumptions!$C$9*Assumptions!$C$10)*NORMSDIST(((LN(2100/Assumptions!$C$7)+(Assumptions!$C$9-Assumptions!$C$11+0.25^2/2)*Assumptions!$C$10)/(0.25*SQRT(Assumptions!$C$10)))-0.25*SQRT(Assumptions!$C$10)) -> 13.322473 | G14: =2100*EXP(-Assumptions!$C$11*Assumptions!$C$10)*NORMSDIST((LN(2100/Assumptions!$C$7)+(Assumptions!$C$9-Assumptions!$C$11+0.3^2/2)*Assumptions!$C$10)/(0.3*SQRT(Assumptions!$C$10)))-Assumptions!$C$7*EXP(-Assumptions!$C$9*Assumptions!$C$10)*NORMSDIST(((LN(2100/Assumptions!$C$7)+(Assumptions!$C$9-Assumptions!$C$11+0.3^2/2)*Assumptions!$C$10)/(0.3*SQRT(Assumptions!$C$10)))-0.3*SQRT(Assumptions!$C$10)) -> 24.704988 | H14: =2100*EXP(-Assumptions!$C$11*Assumptions!$C$10)*NORMSDIST((LN(2100/Assumptions!$C$7)+(Assumptions!$C$9-Assumptions!$C$11+0.35^2/2)*Assumptions!$C$10)/(0.35*SQRT(Assumptions!$C$10)))-Assumptions!$C$7*EXP(-Assumptions!$C$9*Assumptions!$C$10)*NORMSDIST(((LN(2100/Assumptions!$C$7)+(Assumptions!$C$9-Assumptions!$C$11+0.35^2/2)*Assumptions!$C$10)/(0.35*SQRT(Assumptions!$C$10)))-0.35*SQRT(Assumptions!$C$10)) -> 38.523484 | I14: =2100*EXP(-Assumptions!$C$11*Assumptions!$C$10)*NORMSDIST((LN(2100/Assumptions!$C$7)+(Assumptions!$C$9-Assumptions!$C$11+0.4^2/2)*Assumptions!$C$10)/(0.4*SQRT(Assumptions!$C$10)))-Assumptions!$C$7*EXP(-Assumptions!$C$9*Assumptions!$C$10)*NORMSDIST(((LN(2100/Assumptions!$C$7)+(Assumptions!$C$9-Assumptions!$C$11+0.4^2/2)*Assumptions!$C$10)/(0.4*SQRT(Assumptions!$C$10)))-0.4*SQRT(Assumptions!$C$10)) -> 54.122245 | J14: =2100*EXP(-Assumptions!$C$11*Assumptions!$C$10)*NORMSDIST((LN(2100/Assumptions!$C$7)+(Assumptions!$C$9-Assumptions!$C$11+0.45^2/2)*Assumptions!$C$10)/(0.45*SQRT(Assumptions!$C$10)))-Assumptions!$C$7*EXP(-Assumptions!$C$9*Assumptions!$C$10)*NORMSDIST(((LN(2100/Assumptions!$C$7)+(Assumptions!$C$9-Assumptions!$C$11+0.45^2/2)*Assumptions!$C$10)/(0.45*SQRT(Assumptions!$C$10)))-0.45*SQRT(Assumptions!$C$10)) -> 71.027322 | K14: =2100*EXP(-Assumptions!$C$11*Assumptions!$C$10)*NORMSDIST((LN(2100/Assumptions!$C$7)+(Assumptions!$C$9-Assumptions!$C$11+0.5^2/2)*Assumptions!$C$10)/(0.5*SQRT(Assumptions!$C$10)))-Assumptions!$C$7*EXP(-Assumptions!$C$9*Assumptions!$C$10)*NORMSDIST(((LN(2100/Assumptions!$C$7)+(Assumptions!$C$9-Assumptions!$C$11+0.5^2/2)*Assumptions!$C$10)/(0.5*SQRT(Assumptions!$C$10)))-0.5*SQRT(Assumptions!$C$10)) -> 88.902899
B15: 2150 | C15: =2150*EXP(-Assumptions!$C$11*Assumptions!$C$10)*NORMSDIST((LN(2150/Assumptions!$C$7)+(Assumptions!$C$9-Assumptions!$C$11+0.1^2/2)*Assumptions!$C$10)/(0.1*SQRT(Assumptions!$C$10)))-Assumptions!$C$7*EXP(-Assumptions!$C$9*Assumptions!$C$10)*NORMSDIST(((LN(2150/Assumptions!$C$7)+(Assumptions!$C$9-Assumptions!$C$11+0.1^2/2)*Assumptions!$C$10)/(0.1*SQRT(Assumptions!$C$10)))-0.1*SQRT(Assumptions!$C$10)) -> 0.10619767 | D15: =2150*EXP(-Assumptions!$C$11*Assumptions!$C$10)*NORMSDIST((LN(2150/Assumptions!$C$7)+(Assumptions!$C$9-Assumptions!$C$11+0.15^2/2)*Assumptions!$C$10)/(0.15*SQRT(Assumptions!$C$10)))-Assumptions!$C$7*EXP(-Assumptions!$C$9*Assumptions!$C$10)*NORMSDIST(((LN(2150/Assumptions!$C$7)+(Assumptions!$C$9-Assumptions!$C$11+0.15^2/2)*Assumptions!$C$10)/(0.15*SQRT(Assumptions!$C$10)))-0.15*SQRT(Assumptions!$C$10)) -> 2.2918916 | E15: =2150*EXP(-Assumptions!$C$11*Assumptions!$C$10)*NORMSDIST((LN(2150/Assumptions!$C$7)+(Assumptions!$C$9-Assumptions!$C$11+0.2^2/2)*Assumptions!$C$10)/(0.2*SQRT(Assumptions!$C$10)))-Assumptions!$C$7*EXP(-Assumptions!$C$9*Assumptions!$C$10)*NORMSDIST(((LN(2150/Assumptions!$C$7)+(Assumptions!$C$9-Assumptions!$C$11+0.2^2/2)*Assumptions!$C$10)/(0.2*SQRT(Assumptions!$C$10)))-0.2*SQRT(Assumptions!$C$10)) -> 8.9717988 | F15: =2150*EXP(-Assumptions!$C$11*Assumptions!$C$10)*NORMSDIST((LN(2150/Assumptions!$C$7)+(Assumptions!$C$9-Assumptions!$C$11+0.25^2/2)*Assumptions!$C$10)/(0.25*SQRT(Assumptions!$C$10)))-Assumptions!$C$7*EXP(-Assumptions!$C$9*Assumptions!$C$10)*NORMSDIST(((LN(2150/Assumptions!$C$7)+(Assumptions!$C$9-Assumptions!$C$11+0.25^2/2)*Assumptions!$C$10)/(0.25*SQRT(Assumptions!$C$10)))-0.25*SQRT(Assumptions!$C$10)) -> 19.808538 | G15: =2150*EXP(-Assumptions!$C$11*Assumptions!$C$10)*NORMSDIST((LN(2150/Assumptions!$C$7)+(Assumptions!$C$9-Assumptions!$C$11+0.3^2/2)*Assumptions!$C$10)/(0.3*SQRT(Assumptions!$C$10)))-Assumptions!$C$7*EXP(-Assumptions!$C$9*Assumptions!$C$10)*NORMSDIST(((LN(2150/Assumptions!$C$7)+(Assumptions!$C$9-Assumptions!$C$11+0.3^2/2)*Assumptions!$C$10)/(0.3*SQRT(Assumptions!$C$10)))-0.3*SQRT(Assumptions!$C$10)) -> 33.674111 | H15: =2150*EXP(-Assumptions!$C$11*Assumptions!$C$10)*NORMSDIST((LN(2150/Assumptions!$C$7)+(Assumptions!$C$9-Assumptions!$C$11+0.35^2/2)*Assumptions!$C$10)/(0.35*SQRT(Assumptions!$C$10)))-Assumptions!$C$7*EXP(-Assumptions!$C$9*Assumptions!$C$10)*NORMSDIST(((LN(2150/Assumptions!$C$7)+(Assumptions!$C$9-Assumptions!$C$11+0.35^2/2)*Assumptions!$C$10)/(0.35*SQRT(Assumptions!$C$10)))-0.35*SQRT(Assumptions!$C$10)) -> 49.644672 | I15: =2150*EXP(-Assumptions!$C$11*Assumptions!$C$10)*NORMSDIST((LN(2150/Assumptions!$C$7)+(Assumptions!$C$9-Assumptions!$C$11+0.4^2/2)*Assumptions!$C$10)/(0.4*SQRT(Assumptions!$C$10)))-Assumptions!$C$7*EXP(-Assumptions!$C$9*Assumptions!$C$10)*NORMSDIST(((LN(2150/Assumptions!$C$7)+(Assumptions!$C$9-Assumptions!$C$11+0.4^2/2)*Assumptions!$C$10)/(0.4*SQRT(Assumptions!$C$10)))-0.4*SQRT(Assumptions!$C$10)) -> 67.085849 | J15: =2150*EXP(-Assumptions!$C$11*Assumptions!$C$10)*NORMSDIST((LN(2150/Assumptions!$C$7)+(Assumptions!$C$9-Assumptions!$C$11+0.45^2/2)*Assumptions!$C$10)/(0.45*SQRT(Assumptions!$C$10)))-Assumptions!$C$7*EXP(-Assumptions!$C$9*Assumptions!$C$10)*NORMSDIST(((LN(2150/Assumptions!$C$7)+(Assumptions!$C$9-Assumptions!$C$11+0.45^2/2)*Assumptions!$C$10)/(0.45*SQRT(Assumptions!$C$10)))-0.45*SQRT(Assumptions!$C$10)) -> 85.573806 | K15: =2150*EXP(-Assumptions!$C$11*Assumptions!$C$10)*NORMSDIST((LN(2150/Assumptions!$C$7)+(Assumptions!$C$9-Assumptions!$C$11+0.5^2/2)*Assumptions!$C$10)/(0.5*SQRT(Assumptions!$C$10)))-Assumptions!$C$7*EXP(-Assumptions!$C$9*Assumptions!$C$10)*NORMSDIST(((LN(2150/Assumptions!$C$7)+(Assumptions!$C$9-Assumptions!$C$11+0.5^2/2)*Assumptions!$C$10)/(0.5*SQRT(Assumptions!$C$10)))-0.5*SQRT(Assumptions!$C$10)) -> 104.82203
B16: 2200 | C16: =2200*EXP(-Assumptions!$C$11*Assumptions!$C$10)*NORMSDIST((LN(2200/Assumptions!$C$7)+(Assumptions!$C$9-Assumptions!$C$11+0.1^2/2)*Assumptions!$C$10)/(0.1*SQRT(Assumptions!$C$10)))-Assumptions!$C$7*EXP(-Assumptions!$C$9*Assumptions!$C$10)*NORMSDIST(((LN(2200/Assumptions!$C$7)+(Assumptions!$C$9-Assumptions!$C$11+0.1^2/2)*Assumptions!$C$10)/(0.1*SQRT(Assumptions!$C$10)))-0.1*SQRT(Assumptions!$C$10)) -> 0.44863746 | D16: =2200*EXP(-Assumptions!$C$11*Assumptions!$C$10)*NORMSDIST((LN(2200/Assumptions!$C$7)+(Assumptions!$C$9-Assumptions!$C$11+0.15^2/2)*Assumptions!$C$10)/(0.15*SQRT(Assumptions!$C$10)))-Assumptions!$C$7*EXP(-Assumptions!$C$9*Assumptions!$C$10)*NORMSDIST(((LN(2200/Assumptions!$C$7)+(Assumptions!$C$9-Assumptions!$C$11+0.15^2/2)*Assumptions!$C$10)/(0.15*SQRT(Assumptions!$C$10)))-0.15*SQRT(Assumptions!$C$10)) -> 4.8634188 | E16: =2200*EXP(-Assumptions!$C$11*Assumptions!$C$10)*NORMSDIST((LN(2200/Assumptions!$C$7)+(Assumptions!$C$9-Assumptions!$C$11+0.2^2/2)*Assumptions!$C$10)/(0.2*SQRT(Assumptions!$C$10)))-Assumptions!$C$7*EXP(-Assumptions!$C$9*Assumptions!$C$10)*NORMSDIST(((LN(2200/Assumptions!$C$7)+(Assumptions!$C$9-Assumptions!$C$11+0.2^2/2)*Assumptions!$C$10)/(0.2*SQRT(Assumptions!$C$10)))-0.2*SQRT(Assumptions!$C$10)) -> 14.68487 | F16: =2200*EXP(-Assumptions!$C$11*Assumptions!$C$10)*NORMSDIST((LN(2200/Assumptions!$C$7)+(Assumptions!$C$9-Assumptions!$C$11+0.25^2/2)*Assumptions!$C$10)/(0.25*SQRT(Assumptions!$C$10)))-Assumptions!$C$7*EXP(-Assumptions!$C$9*Assumptions!$C$10)*NORMSDIST(((LN(2200/Assumptions!$C$7)+(Assumptions!$C$9-Assumptions!$C$11+0.25^2/2)*Assumptions!$C$10)/(0.25*SQRT(Assumptions!$C$10)))-0.25*SQRT(Assumptions!$C$10)) -> 28.461581 | G16: =2200*EXP(-Assumptions!$C$11*Assumptions!$C$10)*NORMSDIST((LN(2200/Assumptions!$C$7)+(Assumptions!$C$9-Assumptions!$C$11+0.3^2/2)*Assumptions!$C$10)/(0.3*SQRT(Assumptions!$C$10)))-Assumptions!$C$7*EXP(-Assumptions!$C$9*Assumptions!$C$10)*NORMSDIST(((LN(2200/Assumptions!$C$7)+(Assumptions!$C$9-Assumptions!$C$11+0.3^2/2)*Assumptions!$C$10)/(0.3*SQRT(Assumptions!$C$10)))-0.3*SQRT(Assumptions!$C$10)) -> 44.810439 | H16: =2200*EXP(-Assumptions!$C$11*Assumptions!$C$10)*NORMSDIST((LN(2200/Assumptions!$C$7)+(Assumptions!$C$9-Assumptions!$C$11+0.35^2/2)*Assumptions!$C$10)/(0.35*SQRT(Assumptions!$C$10)))-Assumptions!$C$7*EXP(-Assumptions!$C$9*Assumptions!$C$10)*NORMSDIST(((LN(2200/Assumptions!$C$7)+(Assumptions!$C$9-Assumptions!$C$11+0.35^2/2)*Assumptions!$C$10)/(0.35*SQRT(Assumptions!$C$10)))-0.35*SQRT(Assumptions!$C$10)) -> 62.83907 | I16: =2200*EXP(-Assumptions!$C$11*Assumptions!$C$10)*NORMSDIST((LN(2200/Assumptions!$C$7)+(Assumptions!$C$9-Assumptions!$C$11+0.4^2/2)*Assumptions!$C$10)/(0.4*SQRT(Assumptions!$C$10)))-Assumptions!$C$7*EXP(-Assumptions!$C$9*Assumptions!$C$10)*NORMSDIST(((LN(2200/Assumptions!$C$7)+(Assumptions!$C$9-Assumptions!$C$11+0.4^2/2)*Assumptions!$C$10)/(0.4*SQRT(Assumptions!$C$10)))-0.4*SQRT(Assumptions!$C$10)) -> 81.996767 | J16: =2200*EXP(-Assumptions!$C$11*Assumptions!$C$10)*NORMSDIST((LN(2200/Assumptions!$C$7)+(Assumptions!$C$9-Assumptions!$C$11+0.45^2/2)*Assumptions!$C$10)/(0.45*SQRT(Assumptions!$C$10)))-Assumptions!$C$7*EXP(-Assumptions!$C$9*Assumptions!$C$10)*NORMSDIST(((LN(2200/Assumptions!$C$7)+(Assumptions!$C$9-Assumptions!$C$11+0.45^2/2)*Assumptions!$C$10)/(0.45*SQRT(Assumptions!$C$10)))-0.45*SQRT(Assumptions!$C$10)) -> 101.93659 | K16: =2200*EXP(-Assumptions!$C$11*Assumptions!$C$10)*NORMSDIST((LN(2200/Assumptions!$C$7)+(Assumptions!$C$9-Assumptions!$C$11+0.5^2/2)*Assumptions!$C$10)/(0.5*SQRT(Assumptions!$C$10)))-Assumptions!$C$7*EXP(-Assumptions!$C$9*Assumptions!$C$10)*NORMSDIST(((LN(2200/Assumptions!$C$7)+(Assumptions!$C$9-Assumptions!$C$11+0.5^2/2)*Assumptions!$C$10)/(0.5*SQRT(Assumptions!$C$10)))-0.5*SQRT(Assumptions!$C$10)) -> 122.43222
B17: 2250 | C17: =2250*EXP(-Assumptions!$C$11*Assumptions!$C$10)*NORMSDIST((LN(2250/Assumptions!$C$7)+(Assumptions!$C$9-Assumptions!$C$11+0.1^2/2)*Assumptions!$C$10)/(0.1*SQRT(Assumptions!$C$10)))-Assumptions!$C$7*EXP(-Assumptions!$C$9*Assumptions!$C$10)*NORMSDIST(((LN(2250/Assumptions!$C$7)+(Assumptions!$C$9-Assumptions!$C$11+0.1^2/2)*Assumptions!$C$10)/(0.1*SQRT(Assumptions!$C$10)))-0.1*SQRT(Assumptions!$C$10)) -> 1.5454667 | D17: =2250*EXP(-Assumptions!$C$11*Assumptions!$C$10)*NORMSDIST((LN(2250/Assumptions!$C$7)+(Assumptions!$C$9-Assumptions!$C$11+0.15^2/2)*Assumptions!$C$10)/(0.15*SQRT(Assumptions!$C$10)))-Assumptions!$C$7*EXP(-Assumptions!$C$9*Assumptions!$C$10)*NORMSDIST(((LN(2250/Assumptions!$C$7)+(Assumptions!$C$9-Assumptions!$C$11+0.15^2/2)*Assumptions!$C$10)/(0.15*SQRT(Assumptions!$C$10)))-0.15*SQRT(Assumptions!$C$10)) -> 9.4541678 | E17: =2250*EXP(-Assumptions!$C$11*Assumptions!$C$10)*NORMSDIST((LN(2250/Assumptions!$C$7)+(Assumptions!$C$9-Assumptions!$C$11+0.2^2/2)*Assumptions!$C$10)/(0.2*SQRT(Assumptions!$C$10)))-Assumptions!$C$7*EXP(-Assumptions!$C$9*Assumptions!$C$10)*NORMSDIST(((LN(2250/Assumptions!$C$7)+(Assumptions!$C$9-Assumptions!$C$11+0.2^2/2)*Assumptions!$C$10)/(0.2*SQRT(Assumptions!$C$10)))-0.2*SQRT(Assumptions!$C$10)) -> 22.891 | F17: =2250*EXP(-Assumptions!$C$11*Assumptions!$C$10)*NORMSDIST((LN(2250/Assumptions!$C$7)+(Assumptions!$C$9-Assumptions!$C$11+0.25^2/2)*Assumptions!$C$10)/(0.25*SQRT(Assumptions!$C$10)))-Assumptions!$C$7*EXP(-Assumptions!$C$9*Assumptions!$C$10)*NORMSDIST(((LN(2250/Assumptions!$C$7)+(Assumptions!$C$9-Assumptions!$C$11+0.25^2/2)*Assumptions!$C$10)/(0.25*SQRT(Assumptions!$C$10)))-0.25*SQRT(Assumptions!$C$10)) -> 39.63118 | G17: =2250*EXP(-Assumptions!$C$11*Assumptions!$C$10)*NORMSDIST((LN(2250/Assumptions!$C$7)+(Assumptions!$C$9-Assumptions!$C$11+0.3^2/2)*Assumptions!$C$10)/(0.3*SQRT(Assumptions!$C$10)))-Assumptions!$C$7*EXP(-Assumptions!$C$9*Assumptions!$C$10)*NORMSDIST(((LN(2250/Assumptions!$C$7)+(Assumptions!$C$9-Assumptions!$C$11+0.3^2/2)*Assumptions!$C$10)/(0.3*SQRT(Assumptions!$C$10)))-0.3*SQRT(Assumptions!$C$10)) -> 58.326541 | H17: =2250*EXP(-Assumptions!$C$11*Assumptions!$C$10)*NORMSDIST((LN(2250/Assumptions!$C$7)+(Assumptions!$C$9-Assumptions!$C$11+0.35^2/2)*Assumptions!$C$10)/(0.35*SQRT(Assumptions!$C$10)))-Assumptions!$C$7*EXP(-Assumptions!$C$9*Assumptions!$C$10)*NORMSDIST(((LN(2250/Assumptions!$C$7)+(Assumptions!$C$9-Assumptions!$C$11+0.35^2/2)*Assumptions!$C$10)/(0.35*SQRT(Assumptions!$C$10)))-0.35*SQRT(Assumptions!$C$10)) -> 78.234225 | I17: =2250*EXP(-Assumptions!$C$11*Assumptions!$C$10)*NORMSDIST((LN(2250/Assumptions!$C$7)+(Assumptions!$C$9-Assumptions!$C$11+0.4^2/2)*Assumptions!$C$10)/(0.4*SQRT(Assumptions!$C$10)))-Assumptions!$C$7*EXP(-Assumptions!$C$9*Assumptions!$C$10)*NORMSDIST(((LN(2250/Assumptions!$C$7)+(Assumptions!$C$9-Assumptions!$C$11+0.4^2/2)*Assumptions!$C$10)/(0.4*SQRT(Assumptions!$C$10)))-0.4*SQRT(Assumptions!$C$10)) -> 98.929776 | J17: =2250*EXP(-Assumptions!$C$11*Assumptions!$C$10)*NORMSDIST((LN(2250/Assumptions!$C$7)+(Assumptions!$C$9-Assumptions!$C$11+0.45^2/2)*Assumptions!$C$10)/(0.45*SQRT(Assumptions!$C$10)))-Assumptions!$C$7*EXP(-Assumptions!$C$9*Assumptions!$C$10)*NORMSDIST(((LN(2250/Assumptions!$C$7)+(Assumptions!$C$9-Assumptions!$C$11+0.45^2/2)*Assumptions!$C$10)/(0.45*SQRT(Assumptions!$C$10)))-0.45*SQRT(Assumptions!$C$10)) -> 120.15711 | K17: =2250*EXP(-Assumptions!$C$11*Assumptions!$C$10)*NORMSDIST((LN(2250/Assumptions!$C$7)+(Assumptions!$C$9-Assumptions!$C$11+0.5^2/2)*Assumptions!$C$10)/(0.5*SQRT(Assumptions!$C$10)))-Assumptions!$C$7*EXP(-Assumptions!$C$9*Assumptions!$C$10)*NORMSDIST(((LN(2250/Assumptions!$C$7)+(Assumptions!$C$9-Assumptions!$C$11+0.5^2/2)*Assumptions!$C$10)/(0.5*SQRT(Assumptions!$C$10)))-0.5*SQRT(Assumptions!$C$10)) -> 141.75345
B18: 2300 | C18: =2300*EXP(-Assumptions!$C$11*Assumptions!$C$10)*NORMSDIST((LN(2300/Assumptions!$C$7)+(Assumptions!$C$9-Assumptions!$C$11+0.1^2/2)*Assumptions!$C$10)/(0.1*SQRT(Assumptions!$C$10)))-Assumptions!$C$7*EXP(-Assumptions!$C$9*Assumptions!$C$10)*NORMSDIST(((LN(2300/Assumptions!$C$7)+(Assumptions!$C$9-Assumptions!$C$11+0.1^2/2)*Assumptions!$C$10)/(0.1*SQRT(Assumptions!$C$10)))-0.1*SQRT(Assumptions!$C$10)) -> 4.4255121 | D18: =2300*EXP(-Assumptions!$C$11*Assumptions!$C$10)*NORMSDIST((LN(2300/Assumptions!$C$7)+(Assumptions!$C$9-Assumptions!$C$11+0.15^2/2)*Assumptions!$C$10)/(0.15*SQRT(Assumptions!$C$10)))-Assumptions!$C$7*EXP(-Assumptions!$C$9*Assumptions!$C$10)*NORMSDIST(((LN(2300/Assumptions!$C$7)+(Assumptions!$C$9-Assumptions!$C$11+0.15^2/2)*Assumptions!$C$10)/(0.15*SQRT(Assumptions!$C$10)))-0.15*SQRT(Assumptions!$C$10)) -> 16.972927 | E18: =2300*EXP(-Assumptions!$C$11*Assumptions!$C$10)*NORMSDIST((LN(2300/Assumptions!$C$7)+(Assumptions!$C$9-Assumptions!$C$11+0.2^2/2)*Assumptions!$C$10)/(0.2*SQRT(Assumptions!$C$10)))-Assumptions!$C$7*EXP(-Assumptions!$C$9*Assumptions!$C$10)*NORMSDIST(((LN(2300/Assumptions!$C$7)+(Assumptions!$C$9-Assumptions!$C$11+0.2^2/2)*Assumptions!$C$10)/(0.2*SQRT(Assumptions!$C$10)))-0.2*SQRT(Assumptions!$C$10)) -> 34.129749 | F18: =2300*EXP(-Assumptions!$C$11*Assumptions!$C$10)*NORMSDIST((LN(2300/Assumptions!$C$7)+(Assumptions!$C$9-Assumptions!$C$11+0.25^2/2)*Assumptions!$C$10)/(0.25*SQRT(Assumptions!$C$10)))-Assumptions!$C$7*EXP(-Assumptions!$C$9*Assumptions!$C$10)*NORMSDIST(((LN(2300/Assumptions!$C$7)+(Assumptions!$C$9-Assumptions!$C$11+0.25^2/2)*Assumptions!$C$10)/(0.25*SQRT(Assumptions!$C$10)))-0.25*SQRT(Assumptions!$C$10)) -> 53.62048 | G18: =2300*EXP(-Assumptions!$C$11*Assumptions!$C$10)*NORMSDIST((LN(2300/Assumptions!$C$7)+(Assumptions!$C$9-Assumptions!$C$11+0.3^2/2)*Assumptions!$C$10)/(0.3*SQRT(Assumptions!$C$10)))-Assumptions!$C$7*EXP(-Assumptions!$C$9*Assumptions!$C$10)*NORMSDIST(((LN(2300/Assumptions!$C$7)+(Assumptions!$C$9-Assumptions!$C$11+0.3^2/2)*Assumptions!$C$10)/(0.3*SQRT(Assumptions!$C$10)))-0.3*SQRT(Assumptions!$C$10)) -> 74.392085 | H18: =2300*EXP(-Assumptions!$C$11*Assumptions!$C$10)*NORMSDIST((LN(2300/Assumptions!$C$7)+(Assumptions!$C$9-Assumptions!$C$11+0.35^2/2)*Assumptions!$C$10)/(0.35*SQRT(Assumptions!$C$10)))-Assumptions!$C$7*EXP(-Assumptions!$C$9*Assumptions!$C$10)*NORMSDIST(((LN(2300/Assumptions!$C$7)+(Assumptions!$C$9-Assumptions!$C$11+0.35^2/2)*Assumptions!$C$10)/(0.35*SQRT(Assumptions!$C$10)))-0.35*SQRT(Assumptions!$C$10)) -> 95.923927 | I18: =2300*EXP(-Assumptions!$C$11*Assumptions!$C$10)*NORMSDIST((LN(2300/Assumptions!$C$7)+(Assumptions!$C$9-Assumptions!$C$11+0.4^2/2)*Assumptions!$C$10)/(0.4*SQRT(Assumptions!$C$10)))-Assumptions!$C$7*EXP(-Assumptions!$C$9*Assumptions!$C$10)*NORMSDIST(((LN(2300/Assumptions!$C$7)+(Assumptions!$C$9-Assumptions!$C$11+0.4^2/2)*Assumptions!$C$10)/(0.4*SQRT(Assumptions!$C$10)))-0.4*SQRT(Assumptions!$C$10)) -> 117.93418 | J18: =2300*EXP(-Assumptions!$C$11*Assumptions!$C$10)*NORMSDIST((LN(2300/Assumptions!$C$7)+(Assumptions!$C$9-Assumptions!$C$11+0.45^2/2)*Assumptions!$C$10)/(0.45*SQRT(Assumptions!$C$10)))-Assumptions!$C$7*EXP(-Assumptions!$C$9*Assumptions!$C$10)*NORMSDIST(((LN(2300/Assumptions!$C$7)+(Assumptions!$C$9-Assumptions!$C$11+0.45^2/2)*Assumptions!$C$10)/(0.45*SQRT(Assumptions!$C$10)))-0.45*SQRT(Assumptions!$C$10)) -> 140.25777 | K18: =2300*EXP(-Assumptions!$C$11*Assumptions!$C$10)*NORMSDIST((LN(2300/Assumptions!$C$7)+(Assumptions!$C$9-Assumptions!$C$11+0.5^2/2)*Assumptions!$C$10)/(0.5*SQRT(Assumptions!$C$10)))-Assumptions!$C$7*EXP(-Assumptions!$C$9*Assumptions!$C$10)*NORMSDIST(((LN(2300/Assumptions!$C$7)+(Assumptions!$C$9-Assumptions!$C$11+0.5^2/2)*Assumptions!$C$10)/(0.5*SQRT(Assumptions!$C$10)))-0.5*SQRT(Assumptions!$C$10)) -> 162.7914
B19: 2350 | C19: =2350*EXP(-Assumptions!$C$11*Assumptions!$C$10)*NORMSDIST((LN(2350/Assumptions!$C$7)+(Assumptions!$C$9-Assumptions!$C$11+0.1^2/2)*Assumptions!$C$10)/(0.1*SQRT(Assumptions!$C$10)))-Assumptions!$C$7*EXP(-Assumptions!$C$9*Assumptions!$C$10)*NORMSDIST(((LN(2350/Assumptions!$C$7)+(Assumptions!$C$9-Assumptions!$C$11+0.1^2/2)*Assumptions!$C$10)/(0.1*SQRT(Assumptions!$C$10)))-0.1*SQRT(Assumptions!$C$10)) -> 10.735678 | D19: =2350*EXP(-Assumptions!$C$11*Assumptions!$C$10)*NORMSDIST((LN(2350/Assumptions!$C$7)+(Assumptions!$C$9-Assumptions!$C$11+0.15^2/2)*Assumptions!$C$10)/(0.15*SQRT(Assumptions!$C$10)))-Assumptions!$C$7*EXP(-Assumptions!$C$9*Assumptions!$C$10)*NORMSDIST(((LN(2350/Assumptions!$C$7)+(Assumptions!$C$9-Assumptions!$C$11+0.15^2/2)*Assumptions!$C$10)/(0.15*SQRT(Assumptions!$C$10)))-0.15*SQRT(Assumptions!$C$10)) -> 28.359048 | E19: =2350*EXP(-Assumptions!$C$11*Assumptions!$C$10)*NORMSDIST((LN(2350/Assumptions!$C$7)+(Assumptions!$C$9-Assumptions!$C$11+0.2^2/2)*Assumptions!$C$10)/(0.2*SQRT(Assumptions!$C$10)))-Assumptions!$C$7*EXP(-Assumptions!$C$9*Assumptions!$C$10)*NORMSDIST(((LN(2350/Assumptions!$C$7)+(Assumptions!$C$9-Assumptions!$C$11+0.2^2/2)*Assumptions!$C$10)/(0.2*SQRT(Assumptions!$C$10)))-0.2*SQRT(Assumptions!$C$10)) -> 48.868265 | F19: =2350*EXP(-Assumptions!$C$11*Assumptions!$C$10)*NORMSDIST((LN(2350/Assumptions!$C$7)+(Assumptions!$C$9-Assumptions!$C$11+0.25^2/2)*Assumptions!$C$10)/(0.25*SQRT(Assumptions!$C$10)))-Assumptions!$C$7*EXP(-Assumptions!$C$9*Assumptions!$C$10)*NORMSDIST(((LN(2350/Assumptions!$C$7)+(Assumptions!$C$9-Assumptions!$C$11+0.25^2/2)*Assumptions!$C$10)/(0.25*SQRT(Assumptions!$C$10)))-0.25*SQRT(Assumptions!$C$10)) -> 70.664858 | G19: =2350*EXP(-Assumptions!$C$11*Assumptions!$C$10)*NORMSDIST((LN(2350/Assumptions!$C$7)+(Assumptions!$C$9-Assumptions!$C$11+0.3^2/2)*Assumptions!$C$10)/(0.3*SQRT(Assumptions!$C$10)))-Assumptions!$C$7*EXP(-Assumptions!$C$9*Assumptions!$C$10)*NORMSDIST(((LN(2350/Assumptions!$C$7)+(Assumptions!$C$9-Assumptions!$C$11+0.3^2/2)*Assumptions!$C$10)/(0.3*SQRT(Assumptions!$C$10)))-0.3*SQRT(Assumptions!$C$10)) -> 93.126379 | H19: =2350*EXP(-Assumptions!$C$11*Assumptions!$C$10)*NORMSDIST((LN(2350/Assumptions!$C$7)+(Assumptions!$C$9-Assumptions!$C$11+0.35^2/2)*Assumptions!$C$10)/(0.35*SQRT(Assumptions!$C$10)))-Assumptions!$C$7*EXP(-Assumptions!$C$9*Assumptions!$C$10)*NORMSDIST(((LN(2350/Assumptions!$C$7)+(Assumptions!$C$9-Assumptions!$C$11+0.35^2/2)*Assumptions!$C$10)/(0.35*SQRT(Assumptions!$C$10)))-0.35*SQRT(Assumptions!$C$10)) -> 115.96606 | I19: =2350*EXP(-Assumptions!$C$11*Assumptions!$C$10)*NORMSDIST((LN(2350/Assumptions!$C$7)+(Assumptions!$C$9-Assumptions!$C$11+0.4^2/2)*Assumptions!$C$10)/(0.4*SQRT(Assumptions!$C$10)))-Assumptions!$C$7*EXP(-Assumptions!$C$9*Assumptions!$C$10)*NORMSDIST(((LN(2350/Assumptions!$C$7)+(Assumptions!$C$9-Assumptions!$C$11+0.4^2/2)*Assumptions!$C$10)/(0.4*SQRT(Assumptions!$C$10)))-0.4*SQRT(Assumptions!$C$10)) -> 139.03369 | J19: =2350*EXP(-Assumptions!$C$11*Assumptions!$C$10)*NORMSDIST((LN(2350/Assumptions!$C$7)+(Assumptions!$C$9-Assumptions!$C$11+0.45^2/2)*Assumptions!$C$10)/(0.45*SQRT(Assumptions!$C$10)))-Assumptions!$C$7*EXP(-Assumptions!$C$9*Assumptions!$C$10)*NORMSDIST(((LN(2350/Assumptions!$C$7)+(Assumptions!$C$9-Assumptions!$C$11+0.45^2/2)*Assumptions!$C$10)/(0.45*SQRT(Assumptions!$C$10)))-0.45*SQRT(Assumptions!$C$10)) -> 162.24248 | K19: =2350*EXP(-Assumptions!$C$11*Assumptions!$C$10)*NORMSDIST((LN(2350/Assumptions!$C$7)+(Assumptions!$C$9-Assumptions!$C$11+0.5^2/2)*Assumptions!$C$10)/(0.5*SQRT(Assumptions!$C$10)))-Assumptions!$C$7*EXP(-Assumptions!$C$9*Assumptions!$C$10)*NORMSDIST(((LN(2350/Assumptions!$C$7)+(Assumptions!$C$9-Assumptions!$C$11+0.5^2/2)*Assumptions!$C$10)/(0.5*SQRT(Assumptions!$C$10)))-0.5*SQRT(Assumptions!$C$10)) -> 185.53824
B20: 2400 | C20: =2400*EXP(-Assumptions!$C$11*Assumptions!$C$10)*NORMSDIST((LN(2400/Assumptions!$C$7)+(Assumptions!$C$9-Assumptions!$C$11+0.1^2/2)*Assumptions!$C$10)/(0.1*SQRT(Assumptions!$C$10)))-Assumptions!$C$7*EXP(-Assumptions!$C$9*Assumptions!$C$10)*NORMSDIST(((LN(2400/Assumptions!$C$7)+(Assumptions!$C$9-Assumptions!$C$11+0.1^2/2)*Assumptions!$C$10)/(0.1*SQRT(Assumptions!$C$10)))-0.1*SQRT(Assumptions!$C$10)) -> 22.480419 | D20: =2400*EXP(-Assumptions!$C$11*Assumptions!$C$10)*NORMSDIST((LN(2400/Assumptions!$C$7)+(Assumptions!$C$9-Assumptions!$C$11+0.15^2/2)*Assumptions!$C$10)/(0.15*SQRT(Assumptions!$C$10)))-Assumptions!$C$7*EXP(-Assumptions!$C$9*Assumptions!$C$10)*NORMSDIST(((LN(2400/Assumptions!$C$7)+(Assumptions!$C$9-Assumptions!$C$11+0.15^2/2)*Assumptions!$C$10)/(0.15*SQRT(Assumptions!$C$10)))-0.15*SQRT(Assumptions!$C$10)) -> 44.424337 | E20: =2400*EXP(-Assumptions!$C$11*Assumptions!$C$10)*NORMSDIST((LN(2400/Assumptions!$C$7)+(Assumptions!$C$9-Assumptions!$C$11+0.2^2/2)*Assumptions!$C$10)/(0.2*SQRT(Assumptions!$C$10)))-Assumptions!$C$7*EXP(-Assumptions!$C$9*Assumptions!$C$10)*NORMSDIST(((LN(2400/Assumptions!$C$7)+(Assumptions!$C$9-Assumptions!$C$11+0.2^2/2)*Assumptions!$C$10)/(0.2*SQRT(Assumptions!$C$10)))-0.2*SQRT(Assumptions!$C$10)) -> 67.450955 | F20: =2400*EXP(-Assumptions!$C$11*Assumptions!$C$10)*NORMSDIST((LN(2400/Assumptions!$C$7)+(Assumptions!$C$9-Assumptions!$C$11+0.25^2/2)*Assumptions!$C$10)/(0.25*SQRT(Assumptions!$C$10)))-Assumptions!$C$7*EXP(-Assumptions!$C$9*Assumptions!$C$10)*NORMSDIST(((LN(2400/Assumptions!$C$7)+(Assumptions!$C$9-Assumptions!$C$11+0.25^2/2)*Assumptions!$C$10)/(0.25*SQRT(Assumptions!$C$10)))-0.25*SQRT(Assumptions!$C$10)) -> 90.916758 | G20: =2400*EXP(-Assumptions!$C$11*Assumptions!$C$10)*NORMSDIST((LN(2400/Assumptions!$C$7)+(Assumptions!$C$9-Assumptions!$C$11+0.3^2/2)*Assumptions!$C$10)/(0.3*SQRT(Assumptions!$C$10)))-Assumptions!$C$7*EXP(-Assumptions!$C$9*Assumptions!$C$10)*NORMSDIST(((LN(2400/Assumptions!$C$7)+(Assumptions!$C$9-Assumptions!$C$11+0.3^2/2)*Assumptions!$C$10)/(0.3*SQRT(Assumptions!$C$10)))-0.3*SQRT(Assumptions!$C$10)) -> 114.59437 | H20: =2400*EXP(-Assumptions!$C$11*Assumptions!$C$10)*NORMSDIST((LN(2400/Assumptions!$C$7)+(Assumptions!$C$9-Assumptions!$C$11+0.35^2/2)*Assumptions!$C$10)/(0.35*SQRT(Assumptions!$C$10)))-Assumptions!$C$7*EXP(-Assumptions!$C$9*Assumptions!$C$10)*NORMSDIST(((LN(2400/Assumptions!$C$7)+(Assumptions!$C$9-Assumptions!$C$11+0.35^2/2)*Assumptions!$C$10)/(0.35*SQRT(Assumptions!$C$10)))-0.35*SQRT(Assumptions!$C$10)) -> 138.38223 | I20: =2400*EXP(-Assumptions!$C$11*Assumptions!$C$10)*NORMSDIST((LN(2400/Assumptions!$C$7)+(Assumptions!$C$9-Assumptions!$C$11+0.4^2/2)*Assumptions!$C$10)/(0.4*SQRT(Assumptions!$C$10)))-Assumptions!$C$7*EXP(-Assumptions!$C$9*Assumptions!$C$10)*NORMSDIST(((LN(2400/Assumptions!$C$7)+(Assumptions!$C$9-Assumptions!$C$11+0.4^2/2)*Assumptions!$C$10)/(0.4*SQRT(Assumptions!$C$10)))-0.4*SQRT(Assumptions!$C$10)) -> 162.22715 | J20: =2400*EXP(-Assumptions!$C$11*Assumptions!$C$10)*NORMSDIST((LN(2400/Assumptions!$C$7)+(Assumptions!$C$9-Assumptions!$C$11+0.45^2/2)*Assumptions!$C$10)/(0.45*SQRT(Assumptions!$C$10)))-Assumptions!$C$7*EXP(-Assumptions!$C$9*Assumptions!$C$10)*NORMSDIST(((LN(2400/Assumptions!$C$7)+(Assumptions!$C$9-Assumptions!$C$11+0.45^2/2)*Assumptions!$C$10)/(0.45*SQRT(Assumptions!$C$10)))-0.45*SQRT(Assumptions!$C$10)) -> 186.09776 | K20: =2400*EXP(-Assumptions!$C$11*Assumptions!$C$10)*NORMSDIST((LN(2400/Assumptions!$C$7)+(Assumptions!$C$9-Assumptions!$C$11+0.5^2/2)*Assumptions!$C$10)/(0.5*SQRT(Assumptions!$C$10)))-Assumptions!$C$7*EXP(-Assumptions!$C$9*Assumptions!$C$10)*NORMSDIST(((LN(2400/Assumptions!$C$7)+(Assumptions!$C$9-Assumptions!$C$11+0.5^2/2)*Assumptions!$C$10)/(0.5*SQRT(Assumptions!$C$10)))-0.5*SQRT(Assumptions!$C$10)) -> 209.97367
B21: 2450 | C21: =2450*EXP(-Assumptions!$C$11*Assumptions!$C$10)*NORMSDIST((LN(2450/Assumptions!$C$7)+(Assumptions!$C$9-Assumptions!$C$11+0.1^2/2)*Assumptions!$C$10)/(0.1*SQRT(Assumptions!$C$10)))-Assumptions!$C$7*EXP(-Assumptions!$C$9*Assumptions!$C$10)*NORMSDIST(((LN(2450/Assumptions!$C$7)+(Assumptions!$C$9-Assumptions!$C$11+0.1^2/2)*Assumptions!$C$10)/(0.1*SQRT(Assumptions!$C$10)))-0.1*SQRT(Assumptions!$C$10)) -> 41.397349 | D21: =2450*EXP(-Assumptions!$C$11*Assumptions!$C$10)*NORMSDIST((LN(2450/Assumptions!$C$7)+(Assumptions!$C$9-Assumptions!$C$11+0.15^2/2)*Assumptions!$C$10)/(0.15*SQRT(Assumptions!$C$10)))-Assumptions!$C$7*EXP(-Assumptions!$C$9*Assumptions!$C$10)*NORMSDIST(((LN(2450/Assumptions!$C$7)+(Assumptions!$C$9-Assumptions!$C$11+0.15^2/2)*Assumptions!$C$10)/(0.15*SQRT(Assumptions!$C$10)))-0.15*SQRT(Assumptions!$C$10)) -> 65.702928 | E21: =2450*EXP(-Assumptions!$C$11*Assumptions!$C$10)*NORMSDIST((LN(2450/Assumptions!$C$7)+(Assumptions!$C$9-Assumptions!$C$11+0.2^2/2)*Assumptions!$C$10)/(0.2*SQRT(Assumptions!$C$10)))-Assumptions!$C$7*EXP(-Assumptions!$C$9*Assumptions!$C$10)*NORMSDIST(((LN(2450/Assumptions!$C$7)+(Assumptions!$C$9-Assumptions!$C$11+0.2^2/2)*Assumptions!$C$10)/(0.2*SQRT(Assumptions!$C$10)))-0.2*SQRT(Assumptions!$C$10)) -> 90.064631 | F21: =2450*EXP(-Assumptions!$C$11*Assumptions!$C$10)*NORMSDIST((LN(2450/Assumptions!$C$7)+(Assumptions!$C$9-Assumptions!$C$11+0.25^2/2)*Assumptions!$C$10)/(0.25*SQRT(Assumptions!$C$10)))-Assumptions!$C$7*EXP(-Assumptions!$C$9*Assumptions!$C$10)*NORMSDIST(((LN(2450/Assumptions!$C$7)+(Assumptions!$C$9-Assumptions!$C$11+0.25^2/2)*Assumptions!$C$10)/(0.25*SQRT(Assumptions!$C$10)))-0.25*SQRT(Assumptions!$C$10)) -> 114.43816 | G21: =2450*EXP(-Assumptions!$C$11*Assumptions!$C$10)*NORMSDIST((LN(2450/Assumptions!$C$7)+(Assumptions!$C$9-Assumptions!$C$11+0.3^2/2)*Assumptions!$C$10)/(0.3*SQRT(Assumptions!$C$10)))-Assumptions!$C$7*EXP(-Assumptions!$C$9*Assumptions!$C$10)*NORMSDIST(((LN(2450/Assumptions!$C$7)+(Assumptions!$C$9-Assumptions!$C$11+0.3^2/2)*Assumptions!$C$10)/(0.3*SQRT(Assumptions!$C$10)))-0.3*SQRT(Assumptions!$C$10)) -> 138.80618 | H21: =2450*EXP(-Assumptions!$C$11*Assumptions!$C$10)*NORMSDIST((LN(2450/Assumptions!$C$7)+(Assumptions!$C$9-Assumptions!$C$11+0.35^2/2)*Assumptions!$C$10)/(0.35*SQRT(Assumptions!$C$10)))-Assumptions!$C$7*EXP(-Assumptions!$C$9*Assumptions!$C$10)*NORMSDIST(((LN(2450/Assumptions!$C$7)+(Assumptions!$C$9-Assumptions!$C$11+0.35^2/2)*Assumptions!$C$10)/(0.35*SQRT(Assumptions!$C$10)))-0.35*SQRT(Assumptions!$C$10)) -> 163.15909 | I21: =2450*EXP(-Assumptions!$C$11*Assumptions!$C$10)*NORMSDIST((LN(2450/Assumptions!$C$7)+(Assumptions!$C$9-Assumptions!$C$11+0.4^2/2)*Assumptions!$C$10)/(0.4*SQRT(Assumptions!$C$10)))-Assumptions!$C$7*EXP(-Assumptions!$C$9*Assumptions!$C$10)*NORMSDIST(((LN(2450/Assumptions!$C$7)+(Assumptions!$C$9-Assumptions!$C$11+0.4^2/2)*Assumptions!$C$10)/(0.4*SQRT(Assumptions!$C$10)))-0.4*SQRT(Assumptions!$C$10)) -> 187.4902 | J21: =2450*EXP(-Assumptions!$C$11*Assumptions!$C$10)*NORMSDIST((LN(2450/Assumptions!$C$7)+(Assumptions!$C$9-Assumptions!$C$11+0.45^2/2)*Assumptions!$C$10)/(0.45*SQRT(Assumptions!$C$10)))-Assumptions!$C$7*EXP(-Assumptions!$C$9*Assumptions!$C$10)*NORMSDIST(((LN(2450/Assumptions!$C$7)+(Assumptions!$C$9-Assumptions!$C$11+0.45^2/2)*Assumptions!$C$10)/(0.45*SQRT(Assumptions!$C$10)))-0.45*SQRT(Assumptions!$C$10)) -> 211.79413 | K21: =2450*EXP(-Assumptions!$C$11*Assumptions!$C$10)*NORMSDIST((LN(2450/Assumptions!$C$7)+(Assumptions!$C$9-Assumptions!$C$11+0.5^2/2)*Assumptions!$C$10)/(0.5*SQRT(Assumptions!$C$10)))-Assumptions!$C$7*EXP(-Assumptions!$C$9*Assumptions!$C$10)*NORMSDIST(((LN(2450/Assumptions!$C$7)+(Assumptions!$C$9-Assumptions!$C$11+0.5^2/2)*Assumptions!$C$10)/(0.5*SQRT(Assumptions!$C$10)))-0.5*SQRT(Assumptions!$C$10)) -> 236.06615
B22: 2500 | C22: =2500*EXP(-Assumptions!$C$11*Assumptions!$C$10)*NORMSDIST((LN(2500/Assumptions!$C$7)+(Assumptions!$C$9-Assumptions!$C$11+0.1^2/2)*Assumptions!$C$10)/(0.1*SQRT(Assumptions!$C$10)))-Assumptions!$C$7*EXP(-Assumptions!$C$9*Assumptions!$C$10)*NORMSDIST(((LN(2500/Assumptions!$C$7)+(Assumptions!$C$9-Assumptions!$C$11+0.1^2/2)*Assumptions!$C$10)/(0.1*SQRT(Assumptions!$C$10)))-0.1*SQRT(Assumptions!$C$10)) -> 68.281509 | D22: =2500*EXP(-Assumptions!$C$11*Assumptions!$C$10)*NORMSDIST((LN(2500/Assumptions!$C$7)+(Assumptions!$C$9-Assumptions!$C$11+0.15^2/2)*Assumptions!$C$10)/(0.15*SQRT(Assumptions!$C$10)))-Assumptions!$C$7*EXP(-Assumptions!$C$9*Assumptions!$C$10)*NORMSDIST(((LN(2500/Assumptions!$C$7)+(Assumptions!$C$9-Assumptions!$C$11+0.15^2/2)*Assumptions!$C$10)/(0.15*SQRT(Assumptions!$C$10)))-0.15*SQRT(Assumptions!$C$10)) -> 92.356339 | E22: =2500*EXP(-Assumptions!$C$11*Assumptions!$C$10)*NORMSDIST((LN(2500/Assumptions!$C$7)+(Assumptions!$C$9-Assumptions!$C$11+0.2^2/2)*Assumptions!$C$10)/(0.2*SQRT(Assumptions!$C$10)))-Assumptions!$C$7*EXP(-Assumptions!$C$9*Assumptions!$C$10)*NORMSDIST(((LN(2500/Assumptions!$C$7)+(Assumptions!$C$9-Assumptions!$C$11+0.2^2/2)*Assumptions!$C$10)/(0.2*SQRT(Assumptions!$C$10)))-0.2*SQRT(Assumptions!$C$10)) -> 116.72474 | F22: =2500*EXP(-Assumptions!$C$11*Assumptions!$C$10)*NORMSDIST((LN(2500/Assumptions!$C$7)+(Assumptions!$C$9-Assumptions!$C$11+0.25^2/2)*Assumptions!$C$10)/(0.25*SQRT(Assumptions!$C$10)))-Assumptions!$C$7*EXP(-Assumptions!$C$9*Assumptions!$C$10)*NORMSDIST(((LN(2500/Assumptions!$C$7)+(Assumptions!$C$9-Assumptions!$C$11+0.25^2/2)*Assumptions!$C$10)/(0.25*SQRT(Assumptions!$C$10)))-0.25*SQRT(Assumptions!$C$10)) -> 141.20096 | G22: =2500*EXP(-Assumptions!$C$11*Assumptions!$C$10)*NORMSDIST((LN(2500/Assumptions!$C$7)+(Assumptions!$C$9-Assumptions!$C$11+0.3^2/2)*Assumptions!$C$10)/(0.3*SQRT(Assumptions!$C$10)))-Assumptions!$C$7*EXP(-Assumptions!$C$9*Assumptions!$C$10)*NORMSDIST(((LN(2500/Assumptions!$C$7)+(Assumptions!$C$9-Assumptions!$C$11+0.3^2/2)*Assumptions!$C$10)/(0.3*SQRT(Assumptions!$C$10)))-0.3*SQRT(Assumptions!$C$10)) -> 165.7198 | H22: =2500*EXP(-Assumptions!$C$11*Assumptions!$C$10)*NORMSDIST((LN(2500/Assumptions!$C$7)+(Assumptions!$C$9-Assumptions!$C$11+0.35^2/2)*Assumptions!$C$10)/(0.35*SQRT(Assumptions!$C$10)))-Assumptions!$C$7*EXP(-Assumptions!$C$9*Assumptions!$C$10)*NORMSDIST(((LN(2500/Assumptions!$C$7)+(Assumptions!$C$9-Assumptions!$C$11+0.35^2/2)*Assumptions!$C$10)/(0.35*SQRT(Assumptions!$C$10)))-0.35*SQRT(Assumptions!$C$10)) -> 190.25097 | I22: =2500*EXP(-Assumptions!$C$11*Assumptions!$C$10)*NORMSDIST((LN(2500/Assumptions!$C$7)+(Assumptions!$C$9-Assumptions!$C$11+0.4^2/2)*Assumptions!$C$10)/(0.4*SQRT(Assumptions!$C$10)))-Assumptions!$C$7*EXP(-Assumptions!$C$9*Assumptions!$C$10)*NORMSDIST(((LN(2500/Assumptions!$C$7)+(Assumptions!$C$9-Assumptions!$C$11+0.4^2/2)*Assumptions!$C$10)/(0.4*SQRT(Assumptions!$C$10)))-0.4*SQRT(Assumptions!$C$10)) -> 214.77739 | J22: =2500*EXP(-Assumptions!$C$11*Assumptions!$C$10)*NORMSDIST((LN(2500/Assumptions!$C$7)+(Assumptions!$C$9-Assumptions!$C$11+0.45^2/2)*Assumptions!$C$10)/(0.45*SQRT(Assumptions!$C$10)))-Assumptions!$C$7*EXP(-Assumptions!$C$9*Assumptions!$C$10)*NORMSDIST(((LN(2500/Assumptions!$C$7)+(Assumptions!$C$9-Assumptions!$C$11+0.45^2/2)*Assumptions!$C$10)/(0.45*SQRT(Assumptions!$C$10)))-0.45*SQRT(Assumptions!$C$10)) -> 239.28789 | K22: =2500*EXP(-Assumptions!$C$11*Assumptions!$C$10)*NORMSDIST((LN(2500/Assumptions!$C$7)+(Assumptions!$C$9-Assumptions!$C$11+0.5^2/2)*Assumptions!$C$10)/(0.5*SQRT(Assumptions!$C$10)))-Assumptions!$C$7*EXP(-Assumptions!$C$9*Assumptions!$C$10)*NORMSDIST(((LN(2500/Assumptions!$C$7)+(Assumptions!$C$9-Assumptions!$C$11+0.5^2/2)*Assumptions!$C$10)/(0.5*SQRT(Assumptions!$C$10)))-0.5*SQRT(Assumptions!$C$10)) -> 263.77422
B23: 2550 | C23: =2550*EXP(-Assumptions!$C$11*Assumptions!$C$10)*NORMSDIST((LN(2550/Assumptions!$C$7)+(Assumptions!$C$9-Assumptions!$C$11+0.1^2/2)*Assumptions!$C$10)/(0.1*SQRT(Assumptions!$C$10)))-Assumptions!$C$7*EXP(-Assumptions!$C$9*Assumptions!$C$10)*NORMSDIST(((LN(2550/Assumptions!$C$7)+(Assumptions!$C$9-Assumptions!$C$11+0.1^2/2)*Assumptions!$C$10)/(0.1*SQRT(Assumptions!$C$10)))-0.1*SQRT(Assumptions!$C$10)) -> 102.68818 | D23: =2550*EXP(-Assumptions!$C$11*Assumptions!$C$10)*NORMSDIST((LN(2550/Assumptions!$C$7)+(Assumptions!$C$9-Assumptions!$C$11+0.15^2/2)*Assumptions!$C$10)/(0.15*SQRT(Assumptions!$C$10)))-Assumptions!$C$7*EXP(-Assumptions!$C$9*Assumptions!$C$10)*NORMSDIST(((LN(2550/Assumptions!$C$7)+(Assumptions!$C$9-Assumptions!$C$11+0.15^2/2)*Assumptions!$C$10)/(0.15*SQRT(Assumptions!$C$10)))-0.15*SQRT(Assumptions!$C$10)) -> 124.16071 | E23: =2550*EXP(-Assumptions!$C$11*Assumptions!$C$10)*NORMSDIST((LN(2550/Assumptions!$C$7)+(Assumptions!$C$9-Assumptions!$C$11+0.2^2/2)*Assumptions!$C$10)/(0.2*SQRT(Assumptions!$C$10)))-Assumptions!$C$7*EXP(-Assumptions!$C$9*Assumptions!$C$10)*NORMSDIST(((LN(2550/Assumptions!$C$7)+(Assumptions!$C$9-Assumptions!$C$11+0.2^2/2)*Assumptions!$C$10)/(0.2*SQRT(Assumptions!$C$10)))-0.2*SQRT(Assumptions!$C$10)) -> 147.28342 | F23: =2550*EXP(-Assumptions!$C$11*Assumptions!$C$10)*NORMSDIST((LN(2550/Assumptions!$C$7)+(Assumptions!$C$9-Assumptions!$C$11+0.25^2/2)*Assumptions!$C$10)/(0.25*SQRT(Assumptions!$C$10)))-Assumptions!$C$7*EXP(-Assumptions!$C$9*Assumptions!$C$10)*NORMSDIST(((LN(2550/Assumptions!$C$7)+(Assumptions!$C$9-Assumptions!$C$11+0.25^2/2)*Assumptions!$C$10)/(0.25*SQRT(Assumptions!$C$10)))-0.25*SQRT(Assumptions!$C$10)) -> 171.09448 | G23: =2550*EXP(-Assumptions!$C$11*Assumptions!$C$10)*NORMSDIST((LN(2550/Assumptions!$C$7)+(Assumptions!$C$9-Assumptions!$C$11+0.3^2/2)*Assumptions!$C$10)/(0.3*SQRT(Assumptions!$C$10)))-Assumptions!$C$7*EXP(-Assumptions!$C$9*Assumptions!$C$10)*NORMSDIST(((LN(2550/Assumptions!$C$7)+(Assumptions!$C$9-Assumptions!$C$11+0.3^2/2)*Assumptions!$C$10)/(0.3*SQRT(Assumptions!$C$10)))-0.3*SQRT(Assumptions!$C$10)) -> 195.2465 | H23: =2550*EXP(-Assumptions!$C$11*Assumptions!$C$10)*NORMSDIST((LN(2550/Assumptions!$C$7)+(Assumptions!$C$9-Assumptions!$C$11+0.35^2/2)*Assumptions!$C$10)/(0.35*SQRT(Assumptions!$C$10)))-Assumptions!$C$7*EXP(-Assumptions!$C$9*Assumptions!$C$10)*NORMSDIST(((LN(2550/Assumptions!$C$7)+(Assumptions!$C$9-Assumptions!$C$11+0.35^2/2)*Assumptions!$C$10)/(0.35*SQRT(Assumptions!$C$10)))-0.35*SQRT(Assumptions!$C$10)) -> 219.58368 | I23: =2550*EXP(-Assumptions!$C$11*Assumptions!$C$10)*NORMSDIST((LN(2550/Assumptions!$C$7)+(Assumptions!$C$9-Assumptions!$C$11+0.4^2/2)*Assumptions!$C$10)/(0.4*SQRT(Assumptions!$C$10)))-Assumptions!$C$7*EXP(-Assumptions!$C$9*Assumptions!$C$10)*NORMSDIST(((LN(2550/Assumptions!$C$7)+(Assumptions!$C$9-Assumptions!$C$11+0.4^2/2)*Assumptions!$C$10)/(0.4*SQRT(Assumptions!$C$10)))-0.4*SQRT(Assumptions!$C$10)) -> 244.0249 | J23: =2550*EXP(-Assumptions!$C$11*Assumptions!$C$10)*NORMSDIST((LN(2550/Assumptions!$C$7)+(Assumptions!$C$9-Assumptions!$C$11+0.45^2/2)*Assumptions!$C$10)/(0.45*SQRT(Assumptions!$C$10)))-Assumptions!$C$7*EXP(-Assumptions!$C$9*Assumptions!$C$10)*NORMSDIST(((LN(2550/Assumptions!$C$7)+(Assumptions!$C$9-Assumptions!$C$11+0.45^2/2)*Assumptions!$C$10)/(0.45*SQRT(Assumptions!$C$10)))-0.45*SQRT(Assumptions!$C$10)) -> 268.52298 | K23: =2550*EXP(-Assumptions!$C$11*Assumptions!$C$10)*NORMSDIST((LN(2550/Assumptions!$C$7)+(Assumptions!$C$9-Assumptions!$C$11+0.5^2/2)*Assumptions!$C$10)/(0.5*SQRT(Assumptions!$C$10)))-Assumptions!$C$7*EXP(-Assumptions!$C$9*Assumptions!$C$10)*NORMSDIST(((LN(2550/Assumptions!$C$7)+(Assumptions!$C$9-Assumptions!$C$11+0.5^2/2)*Assumptions!$C$10)/(0.5*SQRT(Assumptions!$C$10)))-0.5*SQRT(Assumptions!$C$10)) -> 293.04791
B24: 2600 | C24: =2600*EXP(-Assumptions!$C$11*Assumptions!$C$10)*NORMSDIST((LN(2600/Assumptions!$C$7)+(Assumptions!$C$9-Assumptions!$C$11+0.1^2/2)*Assumptions!$C$10)/(0.1*SQRT(Assumptions!$C$10)))-Assumptions!$C$7*EXP(-Assumptions!$C$9*Assumptions!$C$10)*NORMSDIST(((LN(2600/Assumptions!$C$7)+(Assumptions!$C$9-Assumptions!$C$11+0.1^2/2)*Assumptions!$C$10)/(0.1*SQRT(Assumptions!$C$10)))-0.1*SQRT(Assumptions!$C$10)) -> 143.18695 | D24: =2600*EXP(-Assumptions!$C$11*Assumptions!$C$10)*NORMSDIST((LN(2600/Assumptions!$C$7)+(Assumptions!$C$9-Assumptions!$C$11+0.15^2/2)*Assumptions!$C$10)/(0.15*SQRT(Assumptions!$C$10)))-Assumptions!$C$7*EXP(-Assumptions!$C$9*Assumptions!$C$10)*NORMSDIST(((LN(2600/Assumptions!$C$7)+(Assumptions!$C$9-Assumptions!$C$11+0.15^2/2)*Assumptions!$C$10)/(0.15*SQRT(Assumptions!$C$10)))-0.15*SQRT(Assumptions!$C$10)) -> 160.57314 | E24: =2600*EXP(-Assumptions!$C$11*Assumptions!$C$10)*NORMSDIST((LN(2600/Assumptions!$C$7)+(Assumptions!$C$9-Assumptions!$C$11+0.2^2/2)*Assumptions!$C$10)/(0.2*SQRT(Assumptions!$C$10)))-Assumptions!$C$7*EXP(-Assumptions!$C$9*Assumptions!$C$10)*NORMSDIST(((LN(2600/Assumptions!$C$7)+(Assumptions!$C$9-Assumptions!$C$11+0.2^2/2)*Assumptions!$C$10)/(0.2*SQRT(Assumptions!$C$10)))-0.2*SQRT(Assumptions!$C$10)) -> 181.45581 | F24: =2600*EXP(-Assumptions!$C$11*Assumptions!$C$10)*NORMSDIST((LN(2600/Assumptions!$C$7)+(Assumptions!$C$9-Assumptions!$C$11+0.25^2/2)*Assumptions!$C$10)/(0.25*SQRT(Assumptions!$C$10)))-Assumptions!$C$7*EXP(-Assumptions!$C$9*Assumptions!$C$10)*NORMSDIST(((LN(2600/Assumptions!$C$7)+(Assumptions!$C$9-Assumptions!$C$11+0.25^2/2)*Assumptions!$C$10)/(0.25*SQRT(Assumptions!$C$10)))-0.25*SQRT(Assumptions!$C$10)) -> 203.9384 | G24: =2600*EXP(-Assumptions!$C$11*Assumptions!$C$10)*NORMSDIST((LN(2600/Assumptions!$C$7)+(Assumptions!$C$9-Assumptions!$C$11+0.3^2/2)*Assumptions!$C$10)/(0.3*SQRT(Assumptions!$C$10)))-Assumptions!$C$7*EXP(-Assumptions!$C$9*Assumptions!$C$10)*NORMSDIST(((LN(2600/Assumptions!$C$7)+(Assumptions!$C$9-Assumptions!$C$11+0.3^2/2)*Assumptions!$C$10)/(0.3*SQRT(Assumptions!$C$10)))-0.3*SQRT(Assumptions!$C$10)) -> 227.2581 | H24: =2600*EXP(-Assumptions!$C$11*Assumptions!$C$10)*NORMSDIST((LN(2600/Assumptions!$C$7)+(Assumptions!$C$9-Assumptions!$C$11+0.35^2/2)*Assumptions!$C$10)/(0.35*SQRT(Assumptions!$C$10)))-Assumptions!$C$7*EXP(-Assumptions!$C$9*Assumptions!$C$10)*NORMSDIST(((LN(2600/Assumptions!$C$7)+(Assumptions!$C$9-Assumptions!$C$11+0.35^2/2)*Assumptions!$C$10)/(0.35*SQRT(Assumptions!$C$10)))-0.35*SQRT(Assumptions!$C$10)) -> 251.05893 | I24: =2600*EXP(-Assumptions!$C$11*Assumptions!$C$10)*NORMSDIST((LN(2600/Assumptions!$C$7)+(Assumptions!$C$9-Assumptions!$C$11+0.4^2/2)*Assumptions!$C$10)/(0.4*SQRT(Assumptions!$C$10)))-Assumptions!$C$7*EXP(-Assumptions!$C$9*Assumptions!$C$10)*NORMSDIST(((LN(2600/Assumptions!$C$7)+(Assumptions!$C$9-Assumptions!$C$11+0.4^2/2)*Assumptions!$C$10)/(0.4*SQRT(Assumptions!$C$10)))-0.4*SQRT(Assumptions!$C$10)) -> 275.15339 | J24: =2600*EXP(-Assumptions!$C$11*Assumptions!$C$10)*NORMSDIST((LN(2600/Assumptions!$C$7)+(Assumptions!$C$9-Assumptions!$C$11+0.45^2/2)*Assumptions!$C$10)/(0.45*SQRT(Assumptions!$C$10)))-Assumptions!$C$7*EXP(-Assumptions!$C$9*Assumptions!$C$10)*NORMSDIST(((LN(2600/Assumptions!$C$7)+(Assumptions!$C$9-Assumptions!$C$11+0.45^2/2)*Assumptions!$C$10)/(0.45*SQRT(Assumptions!$C$10)))-0.45*SQRT(Assumptions!$C$10)) -> 299.43301 | K24: =2600*EXP(-Assumptions!$C$11*Assumptions!$C$10)*NORMSDIST((LN(2600/Assumptions!$C$7)+(Assumptions!$C$9-Assumptions!$C$11+0.5^2/2)*Assumptions!$C$10)/(0.5*SQRT(Assumptions!$C$10)))-Assumptions!$C$7*EXP(-Assumptions!$C$9*Assumptions!$C$10)*NORMSDIST(((LN(2600/Assumptions!$C$7)+(Assumptions!$C$9-Assumptions!$C$11+0.5^2/2)*Assumptions!$C$10)/(0.5*SQRT(Assumptions!$C$10)))-0.5*SQRT(Assumptions!$C$10)) -> 323.83014
B25: 2650 | C25: =2650*EXP(-Assumptions!$C$11*Assumptions!$C$10)*NORMSDIST((LN(2650/Assumptions!$C$7)+(Assumptions!$C$9-Assumptions!$C$11+0.1^2/2)*Assumptions!$C$10)/(0.1*SQRT(Assumptions!$C$10)))-Assumptions!$C$7*EXP(-Assumptions!$C$9*Assumptions!$C$10)*NORMSDIST(((LN(2650/Assumptions!$C$7)+(Assumptions!$C$9-Assumptions!$C$11+0.1^2/2)*Assumptions!$C$10)/(0.1*SQRT(Assumptions!$C$10)))-0.1*SQRT(Assumptions!$C$10)) -> 187.95355 | D25: =2650*EXP(-Assumptions!$C$11*Assumptions!$C$10)*NORMSDIST((LN(2650/Assumptions!$C$7)+(Assumptions!$C$9-Assumptions!$C$11+0.15^2/2)*Assumptions!$C$10)/(0.15*SQRT(Assumptions!$C$10)))-Assumptions!$C$7*EXP(-Assumptions!$C$9*Assumptions!$C$10)*NORMSDIST(((LN(2650/Assumptions!$C$7)+(Assumptions!$C$9-Assumptions!$C$11+0.15^2/2)*Assumptions!$C$10)/(0.15*SQRT(Assumptions!$C$10)))-0.15*SQRT(Assumptions!$C$10)) -> 200.84886 | E25: =2650*EXP(-Assumptions!$C$11*Assumptions!$C$10)*NORMSDIST((LN(2650/Assumptions!$C$7)+(Assumptions!$C$9-Assumptions!$C$11+0.2^2/2)*Assumptions!$C$10)/(0.2*SQRT(Assumptions!$C$10)))-Assumptions!$C$7*EXP(-Assumptions!$C$9*Assumptions!$C$10)*NORMSDIST(((LN(2650/Assumptions!$C$7)+(Assumptions!$C$9-Assumptions!$C$11+0.2^2/2)*Assumptions!$C$10)/(0.2*SQRT(Assumptions!$C$10)))-0.2*SQRT(Assumptions!$C$10)) -> 218.85808 | F25: =2650*EXP(-Assumptions!$C$11*Assumptions!$C$10)*NORMSDIST((LN(2650/Assumptions!$C$7)+(Assumptions!$C$9-Assumptions!$C$11+0.25^2/2)*Assumptions!$C$10)/(0.25*SQRT(Assumptions!$C$10)))-Assumptions!$C$7*EXP(-Assumptions!$C$9*Assumptions!$C$10)*NORMSDIST(((LN(2650/Assumptions!$C$7)+(Assumptions!$C$9-Assumptions!$C$11+0.25^2/2)*Assumptions!$C$10)/(0.25*SQRT(Assumptions!$C$10)))-0.25*SQRT(Assumptions!$C$10)) -> 239.49915 | G25: =2650*EXP(-Assumptions!$C$11*Assumptions!$C$10)*NORMSDIST((LN(2650/Assumptions!$C$7)+(Assumptions!$C$9-Assumptions!$C$11+0.3^2/2)*Assumptions!$C$10)/(0.3*SQRT(Assumptions!$C$10)))-Assumptions!$C$7*EXP(-Assumptions!$C$9*Assumptions!$C$10)*NORMSDIST(((LN(2650/Assumptions!$C$7)+(Assumptions!$C$9-Assumptions!$C$11+0.3^2/2)*Assumptions!$C$10)/(0.3*SQRT(Assumptions!$C$10)))-0.3*SQRT(Assumptions!$C$10)) -> 261.59539 | H25: =2650*EXP(-Assumptions!$C$11*Assumptions!$C$10)*NORMSDIST((LN(2650/Assumptions!$C$7)+(Assumptions!$C$9-Assumptions!$C$11+0.35^2/2)*Assumptions!$C$10)/(0.35*SQRT(Assumptions!$C$10)))-Assumptions!$C$7*EXP(-Assumptions!$C$9*Assumptions!$C$10)*NORMSDIST(((LN(2650/Assumptions!$C$7)+(Assumptions!$C$9-Assumptions!$C$11+0.35^2/2)*Assumptions!$C$10)/(0.35*SQRT(Assumptions!$C$10)))-0.35*SQRT(Assumptions!$C$10)) -> 284.55925 | I25: =2650*EXP(-Assumptions!$C$11*Assumptions!$C$10)*NORMSDIST((LN(2650/Assumptions!$C$7)+(Assumptions!$C$9-Assumptions!$C$11+0.4^2/2)*Assumptions!$C$10)/(0.4*SQRT(Assumptions!$C$10)))-Assumptions!$C$7*EXP(-Assumptions!$C$9*Assumptions!$C$10)*NORMSDIST(((LN(2650/Assumptions!$C$7)+(Assumptions!$C$9-Assumptions!$C$11+0.4^2/2)*Assumptions!$C$10)/(0.4*SQRT(Assumptions!$C$10)))-0.4*SQRT(Assumptions!$C$10)) -> 308.07111 | J25: =2650*EXP(-Assumptions!$C$11*Assumptions!$C$10)*NORMSDIST((LN(2650/Assumptions!$C$7)+(Assumptions!$C$9-Assumptions!$C$11+0.45^2/2)*Assumptions!$C$10)/(0.45*SQRT(Assumptions!$C$10)))-Assumptions!$C$7*EXP(-Assumptions!$C$9*Assumptions!$C$10)*NORMSDIST(((LN(2650/Assumptions!$C$7)+(Assumptions!$C$9-Assumptions!$C$11+0.45^2/2)*Assumptions!$C$10)/(0.45*SQRT(Assumptions!$C$10)))-0.45*SQRT(Assumptions!$C$10)) -> 331.94326 | K25: =2650*EXP(-Assumptions!$C$11*Assumptions!$C$10)*NORMSDIST((LN(2650/Assumptions!$C$7)+(Assumptions!$C$9-Assumptions!$C$11+0.5^2/2)*Assumptions!$C$10)/(0.5*SQRT(Assumptions!$C$10)))-Assumptions!$C$7*EXP(-Assumptions!$C$9*Assumptions!$C$10)*NORMSDIST(((LN(2650/Assumptions!$C$7)+(Assumptions!$C$9-Assumptions!$C$11+0.5^2/2)*Assumptions!$C$10)/(0.5*SQRT(Assumptions!$C$10)))-0.5*SQRT(Assumptions!$C$10)) -> 356.05813
B26: 2700 | C26: =2700*EXP(-Assumptions!$C$11*Assumptions!$C$10)*NORMSDIST((LN(2700/Assumptions!$C$7)+(Assumptions!$C$9-Assumptions!$C$11+0.1^2/2)*Assumptions!$C$10)/(0.1*SQRT(Assumptions!$C$10)))-Assumptions!$C$7*EXP(-Assumptions!$C$9*Assumptions!$C$10)*NORMSDIST(((LN(2700/Assumptions!$C$7)+(Assumptions!$C$9-Assumptions!$C$11+0.1^2/2)*Assumptions!$C$10)/(0.1*SQRT(Assumptions!$C$10)))-0.1*SQRT(Assumptions!$C$10)) -> 235.32712 | D26: =2700*EXP(-Assumptions!$C$11*Assumptions!$C$10)*NORMSDIST((LN(2700/Assumptions!$C$7)+(Assumptions!$C$9-Assumptions!$C$11+0.15^2/2)*Assumptions!$C$10)/(0.15*SQRT(Assumptions!$C$10)))-Assumptions!$C$7*EXP(-Assumptions!$C$9*Assumptions!$C$10)*NORMSDIST(((LN(2700/Assumptions!$C$7)+(Assumptions!$C$9-Assumptions!$C$11+0.15^2/2)*Assumptions!$C$10)/(0.15*SQRT(Assumptions!$C$10)))-0.15*SQRT(Assumptions!$C$10)) -> 244.17105 | E26: =2700*EXP(-Assumptions!$C$11*Assumptions!$C$10)*NORMSDIST((LN(2700/Assumptions!$C$7)+(Assumptions!$C$9-Assumptions!$C$11+0.2^2/2)*Assumptions!$C$10)/(0.2*SQRT(Assumptions!$C$10)))-Assumptions!$C$7*EXP(-Assumptions!$C$9*Assumptions!$C$10)*NORMSDIST(((LN(2700/Assumptions!$C$7)+(Assumptions!$C$9-Assumptions!$C$11+0.2^2/2)*Assumptions!$C$10)/(0.2*SQRT(Assumptions!$C$10)))-0.2*SQRT(Assumptions!$C$10)) -> 259.04971 | F26: =2700*EXP(-Assumptions!$C$11*Assumptions!$C$10)*NORMSDIST((LN(2700/Assumptions!$C$7)+(Assumptions!$C$9-Assumptions!$C$11+0.25^2/2)*Assumptions!$C$10)/(0.25*SQRT(Assumptions!$C$10)))-Assumptions!$C$7*EXP(-Assumptions!$C$9*Assumptions!$C$10)*NORMSDIST(((LN(2700/Assumptions!$C$7)+(Assumptions!$C$9-Assumptions!$C$11+0.25^2/2)*Assumptions!$C$10)/(0.25*SQRT(Assumptions!$C$10)))-0.25*SQRT(Assumptions!$C$10)) -> 277.50769 | G26: =2700*EXP(-Assumptions!$C$11*Assumptions!$C$10)*NORMSDIST((LN(2700/Assumptions!$C$7)+(Assumptions!$C$9-Assumptions!$C$11+0.3^2/2)*Assumptions!$C$10)/(0.3*SQRT(Assumptions!$C$10)))-Assumptions!$C$7*EXP(-Assumptions!$C$9*Assumptions!$C$10)*NORMSDIST(((LN(2700/Assumptions!$C$7)+(Assumptions!$C$9-Assumptions!$C$11+0.3^2/2)*Assumptions!$C$10)/(0.3*SQRT(Assumptions!$C$10)))-0.3*SQRT(Assumptions!$C$10)) -> 298.07697 | H26: =2700*EXP(-Assumptions!$C$11*Assumptions!$C$10)*NORMSDIST((LN(2700/Assumptions!$C$7)+(Assumptions!$C$9-Assumptions!$C$11+0.35^2/2)*Assumptions!$C$10)/(0.35*SQRT(Assumptions!$C$10)))-Assumptions!$C$7*EXP(-Assumptions!$C$9*Assumptions!$C$10)*NORMSDIST(((LN(2700/Assumptions!$C$7)+(Assumptions!$C$9-Assumptions!$C$11+0.35^2/2)*Assumptions!$C$10)/(0.35*SQRT(Assumptions!$C$10)))-0.35*SQRT(Assumptions!$C$10)) -> 319.95288 | I26: =2700*EXP(-Assumptions!$C$11*Assumptions!$C$10)*NORMSDIST((LN(2700/Assumptions!$C$7)+(Assumptions!$C$9-Assumptions!$C$11+0.4^2/2)*Assumptions!$C$10)/(0.4*SQRT(Assumptions!$C$10)))-Assumptions!$C$7*EXP(-Assumptions!$C$9*Assumptions!$C$10)*NORMSDIST(((LN(2700/Assumptions!$C$7)+(Assumptions!$C$9-Assumptions!$C$11+0.4^2/2)*Assumptions!$C$10)/(0.4*SQRT(Assumptions!$C$10)))-0.4*SQRT(Assumptions!$C$10)) -> 342.67686 | J26: =2700*EXP(-Assumptions!$C$11*Assumptions!$C$10)*NORMSDIST((LN(2700/Assumptions!$C$7)+(Assumptions!$C$9-Assumptions!$C$11+0.45^2/2)*Assumptions!$C$10)/(0.45*SQRT(Assumptions!$C$10)))-Assumptions!$C$7*EXP(-Assumptions!$C$9*Assumptions!$C$10)*NORMSDIST(((LN(2700/Assumptions!$C$7)+(Assumptions!$C$9-Assumptions!$C$11+0.45^2/2)*Assumptions!$C$10)/(0.45*SQRT(Assumptions!$C$10)))-0.45*SQRT(Assumptions!$C$10)) -> 365.97263 | K26: =2700*EXP(-Assumptions!$C$11*Assumptions!$C$10)*NORMSDIST((LN(2700/Assumptions!$C$7)+(Assumptions!$C$9-Assumptions!$C$11+0.5^2/2)*Assumptions!$C$10)/(0.5*SQRT(Assumptions!$C$10)))-Assumptions!$C$7*EXP(-Assumptions!$C$9*Assumptions!$C$10)*NORMSDIST(((LN(2700/Assumptions!$C$7)+(Assumptions!$C$9-Assumptions!$C$11+0.5^2/2)*Assumptions!$C$10)/(0.5*SQRT(Assumptions!$C$10)))-0.5*SQRT(Assumptions!$C$10)) -> 389.66475
B27: 2750 | C27: =2750*EXP(-Assumptions!$C$11*Assumptions!$C$10)*NORMSDIST((LN(2750/Assumptions!$C$7)+(Assumptions!$C$9-Assumptions!$C$11+0.1^2/2)*Assumptions!$C$10)/(0.1*SQRT(Assumptions!$C$10)))-Assumptions!$C$7*EXP(-Assumptions!$C$9*Assumptions!$C$10)*NORMSDIST(((LN(2750/Assumptions!$C$7)+(Assumptions!$C$9-Assumptions!$C$11+0.1^2/2)*Assumptions!$C$10)/(0.1*SQRT(Assumptions!$C$10)))-0.1*SQRT(Assumptions!$C$10)) -> 284.0996 | D27: =2750*EXP(-Assumptions!$C$11*Assumptions!$C$10)*NORMSDIST((LN(2750/Assumptions!$C$7)+(Assumptions!$C$9-Assumptions!$C$11+0.15^2/2)*Assumptions!$C$10)/(0.15*SQRT(Assumptions!$C$10)))-Assumptions!$C$7*EXP(-Assumptions!$C$9*Assumptions!$C$10)*NORMSDIST(((LN(2750/Assumptions!$C$7)+(Assumptions!$C$9-Assumptions!$C$11+0.15^2/2)*Assumptions!$C$10)/(0.15*SQRT(Assumptions!$C$10)))-0.15*SQRT(Assumptions!$C$10)) -> 289.76064 | E27: =2750*EXP(-Assumptions!$C$11*Assumptions!$C$10)*NORMSDIST((LN(2750/Assumptions!$C$7)+(Assumptions!$C$9-Assumptions!$C$11+0.2^2/2)*Assumptions!$C$10)/(0.2*SQRT(Assumptions!$C$10)))-Assumptions!$C$7*EXP(-Assumptions!$C$9*Assumptions!$C$10)*NORMSDIST(((LN(2750/Assumptions!$C$7)+(Assumptions!$C$9-Assumptions!$C$11+0.2^2/2)*Assumptions!$C$10)/(0.2*SQRT(Assumptions!$C$10)))-0.2*SQRT(Assumptions!$C$10)) -> 301.57347 | F27: =2750*EXP(-Assumptions!$C$11*Assumptions!$C$10)*NORMSDIST((LN(2750/Assumptions!$C$7)+(Assumptions!$C$9-Assumptions!$C$11+0.25^2/2)*Assumptions!$C$10)/(0.25*SQRT(Assumptions!$C$10)))-Assumptions!$C$7*EXP(-Assumptions!$C$9*Assumptions!$C$10)*NORMSDIST(((LN(2750/Assumptions!$C$7)+(Assumptions!$C$9-Assumptions!$C$11+0.25^2/2)*Assumptions!$C$10)/(0.25*SQRT(Assumptions!$C$10)))-0.25*SQRT(Assumptions!$C$10)) -> 317.67669 | G27: =2750*EXP(-Assumptions!$C$11*Assumptions!$C$10)*NORMSDIST((LN(2750/Assumptions!$C$7)+(Assumptions!$C$9-Assumptions!$C$11+0.3^2/2)*Assumptions!$C$10)/(0.3*SQRT(Assumptions!$C$10)))-Assumptions!$C$7*EXP(-Assumptions!$C$9*Assumptions!$C$10)*NORMSDIST(((LN(2750/Assumptions!$C$7)+(Assumptions!$C$9-Assumptions!$C$11+0.3^2/2)*Assumptions!$C$10)/(0.3*SQRT(Assumptions!$C$10)))-0.3*SQRT(Assumptions!$C$10)) -> 336.50781 | H27: =2750*EXP(-Assumptions!$C$11*Assumptions!$C$10)*NORMSDIST((LN(2750/Assumptions!$C$7)+(Assumptions!$C$9-Assumptions!$C$11+0.35^2/2)*Assumptions!$C$10)/(0.35*SQRT(Assumptions!$C$10)))-Assumptions!$C$7*EXP(-Assumptions!$C$9*Assumptions!$C$10)*NORMSDIST(((LN(2750/Assumptions!$C$7)+(Assumptions!$C$9-Assumptions!$C$11+0.35^2/2)*Assumptions!$C$10)/(0.35*SQRT(Assumptions!$C$10)))-0.35*SQRT(Assumptions!$C$10)) -> 357.0986 | I27: =2750*EXP(-Assumptions!$C$11*Assumptions!$C$10)*NORMSDIST((LN(2750/Assumptions!$C$7)+(Assumptions!$C$9-Assumptions!$C$11+0.4^2/2)*Assumptions!$C$10)/(0.4*SQRT(Assumptions!$C$10)))-Assumptions!$C$7*EXP(-Assumptions!$C$9*Assumptions!$C$10)*NORMSDIST(((LN(2750/Assumptions!$C$7)+(Assumptions!$C$9-Assumptions!$C$11+0.4^2/2)*Assumptions!$C$10)/(0.4*SQRT(Assumptions!$C$10)))-0.4*SQRT(Assumptions!$C$10)) -> 378.86293 | J27: =2750*EXP(-Assumptions!$C$11*Assumptions!$C$10)*NORMSDIST((LN(2750/Assumptions!$C$7)+(Assumptions!$C$9-Assumptions!$C$11+0.45^2/2)*Assumptions!$C$10)/(0.45*SQRT(Assumptions!$C$10)))-Assumptions!$C$7*EXP(-Assumptions!$C$9*Assumptions!$C$10)*NORMSDIST(((LN(2750/Assumptions!$C$7)+(Assumptions!$C$9-Assumptions!$C$11+0.45^2/2)*Assumptions!$C$10)/(0.45*SQRT(Assumptions!$C$10)))-0.45*SQRT(Assumptions!$C$10)) -> 401.43554 | K27: =2750*EXP(-Assumptions!$C$11*Assumptions!$C$10)*NORMSDIST((LN(2750/Assumptions!$C$7)+(Assumptions!$C$9-Assumptions!$C$11+0.5^2/2)*Assumptions!$C$10)/(0.5*SQRT(Assumptions!$C$10)))-Assumptions!$C$7*EXP(-Assumptions!$C$9*Assumptions!$C$10)*NORMSDIST(((LN(2750/Assumptions!$C$7)+(Assumptions!$C$9-Assumptions!$C$11+0.5^2/2)*Assumptions!$C$10)/(0.5*SQRT(Assumptions!$C$10)))-0.5*SQRT(Assumptions!$C$10)) -> 424.57972
B28: 2800 | C28: =2800*EXP(-Assumptions!$C$11*Assumptions!$C$10)*NORMSDIST((LN(2800/Assumptions!$C$7)+(Assumptions!$C$9-Assumptions!$C$11+0.1^2/2)*Assumptions!$C$10)/(0.1*SQRT(Assumptions!$C$10)))-Assumptions!$C$7*EXP(-Assumptions!$C$9*Assumptions!$C$10)*NORMSDIST(((LN(2800/Assumptions!$C$7)+(Assumptions!$C$9-Assumptions!$C$11+0.1^2/2)*Assumptions!$C$10)/(0.1*SQRT(Assumptions!$C$10)))-0.1*SQRT(Assumptions!$C$10)) -> 333.53612 | D28: =2800*EXP(-Assumptions!$C$11*Assumptions!$C$10)*NORMSDIST((LN(2800/Assumptions!$C$7)+(Assumptions!$C$9-Assumptions!$C$11+0.15^2/2)*Assumptions!$C$10)/(0.15*SQRT(Assumptions!$C$10)))-Assumptions!$C$7*EXP(-Assumptions!$C$9*Assumptions!$C$10)*NORMSDIST(((LN(2800/Assumptions!$C$7)+(Assumptions!$C$9-Assumptions!$C$11+0.15^2/2)*Assumptions!$C$10)/(0.15*SQRT(Assumptions!$C$10)))-0.15*SQRT(Assumptions!$C$10)) -> 336.94804 | E28: =2800*EXP(-Assumptions!$C$11*Assumptions!$C$10)*NORMSDIST((LN(2800/Assumptions!$C$7)+(Assumptions!$C$9-Assumptions!$C$11+0.2^2/2)*Assumptions!$C$10)/(0.2*SQRT(Assumptions!$C$10)))-Assumptions!$C$7*EXP(-Assumptions!$C$9*Assumptions!$C$10)*NORMSDIST(((LN(2800/Assumptions!$C$7)+(Assumptions!$C$9-Assumptions!$C$11+0.2^2/2)*Assumptions!$C$10)/(0.2*SQRT(Assumptions!$C$10)))-0.2*SQRT(Assumptions!$C$10)) -> 345.98833 | F28: =2800*EXP(-Assumptions!$C$11*Assumptions!$C$10)*NORMSDIST((LN(2800/Assumptions!$C$7)+(Assumptions!$C$9-Assumptions!$C$11+0.25^2/2)*Assumptions!$C$10)/(0.25*SQRT(Assumptions!$C$10)))-Assumptions!$C$7*EXP(-Assumptions!$C$9*Assumptions!$C$10)*NORMSDIST(((LN(2800/Assumptions!$C$7)+(Assumptions!$C$9-Assumptions!$C$11+0.25^2/2)*Assumptions!$C$10)/(0.25*SQRT(Assumptions!$C$10)))-0.25*SQRT(Assumptions!$C$10)) -> 359.71589 | G28: =2800*EXP(-Assumptions!$C$11*Assumptions!$C$10)*NORMSDIST((LN(2800/Assumptions!$C$7)+(Assumptions!$C$9-Assumptions!$C$11+0.3^2/2)*Assumptions!$C$10)/(0.3*SQRT(Assumptions!$C$10)))-Assumptions!$C$7*EXP(-Assumptions!$C$9*Assumptions!$C$10)*NORMSDIST(((LN(2800/Assumptions!$C$7)+(Assumptions!$C$9-Assumptions!$C$11+0.3^2/2)*Assumptions!$C$10)/(0.3*SQRT(Assumptions!$C$10)))-0.3*SQRT(Assumptions!$C$10)) -> 376.68719 | H28: =2800*EXP(-Assumptions!$C$11*Assumptions!$C$10)*NORMSDIST((LN(2800/Assumptions!$C$7)+(Assumptions!$C$9-Assumptions!$C$11+0.35^2/2)*Assumptions!$C$10)/(0.35*SQRT(Assumptions!$C$10)))-Assumptions!$C$7*EXP(-Assumptions!$C$9*Assumptions!$C$10)*NORMSDIST(((LN(2800/Assumptions!$C$7)+(Assumptions!$C$9-Assumptions!$C$11+0.35^2/2)*Assumptions!$C$10)/(0.35*SQRT(Assumptions!$C$10)))-0.35*SQRT(Assumptions!$C$10)) -> 395.85011 | I28: =2800*EXP(-Assumptions!$C$11*Assumptions!$C$10)*NORMSDIST((LN(2800/Assumptions!$C$7)+(Assumptions!$C$9-Assumptions!$C$11+0.4^2/2)*Assumptions!$C$10)/(0.4*SQRT(Assumptions!$C$10)))-Assumptions!$C$7*EXP(-Assumptions!$C$9*Assumptions!$C$10)*NORMSDIST(((LN(2800/Assumptions!$C$7)+(Assumptions!$C$9-Assumptions!$C$11+0.4^2/2)*Assumptions!$C$10)/(0.4*SQRT(Assumptions!$C$10)))-0.4*SQRT(Assumptions!$C$10)) -> 416.51774 | J28: =2800*EXP(-Assumptions!$C$11*Assumptions!$C$10)*NORMSDIST((LN(2800/Assumptions!$C$7)+(Assumptions!$C$9-Assumptions!$C$11+0.45^2/2)*Assumptions!$C$10)/(0.45*SQRT(Assumptions!$C$10)))-Assumptions!$C$7*EXP(-Assumptions!$C$9*Assumptions!$C$10)*NORMSDIST(((LN(2800/Assumptions!$C$7)+(Assumptions!$C$9-Assumptions!$C$11+0.45^2/2)*Assumptions!$C$10)/(0.45*SQRT(Assumptions!$C$10)))-0.45*SQRT(Assumptions!$C$10)) -> 438.24359 | K28: =2800*EXP(-Assumptions!$C$11*Assumptions!$C$10)*NORMSDIST((LN(2800/Assumptions!$C$7)+(Assumptions!$C$9-Assumptions!$C$11+0.5^2/2)*Assumptions!$C$10)/(0.5*SQRT(Assumptions!$C$10)))-Assumptions!$C$7*EXP(-Assumptions!$C$9*Assumptions!$C$10)*NORMSDIST(((LN(2800/Assumptions!$C$7)+(Assumptions!$C$9-Assumptions!$C$11+0.5^2/2)*Assumptions!$C$10)/(0.5*SQRT(Assumptions!$C$10)))-0.5*SQRT(Assumptions!$C$10)) -> 460.73083
B29: 2850 | C29: =2850*EXP(-Assumptions!$C$11*Assumptions!$C$10)*NORMSDIST((LN(2850/Assumptions!$C$7)+(Assumptions!$C$9-Assumptions!$C$11+0.1^2/2)*Assumptions!$C$10)/(0.1*SQRT(Assumptions!$C$10)))-Assumptions!$C$7*EXP(-Assumptions!$C$9*Assumptions!$C$10)*NORMSDIST(((LN(2850/Assumptions!$C$7)+(Assumptions!$C$9-Assumptions!$C$11+0.1^2/2)*Assumptions!$C$10)/(0.1*SQRT(Assumptions!$C$10)))-0.1*SQRT(Assumptions!$C$10)) -> 383.2533 | D29: =2850*EXP(-Assumptions!$C$11*Assumptions!$C$10)*NORMSDIST((LN(2850/Assumptions!$C$7)+(Assumptions!$C$9-Assumptions!$C$11+0.15^2/2)*Assumptions!$C$10)/(0.15*SQRT(Assumptions!$C$10)))-Assumptions!$C$7*EXP(-Assumptions!$C$9*Assumptions!$C$10)*NORMSDIST(((LN(2850/Assumptions!$C$7)+(Assumptions!$C$9-Assumptions!$C$11+0.15^2/2)*Assumptions!$C$10)/(0.15*SQRT(Assumptions!$C$10)))-0.15*SQRT(Assumptions!$C$10)) -> 385.20476 | E29: =2850*EXP(-Assumptions!$C$11*Assumptions!$C$10)*NORMSDIST((LN(2850/Assumptions!$C$7)+(Assumptions!$C$9-Assumptions!$C$11+0.2^2/2)*Assumptions!$C$10)/(0.2*SQRT(Assumptions!$C$10)))-Assumptions!$C$7*EXP(-Assumptions!$C$9*Assumptions!$C$10)*NORMSDIST(((LN(2850/Assumptions!$C$7)+(Assumptions!$C$9-Assumptions!$C$11+0.2^2/2)*Assumptions!$C$10)/(0.2*SQRT(Assumptions!$C$10)))-0.2*SQRT(Assumptions!$C$10)) -> 391.893 | F29: =2850*EXP(-Assumptions!$C$11*Assumptions!$C$10)*NORMSDIST((LN(2850/Assumptions!$C$7)+(Assumptions!$C$9-Assumptions!$C$11+0.25^2/2)*Assumptions!$C$10)/(0.25*SQRT(Assumptions!$C$10)))-Assumptions!$C$7*EXP(-Assumptions!$C$9*Assumptions!$C$10)*NORMSDIST(((LN(2850/Assumptions!$C$7)+(Assumptions!$C$9-Assumptions!$C$11+0.25^2/2)*Assumptions!$C$10)/(0.25*SQRT(Assumptions!$C$10)))-0.25*SQRT(Assumptions!$C$10)) -> 403.3446 | G29: =2850*EXP(-Assumptions!$C$11*Assumptions!$C$10)*NORMSDIST((LN(2850/Assumptions!$C$7)+(Assumptions!$C$9-Assumptions!$C$11+0.3^2/2)*Assumptions!$C$10)/(0.3*SQRT(Assumptions!$C$10)))-Assumptions!$C$7*EXP(-Assumptions!$C$9*Assumptions!$C$10)*NORMSDIST(((LN(2850/Assumptions!$C$7)+(Assumptions!$C$9-Assumptions!$C$11+0.3^2/2)*Assumptions!$C$10)/(0.3*SQRT(Assumptions!$C$10)))-0.3*SQRT(Assumptions!$C$10)) -> 418.41539 | H29: =2850*EXP(-Assumptions!$C$11*Assumptions!$C$10)*NORMSDIST((LN(2850/Assumptions!$C$7)+(Assumptions!$C$9-Assumptions!$C$11+0.35^2/2)*Assumptions!$C$10)/(0.35*SQRT(Assumptions!$C$10)))-Assumptions!$C$7*EXP(-Assumptions!$C$9*Assumptions!$C$10)*NORMSDIST(((LN(2850/Assumptions!$C$7)+(Assumptions!$C$9-Assumptions!$C$11+0.35^2/2)*Assumptions!$C$10)/(0.35*SQRT(Assumptions!$C$10)))-0.35*SQRT(Assumptions!$C$10)) -> 436.05997 | I29: =2850*EXP(-Assumptions!$C$11*Assumptions!$C$10)*NORMSDIST((LN(2850/Assumptions!$C$7)+(Assumptions!$C$9-Assumptions!$C$11+0.4^2/2)*Assumptions!$C$10)/(0.4*SQRT(Assumptions!$C$10)))-Assumptions!$C$7*EXP(-Assumptions!$C$9*Assumptions!$C$10)*NORMSDIST(((LN(2850/Assumptions!$C$7)+(Assumptions!$C$9-Assumptions!$C$11+0.4^2/2)*Assumptions!$C$10)/(0.4*SQRT(Assumptions!$C$10)))-0.4*SQRT(Assumptions!$C$10)) -> 455.52823 | J29: =2850*EXP(-Assumptions!$C$11*Assumptions!$C$10)*NORMSDIST((LN(2850/Assumptions!$C$7)+(Assumptions!$C$9-Assumptions!$C$11+0.45^2/2)*Assumptions!$C$10)/(0.45*SQRT(Assumptions!$C$10)))-Assumptions!$C$7*EXP(-Assumptions!$C$9*Assumptions!$C$10)*NORMSDIST(((LN(2850/Assumptions!$C$7)+(Assumptions!$C$9-Assumptions!$C$11+0.45^2/2)*Assumptions!$C$10)/(0.45*SQRT(Assumptions!$C$10)))-0.45*SQRT(Assumptions!$C$10)) -> 476.30714 | K29: =2850*EXP(-Assumptions!$C$11*Assumptions!$C$10)*NORMSDIST((LN(2850/Assumptions!$C$7)+(Assumptions!$C$9-Assumptions!$C$11+0.5^2/2)*Assumptions!$C$10)/(0.5*SQRT(Assumptions!$C$10)))-Assumptions!$C$7*EXP(-Assumptions!$C$9*Assumptions!$C$10)*NORMSDIST(((LN(2850/Assumptions!$C$7)+(Assumptions!$C$9-Assumptions!$C$11+0.5^2/2)*Assumptions!$C$10)/(0.5*SQRT(Assumptions!$C$10)))-0.5*SQRT(Assumptions!$C$10)) -> 498.04492
B30: 2900 | C30: =2900*EXP(-Assumptions!$C$11*Assumptions!$C$10)*NORMSDIST((LN(2900/Assumptions!$C$7)+(Assumptions!$C$9-Assumptions!$C$11+0.1^2/2)*Assumptions!$C$10)/(0.1*SQRT(Assumptions!$C$10)))-Assumptions!$C$7*EXP(-Assumptions!$C$9*Assumptions!$C$10)*NORMSDIST(((LN(2900/Assumptions!$C$7)+(Assumptions!$C$9-Assumptions!$C$11+0.1^2/2)*Assumptions!$C$10)/(0.1*SQRT(Assumptions!$C$10)))-0.1*SQRT(Assumptions!$C$10)) -> 433.07677 | D30: =2900*EXP(-Assumptions!$C$11*Assumptions!$C$10)*NORMSDIST((LN(2900/Assumptions!$C$7)+(Assumptions!$C$9-Assumptions!$C$11+0.15^2/2)*Assumptions!$C$10)/(0.15*SQRT(Assumptions!$C$10)))-Assumptions!$C$7*EXP(-Assumptions!$C$9*Assumptions!$C$10)*NORMSDIST(((LN(2900/Assumptions!$C$7)+(Assumptions!$C$9-Assumptions!$C$11+0.15^2/2)*Assumptions!$C$10)/(0.15*SQRT(Assumptions!$C$10)))-0.15*SQRT(Assumptions!$C$10)) -> 434.14299 | E30: =2900*EXP(-Assumptions!$C$11*Assumptions!$C$10)*NORMSDIST((LN(2900/Assumptions!$C$7)+(Assumptions!$C$9-Assumptions!$C$11+0.2^2/2)*Assumptions!$C$10)/(0.2*SQRT(Assumptions!$C$10)))-Assumptions!$C$7*EXP(-Assumptions!$C$9*Assumptions!$C$10)*NORMSDIST(((LN(2900/Assumptions!$C$7)+(Assumptions!$C$9-Assumptions!$C$11+0.2^2/2)*Assumptions!$C$10)/(0.2*SQRT(Assumptions!$C$10)))-0.2*SQRT(Assumptions!$C$10)) -> 438.93969 | F30: =2900*EXP(-Assumptions!$C$11*Assumptions!$C$10)*NORMSDIST((LN(2900/Assumptions!$C$7)+(Assumptions!$C$9-Assumptions!$C$11+0.25^2/2)*Assumptions!$C$10)/(0.25*SQRT(Assumptions!$C$10)))-Assumptions!$C$7*EXP(-Assumptions!$C$9*Assumptions!$C$10)*NORMSDIST(((LN(2900/Assumptions!$C$7)+(Assumptions!$C$9-Assumptions!$C$11+0.25^2/2)*Assumptions!$C$10)/(0.25*SQRT(Assumptions!$C$10)))-0.25*SQRT(Assumptions!$C$10)) -> 448.30107 | G30: =2900*EXP(-Assumptions!$C$11*Assumptions!$C$10)*NORMSDIST((LN(2900/Assumptions!$C$7)+(Assumptions!$C$9-Assumptions!$C$11+0.3^2/2)*Assumptions!$C$10)/(0.3*SQRT(Assumptions!$C$10)))-Assumptions!$C$7*EXP(-Assumptions!$C$9*Assumptions!$C$10)*NORMSDIST(((LN(2900/Assumptions!$C$7)+(Assumptions!$C$9-Assumptions!$C$11+0.3^2/2)*Assumptions!$C$10)/(0.3*SQRT(Assumptions!$C$10)))-0.3*SQRT(Assumptions!$C$10)) -> 461.49931 | H30: =2900*EXP(-Assumptions!$C$11*Assumptions!$C$10)*NORMSDIST((LN(2900/Assumptions!$C$7)+(Assumptions!$C$9-Assumptions!$C$11+0.35^2/2)*Assumptions!$C$10)/(0.35*SQRT(Assumptions!$C$10)))-Assumptions!$C$7*EXP(-Assumptions!$C$9*Assumptions!$C$10)*NORMSDIST(((LN(2900/Assumptions!$C$7)+(Assumptions!$C$9-Assumptions!$C$11+0.35^2/2)*Assumptions!$C$10)/(0.35*SQRT(Assumptions!$C$10)))-0.35*SQRT(Assumptions!$C$10)) -> 477.58292 | I30: =2900*EXP(-Assumptions!$C$11*Assumptions!$C$10)*NORMSDIST((LN(2900/Assumptions!$C$7)+(Assumptions!$C$9-Assumptions!$C$11+0.4^2/2)*Assumptions!$C$10)/(0.4*SQRT(Assumptions!$C$10)))-Assumptions!$C$7*EXP(-Assumptions!$C$9*Assumptions!$C$10)*NORMSDIST(((LN(2900/Assumptions!$C$7)+(Assumptions!$C$9-Assumptions!$C$11+0.4^2/2)*Assumptions!$C$10)/(0.4*SQRT(Assumptions!$C$10)))-0.4*SQRT(Assumptions!$C$10)) -> 495.78198 | J30: =2900*EXP(-Assumptions!$C$11*Assumptions!$C$10)*NORMSDIST((LN(2900/Assumptions!$C$7)+(Assumptions!$C$9-Assumptions!$C$11+0.45^2/2)*Assumptions!$C$10)/(0.45*SQRT(Assumptions!$C$10)))-Assumptions!$C$7*EXP(-Assumptions!$C$9*Assumptions!$C$10)*NORMSDIST(((LN(2900/Assumptions!$C$7)+(Assumptions!$C$9-Assumptions!$C$11+0.45^2/2)*Assumptions!$C$10)/(0.45*SQRT(Assumptions!$C$10)))-0.45*SQRT(Assumptions!$C$10)) -> 515.53665 | K30: =2900*EXP(-Assumptions!$C$11*Assumptions!$C$10)*NORMSDIST((LN(2900/Assumptions!$C$7)+(Assumptions!$C$9-Assumptions!$C$11+0.5^2/2)*Assumptions!$C$10)/(0.5*SQRT(Assumptions!$C$10)))-Assumptions!$C$7*EXP(-Assumptions!$C$9*Assumptions!$C$10)*NORMSDIST(((LN(2900/Assumptions!$C$7)+(Assumptions!$C$9-Assumptions!$C$11+0.5^2/2)*Assumptions!$C$10)/(0.5*SQRT(Assumptions!$C$10)))-0.5*SQRT(Assumptions!$C$10)) -> 536.44881
B31: 2950 | C31: =2950*EXP(-Assumptions!$C$11*Assumptions!$C$10)*NORMSDIST((LN(2950/Assumptions!$C$7)+(Assumptions!$C$9-Assumptions!$C$11+0.1^2/2)*Assumptions!$C$10)/(0.1*SQRT(Assumptions!$C$10)))-Assumptions!$C$7*EXP(-Assumptions!$C$9*Assumptions!$C$10)*NORMSDIST(((LN(2950/Assumptions!$C$7)+(Assumptions!$C$9-Assumptions!$C$11+0.1^2/2)*Assumptions!$C$10)/(0.1*SQRT(Assumptions!$C$10)))-0.1*SQRT(Assumptions!$C$10)) -> 482.9365 | D31: =2950*EXP(-Assumptions!$C$11*Assumptions!$C$10)*NORMSDIST((LN(2950/Assumptions!$C$7)+(Assumptions!$C$9-Assumptions!$C$11+0.15^2/2)*Assumptions!$C$10)/(0.15*SQRT(Assumptions!$C$10)))-Assumptions!$C$7*EXP(-Assumptions!$C$9*Assumptions!$C$10)*NORMSDIST(((LN(2950/Assumptions!$C$7)+(Assumptions!$C$9-Assumptions!$C$11+0.15^2/2)*Assumptions!$C$10)/(0.15*SQRT(Assumptions!$C$10)))-0.15*SQRT(Assumptions!$C$10)) -> 483.49595 | E31: =2950*EXP(-Assumptions!$C$11*Assumptions!$C$10)*NORMSDIST((LN(2950/Assumptions!$C$7)+(Assumptions!$C$9-Assumptions!$C$11+0.2^2/2)*Assumptions!$C$10)/(0.2*SQRT(Assumptions!$C$10)))-Assumptions!$C$7*EXP(-Assumptions!$C$9*Assumptions!$C$10)*NORMSDIST(((LN(2950/Assumptions!$C$7)+(Assumptions!$C$9-Assumptions!$C$11+0.2^2/2)*Assumptions!$C$10)/(0.2*SQRT(Assumptions!$C$10)))-0.2*SQRT(Assumptions!$C$10)) -> 486.8395 | F31: =2950*EXP(-Assumptions!$C$11*Assumptions!$C$10)*NORMSDIST((LN(2950/Assumptions!$C$7)+(Assumptions!$C$9-Assumptions!$C$11+0.25^2/2)*Assumptions!$C$10)/(0.25*SQRT(Assumptions!$C$10)))-Assumptions!$C$7*EXP(-Assumptions!$C$9*Assumptions!$C$10)*NORMSDIST(((LN(2950/Assumptions!$C$7)+(Assumptions!$C$9-Assumptions!$C$11+0.25^2/2)*Assumptions!$C$10)/(0.25*SQRT(Assumptions!$C$10)))-0.25*SQRT(Assumptions!$C$10)) -> 494.34862 | G31: =2950*EXP(-Assumptions!$C$11*Assumptions!$C$10)*NORMSDIST((LN(2950/Assumptions!$C$7)+(Assumptions!$C$9-Assumptions!$C$11+0.3^2/2)*Assumptions!$C$10)/(0.3*SQRT(Assumptions!$C$10)))-Assumptions!$C$7*EXP(-Assumptions!$C$9*Assumptions!$C$10)*NORMSDIST(((LN(2950/Assumptions!$C$7)+(Assumptions!$C$9-Assumptions!$C$11+0.3^2/2)*Assumptions!$C$10)/(0.3*SQRT(Assumptions!$C$10)))-0.3*SQRT(Assumptions!$C$10)) -> 505.75666 | H31: =2950*EXP(-Assumptions!$C$11*Assumptions!$C$10)*NORMSDIST((LN(2950/Assumptions!$C$7)+(Assumptions!$C$9-Assumptions!$C$11+0.35^2/2)*Assumptions!$C$10)/(0.35*SQRT(Assumptions!$C$10)))-Assumptions!$C$7*EXP(-Assumptions!$C$9*Assumptions!$C$10)*NORMSDIST(((LN(2950/Assumptions!$C$7)+(Assumptions!$C$9-Assumptions!$C$11+0.35^2/2)*Assumptions!$C$10)/(0.35*SQRT(Assumptions!$C$10)))-0.35*SQRT(Assumptions!$C$10)) -> 520.27859 | I31: =2950*EXP(-Assumptions!$C$11*Assumptions!$C$10)*NORMSDIST((LN(2950/Assumptions!$C$7)+(Assumptions!$C$9-Assumptions!$C$11+0.4^2/2)*Assumptions!$C$10)/(0.4*SQRT(Assumptions!$C$10)))-Assumptions!$C$7*EXP(-Assumptions!$C$9*Assumptions!$C$10)*NORMSDIST(((LN(2950/Assumptions!$C$7)+(Assumptions!$C$9-Assumptions!$C$11+0.4^2/2)*Assumptions!$C$10)/(0.4*SQRT(Assumptions!$C$10)))-0.4*SQRT(Assumptions!$C$10)) -> 537.16892 | J31: =2950*EXP(-Assumptions!$C$11*Assumptions!$C$10)*NORMSDIST((LN(2950/Assumptions!$C$7)+(Assumptions!$C$9-Assumptions!$C$11+0.45^2/2)*Assumptions!$C$10)/(0.45*SQRT(Assumptions!$C$10)))-Assumptions!$C$7*EXP(-Assumptions!$C$9*Assumptions!$C$10)*NORMSDIST(((LN(2950/Assumptions!$C$7)+(Assumptions!$C$9-Assumptions!$C$11+0.45^2/2)*Assumptions!$C$10)/(0.45*SQRT(Assumptions!$C$10)))-0.45*SQRT(Assumptions!$C$10)) -> 555.84383 | K31: =2950*EXP(-Assumptions!$C$11*Assumptions!$C$10)*NORMSDIST((LN(2950/Assumptions!$C$7)+(Assumptions!$C$9-Assumptions!$C$11+0.5^2/2)*Assumptions!$C$10)/(0.5*SQRT(Assumptions!$C$10)))-Assumptions!$C$7*EXP(-Assumptions!$C$9*Assumptions!$C$10)*NORMSDIST(((LN(2950/Assumptions!$C$7)+(Assumptions!$C$9-Assumptions!$C$11+0.5^2/2)*Assumptions!$C$10)/(0.5*SQRT(Assumptions!$C$10)))-0.5*SQRT(Assumptions!$C$10)) -> 575.87012
B32: 3000 | C32: =3000*EXP(-Assumptions!$C$11*Assumptions!$C$10)*NORMSDIST((LN(3000/Assumptions!$C$7)+(Assumptions!$C$9-Assumptions!$C$11+0.1^2/2)*Assumptions!$C$10)/(0.1*SQRT(Assumptions!$C$10)))-Assumptions!$C$7*EXP(-Assumptions!$C$9*Assumptions!$C$10)*NORMSDIST(((LN(3000/Assumptions!$C$7)+(Assumptions!$C$9-Assumptions!$C$11+0.1^2/2)*Assumptions!$C$10)/(0.1*SQRT(Assumptions!$C$10)))-0.1*SQRT(Assumptions!$C$10)) -> 532.80744 | D32: =3000*EXP(-Assumptions!$C$11*Assumptions!$C$10)*NORMSDIST((LN(3000/Assumptions!$C$7)+(Assumptions!$C$9-Assumptions!$C$11+0.15^2/2)*Assumptions!$C$10)/(0.15*SQRT(Assumptions!$C$10)))-Assumptions!$C$7*EXP(-Assumptions!$C$9*Assumptions!$C$10)*NORMSDIST(((LN(3000/Assumptions!$C$7)+(Assumptions!$C$9-Assumptions!$C$11+0.15^2/2)*Assumptions!$C$10)/(0.15*SQRT(Assumptions!$C$10)))-0.15*SQRT(Assumptions!$C$10)) -> 533.0905 | E32: =3000*EXP(-Assumptions!$C$11*Assumptions!$C$10)*NORMSDIST((LN(3000/Assumptions!$C$7)+(Assumptions!$C$9-Assumptions!$C$11+0.2^2/2)*Assumptions!$C$10)/(0.2*SQRT(Assumptions!$C$10)))-Assumptions!$C$7*EXP(-Assumptions!$C$9*Assumptions!$C$10)*NORMSDIST(((LN(3000/Assumptions!$C$7)+(Assumptions!$C$9-Assumptions!$C$11+0.2^2/2)*Assumptions!$C$10)/(0.2*SQRT(Assumptions!$C$10)))-0.2*SQRT(Assumptions!$C$10)) -> 535.36122 | F32: =3000*EXP(-Assumptions!$C$11*Assumptions!$C$10)*NORMSDIST((LN(3000/Assumptions!$C$7)+(Assumptions!$C$9-Assumptions!$C$11+0.25^2/2)*Assumptions!$C$10)/(0.25*SQRT(Assumptions!$C$10)))-Assumptions!$C$7*EXP(-Assumptions!$C$9*Assumptions!$C$10)*NORMSDIST(((LN(3000/Assumptions!$C$7)+(Assumptions!$C$9-Assumptions!$C$11+0.25^2/2)*Assumptions!$C$10)/(0.25*SQRT(Assumptions!$C$10)))-0.25*SQRT(Assumptions!$C$10)) -> 541.27898 | G32: =3000*EXP(-Assumptions!$C$11*Assumptions!$C$10)*NORMSDIST((LN(3000/Assumptions!$C$7)+(Assumptions!$C$9-Assumptions!$C$11+0.3^2/2)*Assumptions!$C$10)/(0.3*SQRT(Assumptions!$C$10)))-Assumptions!$C$7*EXP(-Assumptions!$C$9*Assumptions!$C$10)*NORMSDIST(((LN(3000/Assumptions!$C$7)+(Assumptions!$C$9-Assumptions!$C$11+0.3^2/2)*Assumptions!$C$10)/(0.3*SQRT(Assumptions!$C$10)))-0.3*SQRT(Assumptions!$C$10)) -> 551.01892 | H32: =3000*EXP(-Assumptions!$C$11*Assumptions!$C$10)*NORMSDIST((LN(3000/Assumptions!$C$7)+(Assumptions!$C$9-Assumptions!$C$11+0.35^2/2)*Assumptions!$C$10)/(0.35*SQRT(Assumptions!$C$10)))-Assumptions!$C$7*EXP(-Assumptions!$C$9*Assumptions!$C$10)*NORMSDIST(((LN(3000/Assumptions!$C$7)+(Assumptions!$C$9-Assumptions!$C$11+0.35^2/2)*Assumptions!$C$10)/(0.35*SQRT(Assumptions!$C$10)))-0.35*SQRT(Assumptions!$C$10)) -> 564.01359 | I32: =3000*EXP(-Assumptions!$C$11*Assumptions!$C$10)*NORMSDIST((LN(3000/Assumptions!$C$7)+(Assumptions!$C$9-Assumptions!$C$11+0.4^2/2)*Assumptions!$C$10)/(0.4*SQRT(Assumptions!$C$10)))-Assumptions!$C$7*EXP(-Assumptions!$C$9*Assumptions!$C$10)*NORMSDIST(((LN(3000/Assumptions!$C$7)+(Assumptions!$C$9-Assumptions!$C$11+0.4^2/2)*Assumptions!$C$10)/(0.4*SQRT(Assumptions!$C$10)))-0.4*SQRT(Assumptions!$C$10)) -> 579.58278 | J32: =3000*EXP(-Assumptions!$C$11*Assumptions!$C$10)*NORMSDIST((LN(3000/Assumptions!$C$7)+(Assumptions!$C$9-Assumptions!$C$11+0.45^2/2)*Assumptions!$C$10)/(0.45*SQRT(Assumptions!$C$10)))-Assumptions!$C$7*EXP(-Assumptions!$C$9*Assumptions!$C$10)*NORMSDIST(((LN(3000/Assumptions!$C$7)+(Assumptions!$C$9-Assumptions!$C$11+0.45^2/2)*Assumptions!$C$10)/(0.45*SQRT(Assumptions!$C$10)))-0.45*SQRT(Assumptions!$C$10)) -> 597.14267 | K32: =3000*EXP(-Assumptions!$C$11*Assumptions!$C$10)*NORMSDIST((LN(3000/Assumptions!$C$7)+(Assumptions!$C$9-Assumptions!$C$11+0.5^2/2)*Assumptions!$C$10)/(0.5*SQRT(Assumptions!$C$10)))-Assumptions!$C$7*EXP(-Assumptions!$C$9*Assumptions!$C$10)*NORMSDIST(((LN(3000/Assumptions!$C$7)+(Assumptions!$C$9-Assumptions!$C$11+0.5^2/2)*Assumptions!$C$10)/(0.5*SQRT(Assumptions!$C$10)))-0.5*SQRT(Assumptions!$C$10)) -> 616.2379
B33: 3050 | C33: =3050*EXP(-Assumptions!$C$11*Assumptions!$C$10)*NORMSDIST((LN(3050/Assumptions!$C$7)+(Assumptions!$C$9-Assumptions!$C$11+0.1^2/2)*Assumptions!$C$10)/(0.1*SQRT(Assumptions!$C$10)))-Assumptions!$C$7*EXP(-Assumptions!$C$9*Assumptions!$C$10)*NORMSDIST(((LN(3050/Assumptions!$C$7)+(Assumptions!$C$9-Assumptions!$C$11+0.1^2/2)*Assumptions!$C$10)/(0.1*SQRT(Assumptions!$C$10)))-0.1*SQRT(Assumptions!$C$10)) -> 582.68154 | D33: =3050*EXP(-Assumptions!$C$11*Assumptions!$C$10)*NORMSDIST((LN(3050/Assumptions!$C$7)+(Assumptions!$C$9-Assumptions!$C$11+0.15^2/2)*Assumptions!$C$10)/(0.15*SQRT(Assumptions!$C$10)))-Assumptions!$C$7*EXP(-Assumptions!$C$9*Assumptions!$C$10)*NORMSDIST(((LN(3050/Assumptions!$C$7)+(Assumptions!$C$9-Assumptions!$C$11+0.15^2/2)*Assumptions!$C$10)/(0.15*SQRT(Assumptions!$C$10)))-0.15*SQRT(Assumptions!$C$10)) -> 582.82006 | E33: =3050*EXP(-Assumptions!$C$11*Assumptions!$C$10)*NORMSDIST((LN(3050/Assumptions!$C$7)+(Assumptions!$C$9-Assumptions!$C$11+0.2^2/2)*Assumptions!$C$10)/(0.2*SQRT(Assumptions!$C$10)))-Assumptions!$C$7*EXP(-Assumptions!$C$9*Assumptions!$C$10)*NORMSDIST(((LN(3050/Assumptions!$C$7)+(Assumptions!$C$9-Assumptions!$C$11+0.2^2/2)*Assumptions!$C$10)/(0.2*SQRT(Assumptions!$C$10)))-0.2*SQRT(Assumptions!$C$10)) -> 584.32593 | F33: =3050*EXP(-Assumptions!$C$11*Assumptions!$C$10)*NORMSDIST((LN(3050/Assumptions!$C$7)+(Assumptions!$C$9-Assumptions!$C$11+0.25^2/2)*Assumptions!$C$10)/(0.25*SQRT(Assumptions!$C$10)))-Assumptions!$C$7*EXP(-Assumptions!$C$9*Assumptions!$C$10)*NORMSDIST(((LN(3050/Assumptions!$C$7)+(Assumptions!$C$9-Assumptions!$C$11+0.25^2/2)*Assumptions!$C$10)/(0.25*SQRT(Assumptions!$C$10)))-0.25*SQRT(Assumptions!$C$10)) -> 588.91324 | G33: =3050*EXP(-Assumptions!$C$11*Assumptions!$C$10)*NORMSDIST((LN(3050/Assumptions!$C$7)+(Assumptions!$C$9-Assumptions!$C$11+0.3^2/2)*Assumptions!$C$10)/(0.3*SQRT(Assumptions!$C$10)))-Assumptions!$C$7*EXP(-Assumptions!$C$9*Assumptions!$C$10)*NORMSDIST(((LN(3050/Assumptions!$C$7)+(Assumptions!$C$9-Assumptions!$C$11+0.3^2/2)*Assumptions!$C$10)/(0.3*SQRT(Assumptions!$C$10)))-0.3*SQRT(Assumptions!$C$10)) -> 597.13317 | H33: =3050*EXP(-Assumptions!$C$11*Assumptions!$C$10)*NORMSDIST((LN(3050/Assumptions!$C$7)+(Assumptions!$C$9-Assumptions!$C$11+0.35^2/2)*Assumptions!$C$10)/(0.35*SQRT(Assumptions!$C$10)))-Assumptions!$C$7*EXP(-Assumptions!$C$9*Assumptions!$C$10)*NORMSDIST(((LN(3050/Assumptions!$C$7)+(Assumptions!$C$9-Assumptions!$C$11+0.35^2/2)*Assumptions!$C$10)/(0.35*SQRT(Assumptions!$C$10)))-0.35*SQRT(Assumptions!$C$10)) -> 608.66304 | I33: =3050*EXP(-Assumptions!$C$11*Assumptions!$C$10)*NORMSDIST((LN(3050/Assumptions!$C$7)+(Assumptions!$C$9-Assumptions!$C$11+0.4^2/2)*Assumptions!$C$10)/(0.4*SQRT(Assumptions!$C$10)))-Assumptions!$C$7*EXP(-Assumptions!$C$9*Assumptions!$C$10)*NORMSDIST(((LN(3050/Assumptions!$C$7)+(Assumptions!$C$9-Assumptions!$C$11+0.4^2/2)*Assumptions!$C$10)/(0.4*SQRT(Assumptions!$C$10)))-0.4*SQRT(Assumptions!$C$10)) -> 622.92216 | J33: =3050*EXP(-Assumptions!$C$11*Assumptions!$C$10)*NORMSDIST((LN(3050/Assumptions!$C$7)+(Assumptions!$C$9-Assumptions!$C$11+0.45^2/2)*Assumptions!$C$10)/(0.45*SQRT(Assumptions!$C$10)))-Assumptions!$C$7*EXP(-Assumptions!$C$9*Assumptions!$C$10)*NORMSDIST(((LN(3050/Assumptions!$C$7)+(Assumptions!$C$9-Assumptions!$C$11+0.45^2/2)*Assumptions!$C$10)/(0.45*SQRT(Assumptions!$C$10)))-0.45*SQRT(Assumptions!$C$10)) -> 639.35012 | K33: =3050*EXP(-Assumptions!$C$11*Assumptions!$C$10)*NORMSDIST((LN(3050/Assumptions!$C$7)+(Assumptions!$C$9-Assumptions!$C$11+0.5^2/2)*Assumptions!$C$10)/(0.5*SQRT(Assumptions!$C$10)))-Assumptions!$C$7*EXP(-Assumptions!$C$9*Assumptions!$C$10)*NORMSDIST(((LN(3050/Assumptions!$C$7)+(Assumptions!$C$9-Assumptions!$C$11+0.5^2/2)*Assumptions!$C$10)/(0.5*SQRT(Assumptions!$C$10)))-0.5*SQRT(Assumptions!$C$10)) -> 657.48323
B34: 3100 | C34: =3100*EXP(-Assumptions!$C$11*Assumptions!$C$10)*NORMSDIST((LN(3100/Assumptions!$C$7)+(Assumptions!$C$9-Assumptions!$C$11+0.1^2/2)*Assumptions!$C$10)/(0.1*SQRT(Assumptions!$C$10)))-Assumptions!$C$7*EXP(-Assumptions!$C$9*Assumptions!$C$10)*NORMSDIST(((LN(3100/Assumptions!$C$7)+(Assumptions!$C$9-Assumptions!$C$11+0.1^2/2)*Assumptions!$C$10)/(0.1*SQRT(Assumptions!$C$10)))-0.1*SQRT(Assumptions!$C$10)) -> 632.55645 | D34: =3100*EXP(-Assumptions!$C$11*Assumptions!$C$10)*NORMSDIST((LN(3100/Assumptions!$C$7)+(Assumptions!$C$9-Assumptions!$C$11+0.15^2/2)*Assumptions!$C$10)/(0.15*SQRT(Assumptions!$C$10)))-Assumptions!$C$7*EXP(-Assumptions!$C$9*Assumptions!$C$10)*NORMSDIST(((LN(3100/Assumptions!$C$7)+(Assumptions!$C$9-Assumptions!$C$11+0.15^2/2)*Assumptions!$C$10)/(0.15*SQRT(Assumptions!$C$10)))-0.15*SQRT(Assumptions!$C$10)) -> 632.62217 | E34: =3100*EXP(-Assumptions!$C$11*Assumptions!$C$10)*NORMSDIST((LN(3100/Assumptions!$C$7)+(Assumptions!$C$9-Assumptions!$C$11+0.2^2/2)*Assumptions!$C$10)/(0.2*SQRT(Assumptions!$C$10)))-Assumptions!$C$7*EXP(-Assumptions!$C$9*Assumptions!$C$10)*NORMSDIST(((LN(3100/Assumptions!$C$7)+(Assumptions!$C$9-Assumptions!$C$11+0.2^2/2)*Assumptions!$C$10)/(0.2*SQRT(Assumptions!$C$10)))-0.2*SQRT(Assumptions!$C$10)) -> 633.59934 | F34: =3100*EXP(-Assumptions!$C$11*Assumptions!$C$10)*NORMSDIST((LN(3100/Assumptions!$C$7)+(Assumptions!$C$9-Assumptions!$C$11+0.25^2/2)*Assumptions!$C$10)/(0.25*SQRT(Assumptions!$C$10)))-Assumptions!$C$7*EXP(-Assumptions!$C$9*Assumptions!$C$10)*NORMSDIST(((LN(3100/Assumptions!$C$7)+(Assumptions!$C$9-Assumptions!$C$11+0.25^2/2)*Assumptions!$C$10)/(0.25*SQRT(Assumptions!$C$10)))-0.25*SQRT(Assumptions!$C$10)) -> 637.10102 | G34: =3100*EXP(-Assumptions!$C$11*Assumptions!$C$10)*NORMSDIST((LN(3100/Assumptions!$C$7)+(Assumptions!$C$9-Assumptions!$C$11+0.3^2/2)*Assumptions!$C$10)/(0.3*SQRT(Assumptions!$C$10)))-Assumptions!$C$7*EXP(-Assumptions!$C$9*Assumptions!$C$10)*NORMSDIST(((LN(3100/Assumptions!$C$7)+(Assumptions!$C$9-Assumptions!$C$11+0.3^2/2)*Assumptions!$C$10)/(0.3*SQRT(Assumptions!$C$10)))-0.3*SQRT(Assumptions!$C$10)) -> 643.96292 | H34: =3100*EXP(-Assumptions!$C$11*Assumptions!$C$10)*NORMSDIST((LN(3100/Assumptions!$C$7)+(Assumptions!$C$9-Assumptions!$C$11+0.35^2/2)*Assumptions!$C$10)/(0.35*SQRT(Assumptions!$C$10)))-Assumptions!$C$7*EXP(-Assumptions!$C$9*Assumptions!$C$10)*NORMSDIST(((LN(3100/Assumptions!$C$7)+(Assumptions!$C$9-Assumptions!$C$11+0.35^2/2)*Assumptions!$C$10)/(0.35*SQRT(Assumptions!$C$10)))-0.35*SQRT(Assumptions!$C$10)) -> 654.11152 | I34: =3100*EXP(-Assumptions!$C$11*Assumptions!$C$10)*NORMSDIST((LN(3100/Assumptions!$C$7)+(Assumptions!$C$9-Assumptions!$C$11+0.4^2/2)*Assumptions!$C$10)/(0.4*SQRT(Assumptions!$C$10)))-Assumptions!$C$7*EXP(-Assumptions!$C$9*Assumptions!$C$10)*NORMSDIST(((LN(3100/Assumptions!$C$7)+(Assumptions!$C$9-Assumptions!$C$11+0.4^2/2)*Assumptions!$C$10)/(0.4*SQRT(Assumptions!$C$10)))-0.4*SQRT(Assumptions!$C$10)) -> 667.09139 | J34: =3100*EXP(-Assumptions!$C$11*Assumptions!$C$10)*NORMSDIST((LN(3100/Assumptions!$C$7)+(Assumptions!$C$9-Assumptions!$C$11+0.45^2/2)*Assumptions!$C$10)/(0.45*SQRT(Assumptions!$C$10)))-Assumptions!$C$7*EXP(-Assumptions!$C$9*Assumptions!$C$10)*NORMSDIST(((LN(3100/Assumptions!$C$7)+(Assumptions!$C$9-Assumptions!$C$11+0.45^2/2)*Assumptions!$C$10)/(0.45*SQRT(Assumptions!$C$10)))-0.45*SQRT(Assumptions!$C$10)) -> 682.3868 | K34: =3100*EXP(-Assumptions!$C$11*Assumptions!$C$10)*NORMSDIST((LN(3100/Assumptions!$C$7)+(Assumptions!$C$9-Assumptions!$C$11+0.5^2/2)*Assumptions!$C$10)/(0.5*SQRT(Assumptions!$C$10)))-Assumptions!$C$7*EXP(-Assumptions!$C$9*Assumptions!$C$10)*NORMSDIST(((LN(3100/Assumptions!$C$7)+(Assumptions!$C$9-Assumptions!$C$11+0.5^2/2)*Assumptions!$C$10)/(0.5*SQRT(Assumptions!$C$10)))-0.5*SQRT(Assumptions!$C$10)) -> 699.53961
B35: 3150 | C35: =3150*EXP(-Assumptions!$C$11*Assumptions!$C$10)*NORMSDIST((LN(3150/Assumptions!$C$7)+(Assumptions!$C$9-Assumptions!$C$11+0.1^2/2)*Assumptions!$C$10)/(0.1*SQRT(Assumptions!$C$10)))-Assumptions!$C$7*EXP(-Assumptions!$C$9*Assumptions!$C$10)*NORMSDIST(((LN(3150/Assumptions!$C$7)+(Assumptions!$C$9-Assumptions!$C$11+0.1^2/2)*Assumptions!$C$10)/(0.1*SQRT(Assumptions!$C$10)))-0.1*SQRT(Assumptions!$C$10)) -> 682.43155 | D35: =3150*EXP(-Assumptions!$C$11*Assumptions!$C$10)*NORMSDIST((LN(3150/Assumptions!$C$7)+(Assumptions!$C$9-Assumptions!$C$11+0.15^2/2)*Assumptions!$C$10)/(0.15*SQRT(Assumptions!$C$10)))-Assumptions!$C$7*EXP(-Assumptions!$C$9*Assumptions!$C$10)*NORMSDIST(((LN(3150/Assumptions!$C$7)+(Assumptions!$C$9-Assumptions!$C$11+0.15^2/2)*Assumptions!$C$10)/(0.15*SQRT(Assumptions!$C$10)))-0.15*SQRT(Assumptions!$C$10)) -> 682.46183 | E35: =3150*EXP(-Assumptions!$C$11*Assumptions!$C$10)*NORMSDIST((LN(3150/Assumptions!$C$7)+(Assumptions!$C$9-Assumptions!$C$11+0.2^2/2)*Assumptions!$C$10)/(0.2*SQRT(Assumptions!$C$10)))-Assumptions!$C$7*EXP(-Assumptions!$C$9*Assumptions!$C$10)*NORMSDIST(((LN(3150/Assumptions!$C$7)+(Assumptions!$C$9-Assumptions!$C$11+0.2^2/2)*Assumptions!$C$10)/(0.2*SQRT(Assumptions!$C$10)))-0.2*SQRT(Assumptions!$C$10)) -> 683.08344 | F35: =3150*EXP(-Assumptions!$C$11*Assumptions!$C$10)*NORMSDIST((LN(3150/Assumptions!$C$7)+(Assumptions!$C$9-Assumptions!$C$11+0.25^2/2)*Assumptions!$C$10)/(0.25*SQRT(Assumptions!$C$10)))-Assumptions!$C$7*EXP(-Assumptions!$C$9*Assumptions!$C$10)*NORMSDIST(((LN(3150/Assumptions!$C$7)+(Assumptions!$C$9-Assumptions!$C$11+0.25^2/2)*Assumptions!$C$10)/(0.25*SQRT(Assumptions!$C$10)))-0.25*SQRT(Assumptions!$C$10)) -> 685.71837 | G35: =3150*EXP(-Assumptions!$C$11*Assumptions!$C$10)*NORMSDIST((LN(3150/Assumptions!$C$7)+(Assumptions!$C$9-Assumptions!$C$11+0.3^2/2)*Assumptions!$C$10)/(0.3*SQRT(Assumptions!$C$10)))-Assumptions!$C$7*EXP(-Assumptions!$C$9*Assumptions!$C$10)*NORMSDIST(((LN(3150/Assumptions!$C$7)+(Assumptions!$C$9-Assumptions!$C$11+0.3^2/2)*Assumptions!$C$10)/(0.3*SQRT(Assumptions!$C$10)))-0.3*SQRT(Assumptions!$C$10)) -> 691.38815 | H35: =3150*EXP(-Assumptions!$C$11*Assumptions!$C$10)*NORMSDIST((LN(3150/Assumptions!$C$7)+(Assumptions!$C$9-Assumptions!$C$11+0.35^2/2)*Assumptions!$C$10)/(0.35*SQRT(Assumptions!$C$10)))-Assumptions!$C$7*EXP(-Assumptions!$C$9*Assumptions!$C$10)*NORMSDIST(((LN(3150/Assumptions!$C$7)+(Assumptions!$C$9-Assumptions!$C$11+0.35^2/2)*Assumptions!$C$10)/(0.35*SQRT(Assumptions!$C$10)))-0.35*SQRT(Assumptions!$C$10)) -> 700.25369 | I35: =3150*EXP(-Assumptions!$C$11*Assumptions!$C$10)*NORMSDIST((LN(3150/Assumptions!$C$7)+(Assumptions!$C$9-Assumptions!$C$11+0.4^2/2)*Assumptions!$C$10)/(0.4*SQRT(Assumptions!$C$10)))-Assumptions!$C$7*EXP(-Assumptions!$C$9*Assumptions!$C$10)*NORMSDIST(((LN(3150/Assumptions!$C$7)+(Assumptions!$C$9-Assumptions!$C$11+0.4^2/2)*Assumptions!$C$10)/(0.4*SQRT(Assumptions!$C$10)))-0.4*SQRT(Assumptions!$C$10)) -> 712.00105 | J35: =3150*EXP(-Assumptions!$C$11*Assumptions!$C$10)*NORMSDIST((LN(3150/Assumptions!$C$7)+(Assumptions!$C$9-Assumptions!$C$11+0.45^2/2)*Assumptions!$C$10)/(0.45*SQRT(Assumptions!$C$10)))-Assumptions!$C$7*EXP(-Assumptions!$C$9*Assumptions!$C$10)*NORMSDIST(((LN(3150/Assumptions!$C$7)+(Assumptions!$C$9-Assumptions!$C$11+0.45^2/2)*Assumptions!$C$10)/(0.45*SQRT(Assumptions!$C$10)))-0.45*SQRT(Assumptions!$C$10)) -> 726.17739 | K35: =3150*EXP(-Assumptions!$C$11*Assumptions!$C$10)*NORMSDIST((LN(3150/Assumptions!$C$7)+(Assumptions!$C$9-Assumptions!$C$11+0.5^2/2)*Assumptions!$C$10)/(0.5*SQRT(Assumptions!$C$10)))-Assumptions!$C$7*EXP(-Assumptions!$C$9*Assumptions!$C$10)*NORMSDIST(((LN(3150/Assumptions!$C$7)+(Assumptions!$C$9-Assumptions!$C$11+0.5^2/2)*Assumptions!$C$10)/(0.5*SQRT(Assumptions!$C$10)))-0.5*SQRT(Assumptions!$C$10)) -> 742.34338
B36: 3200 | C36: =3200*EXP(-Assumptions!$C$11*Assumptions!$C$10)*NORMSDIST((LN(3200/Assumptions!$C$7)+(Assumptions!$C$9-Assumptions!$C$11+0.1^2/2)*Assumptions!$C$10)/(0.1*SQRT(Assumptions!$C$10)))-Assumptions!$C$7*EXP(-Assumptions!$C$9*Assumptions!$C$10)*NORMSDIST(((LN(3200/Assumptions!$C$7)+(Assumptions!$C$9-Assumptions!$C$11+0.1^2/2)*Assumptions!$C$10)/(0.1*SQRT(Assumptions!$C$10)))-0.1*SQRT(Assumptions!$C$10)) -> 732.3067 | D36: =3200*EXP(-Assumptions!$C$11*Assumptions!$C$10)*NORMSDIST((LN(3200/Assumptions!$C$7)+(Assumptions!$C$9-Assumptions!$C$11+0.15^2/2)*Assumptions!$C$10)/(0.15*SQRT(Assumptions!$C$10)))-Assumptions!$C$7*EXP(-Assumptions!$C$9*Assumptions!$C$10)*NORMSDIST(((LN(3200/Assumptions!$C$7)+(Assumptions!$C$9-Assumptions!$C$11+0.15^2/2)*Assumptions!$C$10)/(0.15*SQRT(Assumptions!$C$10)))-0.15*SQRT(Assumptions!$C$10)) -> 732.32027 | E36: =3200*EXP(-Assumptions!$C$11*Assumptions!$C$10)*NORMSDIST((LN(3200/Assumptions!$C$7)+(Assumptions!$C$9-Assumptions!$C$11+0.2^2/2)*Assumptions!$C$10)/(0.2*SQRT(Assumptions!$C$10)))-Assumptions!$C$7*EXP(-Assumptions!$C$9*Assumptions!$C$10)*NORMSDIST(((LN(3200/Assumptions!$C$7)+(Assumptions!$C$9-Assumptions!$C$11+0.2^2/2)*Assumptions!$C$10)/(0.2*SQRT(Assumptions!$C$10)))-0.2*SQRT(Assumptions!$C$10)) -> 732.70856 | F36: =3200*EXP(-Assumptions!$C$11*Assumptions!$C$10)*NORMSDIST((LN(3200/Assumptions!$C$7)+(Assumptions!$C$9-Assumptions!$C$11+0.25^2/2)*Assumptions!$C$10)/(0.25*SQRT(Assumptions!$C$10)))-Assumptions!$C$7*EXP(-Assumptions!$C$9*Assumptions!$C$10)*NORMSDIST(((LN(3200/Assumptions!$C$7)+(Assumptions!$C$9-Assumptions!$C$11+0.25^2/2)*Assumptions!$C$10)/(0.25*SQRT(Assumptions!$C$10)))-0.25*SQRT(Assumptions!$C$10)) -> 734.66497 | G36: =3200*EXP(-Assumptions!$C$11*Assumptions!$C$10)*NORMSDIST((LN(3200/Assumptions!$C$7)+(Assumptions!$C$9-Assumptions!$C$11+0.3^2/2)*Assumptions!$C$10)/(0.3*SQRT(Assumptions!$C$10)))-Assumptions!$C$7*EXP(-Assumptions!$C$9*Assumptions!$C$10)*NORMSDIST(((LN(3200/Assumptions!$C$7)+(Assumptions!$C$9-Assumptions!$C$11+0.3^2/2)*Assumptions!$C$10)/(0.3*SQRT(Assumptions!$C$10)))-0.3*SQRT(Assumptions!$C$10)) -> 739.30477 | H36: =3200*EXP(-Assumptions!$C$11*Assumptions!$C$10)*NORMSDIST((LN(3200/Assumptions!$C$7)+(Assumptions!$C$9-Assumptions!$C$11+0.35^2/2)*Assumptions!$C$10)/(0.35*SQRT(Assumptions!$C$10)))-Assumptions!$C$7*EXP(-Assumptions!$C$9*Assumptions!$C$10)*NORMSDIST(((LN(3200/Assumptions!$C$7)+(Assumptions!$C$9-Assumptions!$C$11+0.35^2/2)*Assumptions!$C$10)/(0.35*SQRT(Assumptions!$C$10)))-0.35*SQRT(Assumptions!$C$10)) -> 746.99435 | I36: =3200*EXP(-Assumptions!$C$11*Assumptions!$C$10)*NORMSDIST((LN(3200/Assumptions!$C$7)+(Assumptions!$C$9-Assumptions!$C$11+0.4^2/2)*Assumptions!$C$10)/(0.4*SQRT(Assumptions!$C$10)))-Assumptions!$C$7*EXP(-Assumptions!$C$9*Assumptions!$C$10)*NORMSDIST(((LN(3200/Assumptions!$C$7)+(Assumptions!$C$9-Assumptions!$C$11+0.4^2/2)*Assumptions!$C$10)/(0.4*SQRT(Assumptions!$C$10)))-0.4*SQRT(Assumptions!$C$10)) -> 757.56832 | J36: =3200*EXP(-Assumptions!$C$11*Assumptions!$C$10)*NORMSDIST((LN(3200/Assumptions!$C$7)+(Assumptions!$C$9-Assumptions!$C$11+0.45^2/2)*Assumptions!$C$10)/(0.45*SQRT(Assumptions!$C$10)))-Assumptions!$C$7*EXP(-Assumptions!$C$9*Assumptions!$C$10)*NORMSDIST(((LN(3200/Assumptions!$C$7)+(Assumptions!$C$9-Assumptions!$C$11+0.45^2/2)*Assumptions!$C$10)/(0.45*SQRT(Assumptions!$C$10)))-0.45*SQRT(Assumptions!$C$10)) -> 770.65098 | K36: =3200*EXP(-Assumptions!$C$11*Assumptions!$C$10)*NORMSDIST((LN(3200/Assumptions!$C$7)+(Assumptions!$C$9-Assumptions!$C$11+0.5^2/2)*Assumptions!$C$10)/(0.5*SQRT(Assumptions!$C$10)))-Assumptions!$C$7*EXP(-Assumptions!$C$9*Assumptions!$C$10)*NORMSDIST(((LN(3200/Assumptions!$C$7)+(Assumptions!$C$9-Assumptions!$C$11+0.5^2/2)*Assumptions!$C$10)/(0.5*SQRT(Assumptions!$C$10)))-0.5*SQRT(Assumptions!$C$10)) -> 785.83391
B37: 3250 | C37: =3250*EXP(-Assumptions!$C$11*Assumptions!$C$10)*NORMSDIST((LN(3250/Assumptions!$C$7)+(Assumptions!$C$9-Assumptions!$C$11+0.1^2/2)*Assumptions!$C$10)/(0.1*SQRT(Assumptions!$C$10)))-Assumptions!$C$7*EXP(-Assumptions!$C$9*Assumptions!$C$10)*NORMSDIST(((LN(3250/Assumptions!$C$7)+(Assumptions!$C$9-Assumptions!$C$11+0.1^2/2)*Assumptions!$C$10)/(0.1*SQRT(Assumptions!$C$10)))-0.1*SQRT(Assumptions!$C$10)) -> 782.18185 | D37: =3250*EXP(-Assumptions!$C$11*Assumptions!$C$10)*NORMSDIST((LN(3250/Assumptions!$C$7)+(Assumptions!$C$9-Assumptions!$C$11+0.15^2/2)*Assumptions!$C$10)/(0.15*SQRT(Assumptions!$C$10)))-Assumptions!$C$7*EXP(-Assumptions!$C$9*Assumptions!$C$10)*NORMSDIST(((LN(3250/Assumptions!$C$7)+(Assumptions!$C$9-Assumptions!$C$11+0.15^2/2)*Assumptions!$C$10)/(0.15*SQRT(Assumptions!$C$10)))-0.15*SQRT(Assumptions!$C$10)) -> 782.18777 | E37: =3250*EXP(-Assumptions!$C$11*Assumptions!$C$10)*NORMSDIST((LN(3250/Assumptions!$C$7)+(Assumptions!$C$9-Assumptions!$C$11+0.2^2/2)*Assumptions!$C$10)/(0.2*SQRT(Assumptions!$C$10)))-Assumptions!$C$7*EXP(-Assumptions!$C$9*Assumptions!$C$10)*NORMSDIST(((LN(3250/Assumptions!$C$7)+(Assumptions!$C$9-Assumptions!$C$11+0.2^2/2)*Assumptions!$C$10)/(0.2*SQRT(Assumptions!$C$10)))-0.2*SQRT(Assumptions!$C$10)) -> 782.4263 | F37: =3250*EXP(-Assumptions!$C$11*Assumptions!$C$10)*NORMSDIST((LN(3250/Assumptions!$C$7)+(Assumptions!$C$9-Assumptions!$C$11+0.25^2/2)*Assumptions!$C$10)/(0.25*SQRT(Assumptions!$C$10)))-Assumptions!$C$7*EXP(-Assumptions!$C$9*Assumptions!$C$10)*NORMSDIST(((LN(3250/Assumptions!$C$7)+(Assumptions!$C$9-Assumptions!$C$11+0.25^2/2)*Assumptions!$C$10)/(0.25*SQRT(Assumptions!$C$10)))-0.25*SQRT(Assumptions!$C$10)) -> 783.86096 | G37: =3250*EXP(-Assumptions!$C$11*Assumptions!$C$10)*NORMSDIST((LN(3250/Assumptions!$C$7)+(Assumptions!$C$9-Assumptions!$C$11+0.3^2/2)*Assumptions!$C$10)/(0.3*SQRT(Assumptions!$C$10)))-Assumptions!$C$7*EXP(-Assumptions!$C$9*Assumptions!$C$10)*NORMSDIST(((LN(3250/Assumptions!$C$7)+(Assumptions!$C$9-Assumptions!$C$11+0.3^2/2)*Assumptions!$C$10)/(0.3*SQRT(Assumptions!$C$10)))-0.3*SQRT(Assumptions!$C$10)) -> 787.62362 | H37: =3250*EXP(-Assumptions!$C$11*Assumptions!$C$10)*NORMSDIST((LN(3250/Assumptions!$C$7)+(Assumptions!$C$9-Assumptions!$C$11+0.35^2/2)*Assumptions!$C$10)/(0.35*SQRT(Assumptions!$C$10)))-Assumptions!$C$7*EXP(-Assumptions!$C$9*Assumptions!$C$10)*NORMSDIST(((LN(3250/Assumptions!$C$7)+(Assumptions!$C$9-Assumptions!$C$11+0.35^2/2)*Assumptions!$C$10)/(0.35*SQRT(Assumptions!$C$10)))-0.35*SQRT(Assumptions!$C$10)) -> 794.24838 | I37: =3250*EXP(-Assumptions!$C$11*Assumptions!$C$10)*NORMSDIST((LN(3250/Assumptions!$C$7)+(Assumptions!$C$9-Assumptions!$C$11+0.4^2/2)*Assumptions!$C$10)/(0.4*SQRT(Assumptions!$C$10)))-Assumptions!$C$7*EXP(-Assumptions!$C$9*Assumptions!$C$10)*NORMSDIST(((LN(3250/Assumptions!$C$7)+(Assumptions!$C$9-Assumptions!$C$11+0.4^2/2)*Assumptions!$C$10)/(0.4*SQRT(Assumptions!$C$10)))-0.4*SQRT(Assumptions!$C$10)) -> 803.71707 | J37: =3250*EXP(-Assumptions!$C$11*Assumptions!$C$10)*NORMSDIST((LN(3250/Assumptions!$C$7)+(Assumptions!$C$9-Assumptions!$C$11+0.45^2/2)*Assumptions!$C$10)/(0.45*SQRT(Assumptions!$C$10)))-Assumptions!$C$7*EXP(-Assumptions!$C$9*Assumptions!$C$10)*NORMSDIST(((LN(3250/Assumptions!$C$7)+(Assumptions!$C$9-Assumptions!$C$11+0.45^2/2)*Assumptions!$C$10)/(0.45*SQRT(Assumptions!$C$10)))-0.45*SQRT(Assumptions!$C$10)) -> 815.74123 | K37: =3250*EXP(-Assumptions!$C$11*Assumptions!$C$10)*NORMSDIST((LN(3250/Assumptions!$C$7)+(Assumptions!$C$9-Assumptions!$C$11+0.5^2/2)*Assumptions!$C$10)/(0.5*SQRT(Assumptions!$C$10)))-Assumptions!$C$7*EXP(-Assumptions!$C$9*Assumptions!$C$10)*NORMSDIST(((LN(3250/Assumptions!$C$7)+(Assumptions!$C$9-Assumptions!$C$11+0.5^2/2)*Assumptions!$C$10)/(0.5*SQRT(Assumptions!$C$10)))-0.5*SQRT(Assumptions!$C$10)) -> 829.95383
B39: PUT OPTION PRICE (₹) — Spot vs Volatility
B40: Spot ↓ Vol → | C40: 10% | D40: 15% | E40: 20% | F40: 25% | G40: 30% | H40: 35% | I40: 40% | J40: 45% | K40: 50%
B41: 1750 | C41: =Assumptions!$C$7*EXP(-Assumptions!$C$9*Assumptions!$C$10)*NORMSDIST(-(((LN(1750/Assumptions!$C$7)+(Assumptions!$C$9-Assumptions!$C$11+0.1^2/2)*Assumptions!$C$10)/(0.1*SQRT(Assumptions!$C$10)))-0.1*SQRT(Assumptions!$C$10)))-1750*EXP(-Assumptions!$C$11*Assumptions!$C$10)*NORMSDIST(-((LN(1750/Assumptions!$C$7)+(Assumptions!$C$9-Assumptions!$C$11+0.1^2/2)*Assumptions!$C$10)/(0.1*SQRT(Assumptions!$C$10)))) -> 714.07283 | D41: =Assumptions!$C$7*EXP(-Assumptions!$C$9*Assumptions!$C$10)*NORMSDIST(-(((LN(1750/Assumptions!$C$7)+(Assumptions!$C$9-Assumptions!$C$11+0.15^2/2)*Assumptions!$C$10)/(0.15*SQRT(Assumptions!$C$10)))-0.15*SQRT(Assumptions!$C$10)))-1750*EXP(-Assumptions!$C$11*Assumptions!$C$10)*NORMSDIST(-((LN(1750/Assumptions!$C$7)+(Assumptions!$C$9-Assumptions!$C$11+0.15^2/2)*Assumptions!$C$10)/(0.15*SQRT(Assumptions!$C$10)))) -> 714.07291 | E41: =Assumptions!$C$7*EXP(-Assumptions!$C$9*Assumptions!$C$10)*NORMSDIST(-(((LN(1750/Assumptions!$C$7)+(Assumptions!$C$9-Assumptions!$C$11+0.2^2/2)*Assumptions!$C$10)/(0.2*SQRT(Assumptions!$C$10)))-0.2*SQRT(Assumptions!$C$10)))-1750*EXP(-Assumptions!$C$11*Assumptions!$C$10)*NORMSDIST(-((LN(1750/Assumptions!$C$7)+(Assumptions!$C$9-Assumptions!$C$11+0.2^2/2)*Assumptions!$C$10)/(0.2*SQRT(Assumptions!$C$10)))) -> 714.08884 | F41: =Assumptions!$C$7*EXP(-Assumptions!$C$9*Assumptions!$C$10)*NORMSDIST(-(((LN(1750/Assumptions!$C$7)+(Assumptions!$C$9-Assumptions!$C$11+0.25^2/2)*Assumptions!$C$10)/(0.25*SQRT(Assumptions!$C$10)))-0.25*SQRT(Assumptions!$C$10)))-1750*EXP(-Assumptions!$C$11*Assumptions!$C$10)*NORMSDIST(-((LN(1750/Assumptions!$C$7)+(Assumptions!$C$9-Assumptions!$C$11+0.25^2/2)*Assumptions!$C$10)/(0.25*SQRT(Assumptions!$C$10)))) -> 714.3105 | G41: =Assumptions!$C$7*EXP(-Assumptions!$C$9*Assumptions!$C$10)*NORMSDIST(-(((LN(1750/Assumptions!$C$7)+(Assumptions!$C$9-Assumptions!$C$11+0.3^2/2)*Assumptions!$C$10)/(0.3*SQRT(Assumptions!$C$10)))-0.3*SQRT(Assumptions!$C$10)))-1750*EXP(-Assumptions!$C$11*Assumptions!$C$10)*NORMSDIST(-((LN(1750/Assumptions!$C$7)+(Assumptions!$C$9-Assumptions!$C$11+0.3^2/2)*Assumptions!$C$10)/(0.3*SQRT(Assumptions!$C$10)))) -> 715.25518 | H41: =Assumptions!$C$7*EXP(-Assumptions!$C$9*Assumptions!$C$10)*NORMSDIST(-(((LN(1750/Assumptions!$C$7)+(Assumptions!$C$9-Assumptions!$C$11+0.35^2/2)*Assumptions!$C$10)/(0.35*SQRT(Assumptions!$C$10)))-0.35*SQRT(Assumptions!$C$10)))-1750*EXP(-Assumptions!$C$11*Assumptions!$C$10)*NORMSDIST(-((LN(1750/Assumptions!$C$7)+(Assumptions!$C$9-Assumptions!$C$11+0.35^2/2)*Assumptions!$C$10)/(0.35*SQRT(Assumptions!$C$10)))) -> 717.49148 | I41: =Assumptions!$C$7*EXP(-Assumptions!$C$9*Assumptions!$C$10)*NORMSDIST(-(((LN(1750/Assumptions!$C$7)+(Assumptions!$C$9-Assumptions!$C$11+0.4^2/2)*Assumptions!$C$10)/(0.4*SQRT(Assumptions!$C$10)))-0.4*SQRT(Assumptions!$C$10)))-1750*EXP(-Assumptions!$C$11*Assumptions!$C$10)*NORMSDIST(-((LN(1750/Assumptions!$C$7)+(Assumptions!$C$9-Assumptions!$C$11+0.4^2/2)*Assumptions!$C$10)/(0.4*SQRT(Assumptions!$C$10)))) -> 721.35834 | J41: =Assumptions!$C$7*EXP(-Assumptions!$C$9*Assumptions!$C$10)*NORMSDIST(-(((LN(1750/Assumptions!$C$7)+(Assumptions!$C$9-Assumptions!$C$11+0.45^2/2)*Assumptions!$C$10)/(0.45*SQRT(Assumptions!$C$10)))-0.45*SQRT(Assumptions!$C$10)))-1750*EXP(-Assumptions!$C$11*Assumptions!$C$10)*NORMSDIST(-((LN(1750/Assumptions!$C$7)+(Assumptions!$C$9-Assumptions!$C$11+0.45^2/2)*Assumptions!$C$10)/(0.45*SQRT(Assumptions!$C$10)))) -> 726.94357 | K41: =Assumptions!$C$7*EXP(-Assumptions!$C$9*Assumptions!$C$10)*NORMSDIST(-(((LN(1750/Assumptions!$C$7)+(Assumptions!$C$9-Assumptions!$C$11+0.5^2/2)*Assumptions!$C$10)/(0.5*SQRT(Assumptions!$C$10)))-0.5*SQRT(Assumptions!$C$10)))-1750*EXP(-Assumptions!$C$11*Assumptions!$C$10)*NORMSDIST(-((LN(1750/Assumptions!$C$7)+(Assumptions!$C$9-Assumptions!$C$11+0.5^2/2)*Assumptions!$C$10)/(0.5*SQRT(Assumptions!$C$10)))) -> 734.17284
B42: 1800 | C42: =Assumptions!$C$7*EXP(-Assumptions!$C$9*Assumptions!$C$10)*NORMSDIST(-(((LN(1800/Assumptions!$C$7)+(Assumptions!$C$9-Assumptions!$C$11+0.1^2/2)*Assumptions!$C$10)/(0.1*SQRT(Assumptions!$C$10)))-0.1*SQRT(Assumptions!$C$10)))-1800*EXP(-Assumptions!$C$11*Assumptions!$C$10)*NORMSDIST(-((LN(1800/Assumptions!$C$7)+(Assumptions!$C$9-Assumptions!$C$11+0.1^2/2)*Assumptions!$C$10)/(0.1*SQRT(Assumptions!$C$10)))) -> 664.19768 | D42: =Assumptions!$C$7*EXP(-Assumptions!$C$9*Assumptions!$C$10)*NORMSDIST(-(((LN(1800/Assumptions!$C$7)+(Assumptions!$C$9-Assumptions!$C$11+0.15^2/2)*Assumptions!$C$10)/(0.15*SQRT(Assumptions!$C$10)))-0.15*SQRT(Assumptions!$C$10)))-1800*EXP(-Assumptions!$C$11*Assumptions!$C$10)*NORMSDIST(-((LN(1800/Assumptions!$C$7)+(Assumptions!$C$9-Assumptions!$C$11+0.15^2/2)*Assumptions!$C$10)/(0.15*SQRT(Assumptions!$C$10)))) -> 664.19814 | E42: =Assumptions!$C$7*EXP(-Assumptions!$C$9*Assumptions!$C$10)*NORMSDIST(-(((LN(1800/Assumptions!$C$7)+(Assumptions!$C$9-Assumptions!$C$11+0.2^2/2)*Assumptions!$C$10)/(0.2*SQRT(Assumptions!$C$10)))-0.2*SQRT(Assumptions!$C$10)))-1800*EXP(-Assumptions!$C$11*Assumptions!$C$10)*NORMSDIST(-((LN(1800/Assumptions!$C$7)+(Assumptions!$C$9-Assumptions!$C$11+0.2^2/2)*Assumptions!$C$10)/(0.2*SQRT(Assumptions!$C$10)))) -> 664.24486 | F42: =Assumptions!$C$7*EXP(-Assumptions!$C$9*Assumptions!$C$10)*NORMSDIST(-(((LN(1800/Assumptions!$C$7)+(Assumptions!$C$9-Assumptions!$C$11+0.25^2/2)*Assumptions!$C$10)/(0.25*SQRT(Assumptions!$C$10)))-0.25*SQRT(Assumptions!$C$10)))-1800*EXP(-Assumptions!$C$11*Assumptions!$C$10)*NORMSDIST(-((LN(1800/Assumptions!$C$7)+(Assumptions!$C$9-Assumptions!$C$11+0.25^2/2)*Assumptions!$C$10)/(0.25*SQRT(Assumptions!$C$10)))) -> 664.69466 | G42: =Assumptions!$C$7*EXP(-Assumptions!$C$9*Assumptions!$C$10)*NORMSDIST(-(((LN(1800/Assumptions!$C$7)+(Assumptions!$C$9-Assumptions!$C$11+0.3^2/2)*Assumptions!$C$10)/(0.3*SQRT(Assumptions!$C$10)))-0.3*SQRT(Assumptions!$C$10)))-1800*EXP(-Assumptions!$C$11*Assumptions!$C$10)*NORMSDIST(-((LN(1800/Assumptions!$C$7)+(Assumptions!$C$9-Assumptions!$C$11+0.3^2/2)*Assumptions!$C$10)/(0.3*SQRT(Assumptions!$C$10)))) -> 666.24134 | H42: =Assumptions!$C$7*EXP(-Assumptions!$C$9*Assumptions!$C$10)*NORMSDIST(-(((LN(1800/Assumptions!$C$7)+(Assumptions!$C$9-Assumptions!$C$11+0.35^2/2)*Assumptions!$C$10)/(0.35*SQRT(Assumptions!$C$10)))-0.35*SQRT(Assumptions!$C$10)))-1800*EXP(-Assumptions!$C$11*Assumptions!$C$10)*NORMSDIST(-((LN(1800/Assumptions!$C$7)+(Assumptions!$C$9-Assumptions!$C$11+0.35^2/2)*Assumptions!$C$10)/(0.35*SQRT(Assumptions!$C$10)))) -> 669.45099 | I42: =Assumptions!$C$7*EXP(-Assumptions!$C$9*Assumptions!$C$10)*NORMSDIST(-(((LN(1800/Assumptions!$C$7)+(Assumptions!$C$9-Assumptions!$C$11+0.4^2/2)*Assumptions!$C$10)/(0.4*SQRT(Assumptions!$C$10)))-0.4*SQRT(Assumptions!$C$10)))-1800*EXP(-Assumptions!$C$11*Assumptions!$C$10)*NORMSDIST(-((LN(1800/Assumptions!$C$7)+(Assumptions!$C$9-Assumptions!$C$11+0.4^2/2)*Assumptions!$C$10)/(0.4*SQRT(Assumptions!$C$10)))) -> 674.54875 | J42: =Assumptions!$C$7*EXP(-Assumptions!$C$9*Assumptions!$C$10)*NORMSDIST(-(((LN(1800/Assumptions!$C$7)+(Assumptions!$C$9-Assumptions!$C$11+0.45^2/2)*Assumptions!$C$10)/(0.45*SQRT(Assumptions!$C$10)))-0.45*SQRT(Assumptions!$C$10)))-1800*EXP(-Assumptions!$C$11*Assumptions!$C$10)*NORMSDIST(-((LN(1800/Assumptions!$C$7)+(Assumptions!$C$9-Assumptions!$C$11+0.45^2/2)*Assumptions!$C$10)/(0.45*SQRT(Assumptions!$C$10)))) -> 681.50011 | K42: =Assumptions!$C$7*EXP(-Assumptions!$C$9*Assumptions!$C$10)*NORMSDIST(-(((LN(1800/Assumptions!$C$7)+(Assumptions!$C$9-Assumptions!$C$11+0.5^2/2)*Assumptions!$C$10)/(0.5*SQRT(Assumptions!$C$10)))-0.5*SQRT(Assumptions!$C$10)))-1800*EXP(-Assumptions!$C$11*Assumptions!$C$10)*NORMSDIST(-((LN(1800/Assumptions!$C$7)+(Assumptions!$C$9-Assumptions!$C$11+0.5^2/2)*Assumptions!$C$10)/(0.5*SQRT(Assumptions!$C$10)))) -> 690.13948
B43: 1850 | C43: =Assumptions!$C$7*EXP(-Assumptions!$C$9*Assumptions!$C$10)*NORMSDIST(-(((LN(1850/Assumptions!$C$7)+(Assumptions!$C$9-Assumptions!$C$11+0.1^2/2)*Assumptions!$C$10)/(0.1*SQRT(Assumptions!$C$10)))-0.1*SQRT(Assumptions!$C$10)))-1850*EXP(-Assumptions!$C$11*Assumptions!$C$10)*NORMSDIST(-((LN(1850/Assumptions!$C$7)+(Assumptions!$C$9-Assumptions!$C$11+0.1^2/2)*Assumptions!$C$10)/(0.1*SQRT(Assumptions!$C$10)))) -> 614.32252 | D43: =Assumptions!$C$7*EXP(-Assumptions!$C$9*Assumptions!$C$10)*NORMSDIST(-(((LN(1850/Assumptions!$C$7)+(Assumptions!$C$9-Assumptions!$C$11+0.15^2/2)*Assumptions!$C$10)/(0.15*SQRT(Assumptions!$C$10)))-0.15*SQRT(Assumptions!$C$10)))-1850*EXP(-Assumptions!$C$11*Assumptions!$C$10)*NORMSDIST(-((LN(1850/Assumptions!$C$7)+(Assumptions!$C$9-Assumptions!$C$11+0.15^2/2)*Assumptions!$C$10)/(0.15*SQRT(Assumptions!$C$10)))) -> 614.3249 | E43: =Assumptions!$C$7*EXP(-Assumptions!$C$9*Assumptions!$C$10)*NORMSDIST(-(((LN(1850/Assumptions!$C$7)+(Assumptions!$C$9-Assumptions!$C$11+0.2^2/2)*Assumptions!$C$10)/(0.2*SQRT(Assumptions!$C$10)))-0.2*SQRT(Assumptions!$C$10)))-1850*EXP(-Assumptions!$C$11*Assumptions!$C$10)*NORMSDIST(-((LN(1850/Assumptions!$C$7)+(Assumptions!$C$9-Assumptions!$C$11+0.2^2/2)*Assumptions!$C$10)/(0.2*SQRT(Assumptions!$C$10)))) -> 614.44876 | F43: =Assumptions!$C$7*EXP(-Assumptions!$C$9*Assumptions!$C$10)*NORMSDIST(-(((LN(1850/Assumptions!$C$7)+(Assumptions!$C$9-Assumptions!$C$11+0.25^2/2)*Assumptions!$C$10)/(0.25*SQRT(Assumptions!$C$10)))-0.25*SQRT(Assumptions!$C$10)))-1850*EXP(-Assumptions!$C$11*Assumptions!$C$10)*NORMSDIST(-((LN(1850/Assumptions!$C$7)+(Assumptions!$C$9-Assumptions!$C$11+0.25^2/2)*Assumptions!$C$10)/(0.25*SQRT(Assumptions!$C$10)))) -> 615.29941 | G43: =Assumptions!$C$7*EXP(-Assumptions!$C$9*Assumptions!$C$10)*NORMSDIST(-(((LN(1850/Assumptions!$C$7)+(Assumptions!$C$9-Assumptions!$C$11+0.3^2/2)*Assumptions!$C$10)/(0.3*SQRT(Assumptions!$C$10)))-0.3*SQRT(Assumptions!$C$10)))-1850*EXP(-Assumptions!$C$11*Assumptions!$C$10)*NORMSDIST(-((LN(1850/Assumptions!$C$7)+(Assumptions!$C$9-Assumptions!$C$11+0.3^2/2)*Assumptions!$C$10)/(0.3*SQRT(Assumptions!$C$10)))) -> 617.70631 | H43: =Assumptions!$C$7*EXP(-Assumptions!$C$9*Assumptions!$C$10)*NORMSDIST(-(((LN(1850/Assumptions!$C$7)+(Assumptions!$C$9-Assumptions!$C$11+0.35^2/2)*Assumptions!$C$10)/(0.35*SQRT(Assumptions!$C$10)))-0.35*SQRT(Assumptions!$C$10)))-1850*EXP(-Assumptions!$C$11*Assumptions!$C$10)*NORMSDIST(-((LN(1850/Assumptions!$C$7)+(Assumptions!$C$9-Assumptions!$C$11+0.35^2/2)*Assumptions!$C$10)/(0.35*SQRT(Assumptions!$C$10)))) -> 622.14278 | I43: =Assumptions!$C$7*EXP(-Assumptions!$C$9*Assumptions!$C$10)*NORMSDIST(-(((LN(1850/Assumptions!$C$7)+(Assumptions!$C$9-Assumptions!$C$11+0.4^2/2)*Assumptions!$C$10)/(0.4*SQRT(Assumptions!$C$10)))-0.4*SQRT(Assumptions!$C$10)))-1850*EXP(-Assumptions!$C$11*Assumptions!$C$10)*NORMSDIST(-((LN(1850/Assumptions!$C$7)+(Assumptions!$C$9-Assumptions!$C$11+0.4^2/2)*Assumptions!$C$10)/(0.4*SQRT(Assumptions!$C$10)))) -> 628.67258 | J43: =Assumptions!$C$7*EXP(-Assumptions!$C$9*Assumptions!$C$10)*NORMSDIST(-(((LN(1850/Assumptions!$C$7)+(Assumptions!$C$9-Assumptions!$C$11+0.45^2/2)*Assumptions!$C$10)/(0.45*SQRT(Assumptions!$C$10)))-0.45*SQRT(Assumptions!$C$10)))-1850*EXP(-Assumptions!$C$11*Assumptions!$C$10)*NORMSDIST(-((LN(1850/Assumptions!$C$7)+(Assumptions!$C$9-Assumptions!$C$11+0.45^2/2)*Assumptions!$C$10)/(0.45*SQRT(Assumptions!$C$10)))) -> 637.13039 | K43: =Assumptions!$C$7*EXP(-Assumptions!$C$9*Assumptions!$C$10)*NORMSDIST(-(((LN(1850/Assumptions!$C$7)+(Assumptions!$C$9-Assumptions!$C$11+0.5^2/2)*Assumptions!$C$10)/(0.5*SQRT(Assumptions!$C$10)))-0.5*SQRT(Assumptions!$C$10)))-1850*EXP(-Assumptions!$C$11*Assumptions!$C$10)*NORMSDIST(-((LN(1850/Assumptions!$C$7)+(Assumptions!$C$9-Assumptions!$C$11+0.5^2/2)*Assumptions!$C$10)/(0.5*SQRT(Assumptions!$C$10)))) -> 647.26786
B44: 1900 | C44: =Assumptions!$C$7*EXP(-Assumptions!$C$9*Assumptions!$C$10)*NORMSDIST(-(((LN(1900/Assumptions!$C$7)+(Assumptions!$C$9-Assumptions!$C$11+0.1^2/2)*Assumptions!$C$10)/(0.1*SQRT(Assumptions!$C$10)))-0.1*SQRT(Assumptions!$C$10)))-1900*EXP(-Assumptions!$C$11*Assumptions!$C$10)*NORMSDIST(-((LN(1900/Assumptions!$C$7)+(Assumptions!$C$9-Assumptions!$C$11+0.1^2/2)*Assumptions!$C$10)/(0.1*SQRT(Assumptions!$C$10)))) -> 564.44737 | D44: =Assumptions!$C$7*EXP(-Assumptions!$C$9*Assumptions!$C$10)*NORMSDIST(-(((LN(1900/Assumptions!$C$7)+(Assumptions!$C$9-Assumptions!$C$11+0.15^2/2)*Assumptions!$C$10)/(0.15*SQRT(Assumptions!$C$10)))-0.15*SQRT(Assumptions!$C$10)))-1900*EXP(-Assumptions!$C$11*Assumptions!$C$10)*NORMSDIST(-((LN(1900/Assumptions!$C$7)+(Assumptions!$C$9-Assumptions!$C$11+0.15^2/2)*Assumptions!$C$10)/(0.15*SQRT(Assumptions!$C$10)))) -> 564.45778 | E44: =Assumptions!$C$7*EXP(-Assumptions!$C$9*Assumptions!$C$10)*NORMSDIST(-(((LN(1900/Assumptions!$C$7)+(Assumptions!$C$9-Assumptions!$C$11+0.2^2/2)*Assumptions!$C$10)/(0.2*SQRT(Assumptions!$C$10)))-0.2*SQRT(Assumptions!$C$10)))-1900*EXP(-Assumptions!$C$11*Assumptions!$C$10)*NORMSDIST(-((LN(1900/Assumptions!$C$7)+(Assumptions!$C$9-Assumptions!$C$11+0.2^2/2)*Assumptions!$C$10)/(0.2*SQRT(Assumptions!$C$10)))) -> 564.75626 | F44: =Assumptions!$C$7*EXP(-Assumptions!$C$9*Assumptions!$C$10)*NORMSDIST(-(((LN(1900/Assumptions!$C$7)+(Assumptions!$C$9-Assumptions!$C$11+0.25^2/2)*Assumptions!$C$10)/(0.25*SQRT(Assumptions!$C$10)))-0.25*SQRT(Assumptions!$C$10)))-1900*EXP(-Assumptions!$C$11*Assumptions!$C$10)*NORMSDIST(-((LN(1900/Assumptions!$C$7)+(Assumptions!$C$9-Assumptions!$C$11+0.25^2/2)*Assumptions!$C$10)/(0.25*SQRT(Assumptions!$C$10)))) -> 566.26147 | G44: =Assumptions!$C$7*EXP(-Assumptions!$C$9*Assumptions!$C$10)*NORMSDIST(-(((LN(1900/Assumptions!$C$7)+(Assumptions!$C$9-Assumptions!$C$11+0.3^2/2)*Assumptions!$C$10)/(0.3*SQRT(Assumptions!$C$10)))-0.3*SQRT(Assumptions!$C$10)))-1900*EXP(-Assumptions!$C$11*Assumptions!$C$10)*NORMSDIST(-((LN(1900/Assumptions!$C$7)+(Assumptions!$C$9-Assumptions!$C$11+0.3^2/2)*Assumptions!$C$10)/(0.3*SQRT(Assumptions!$C$10)))) -> 569.83294 | H44: =Assumptions!$C$7*EXP(-Assumptions!$C$9*Assumptions!$C$10)*NORMSDIST(-(((LN(1900/Assumptions!$C$7)+(Assumptions!$C$9-Assumptions!$C$11+0.35^2/2)*Assumptions!$C$10)/(0.35*SQRT(Assumptions!$C$10)))-0.35*SQRT(Assumptions!$C$10)))-1900*EXP(-Assumptions!$C$11*Assumptions!$C$10)*NORMSDIST(-((LN(1900/Assumptions!$C$7)+(Assumptions!$C$9-Assumptions!$C$11+0.35^2/2)*Assumptions!$C$10)/(0.35*SQRT(Assumptions!$C$10)))) -> 575.75369 | I44: =Assumptions!$C$7*EXP(-Assumptions!$C$9*Assumptions!$C$10)*NORMSDIST(-(((LN(1900/Assumptions!$C$7)+(Assumptions!$C$9-Assumptions!$C$11+0.4^2/2)*Assumptions!$C$10)/(0.4*SQRT(Assumptions!$C$10)))-0.4*SQRT(Assumptions!$C$10)))-1900*EXP(-Assumptions!$C$11*Assumptions!$C$10)*NORMSDIST(-((LN(1900/Assumptions!$C$7)+(Assumptions!$C$9-Assumptions!$C$11+0.4^2/2)*Assumptions!$C$10)/(0.4*SQRT(Assumptions!$C$10)))) -> 583.89685 | J44: =Assumptions!$C$7*EXP(-Assumptions!$C$9*Assumptions!$C$10)*NORMSDIST(-(((LN(1900/Assumptions!$C$7)+(Assumptions!$C$9-Assumptions!$C$11+0.45^2/2)*Assumptions!$C$10)/(0.45*SQRT(Assumptions!$C$10)))-0.45*SQRT(Assumptions!$C$10)))-1900*EXP(-Assumptions!$C$11*Assumptions!$C$10)*NORMSDIST(-((LN(1900/Assumptions!$C$7)+(Assumptions!$C$9-Assumptions!$C$11+0.45^2/2)*Assumptions!$C$10)/(0.45*SQRT(Assumptions!$C$10)))) -> 593.97325 | K44: =Assumptions!$C$7*EXP(-Assumptions!$C$9*Assumptions!$C$10)*NORMSDIST(-(((LN(1900/Assumptions!$C$7)+(Assumptions!$C$9-Assumptions!$C$11+0.5^2/2)*Assumptions!$C$10)/(0.5*SQRT(Assumptions!$C$10)))-0.5*SQRT(Assumptions!$C$10)))-1900*EXP(-Assumptions!$C$11*Assumptions!$C$10)*NORMSDIST(-((LN(1900/Assumptions!$C$7)+(Assumptions!$C$9-Assumptions!$C$11+0.5^2/2)*Assumptions!$C$10)/(0.5*SQRT(Assumptions!$C$10)))) -> 605.66834
B45: 1950 | C45: =Assumptions!$C$7*EXP(-Assumptions!$C$9*Assumptions!$C$10)*NORMSDIST(-(((LN(1950/Assumptions!$C$7)+(Assumptions!$C$9-Assumptions!$C$11+0.1^2/2)*Assumptions!$C$10)/(0.1*SQRT(Assumptions!$C$10)))-0.1*SQRT(Assumptions!$C$10)))-1950*EXP(-Assumptions!$C$11*Assumptions!$C$10)*NORMSDIST(-((LN(1950/Assumptions!$C$7)+(Assumptions!$C$9-Assumptions!$C$11+0.1^2/2)*Assumptions!$C$10)/(0.1*SQRT(Assumptions!$C$10)))) -> 514.57224 | D45: =Assumptions!$C$7*EXP(-Assumptions!$C$9*Assumptions!$C$10)*NORMSDIST(-(((LN(1950/Assumptions!$C$7)+(Assumptions!$C$9-Assumptions!$C$11+0.15^2/2)*Assumptions!$C$10)/(0.15*SQRT(Assumptions!$C$10)))-0.15*SQRT(Assumptions!$C$10)))-1950*EXP(-Assumptions!$C$11*Assumptions!$C$10)*NORMSDIST(-((LN(1950/Assumptions!$C$7)+(Assumptions!$C$9-Assumptions!$C$11+0.15^2/2)*Assumptions!$C$10)/(0.15*SQRT(Assumptions!$C$10)))) -> 514.61157 | E45: =Assumptions!$C$7*EXP(-Assumptions!$C$9*Assumptions!$C$10)*NORMSDIST(-(((LN(1950/Assumptions!$C$7)+(Assumptions!$C$9-Assumptions!$C$11+0.2^2/2)*Assumptions!$C$10)/(0.2*SQRT(Assumptions!$C$10)))-0.2*SQRT(Assumptions!$C$10)))-1950*EXP(-Assumptions!$C$11*Assumptions!$C$10)*NORMSDIST(-((LN(1950/Assumptions!$C$7)+(Assumptions!$C$9-Assumptions!$C$11+0.2^2/2)*Assumptions!$C$10)/(0.2*SQRT(Assumptions!$C$10)))) -> 515.26853 | F45: =Assumptions!$C$7*EXP(-Assumptions!$C$9*Assumptions!$C$10)*NORMSDIST(-(((LN(1950/Assumptions!$C$7)+(Assumptions!$C$9-Assumptions!$C$11+0.25^2/2)*Assumptions!$C$10)/(0.25*SQRT(Assumptions!$C$10)))-0.25*SQRT(Assumptions!$C$10)))-1950*EXP(-Assumptions!$C$11*Assumptions!$C$10)*NORMSDIST(-((LN(1950/Assumptions!$C$7)+(Assumptions!$C$9-Assumptions!$C$11+0.25^2/2)*Assumptions!$C$10)/(0.25*SQRT(Assumptions!$C$10)))) -> 517.76952 | G45: =Assumptions!$C$7*EXP(-Assumptions!$C$9*Assumptions!$C$10)*NORMSDIST(-(((LN(1950/Assumptions!$C$7)+(Assumptions!$C$9-Assumptions!$C$11+0.3^2/2)*Assumptions!$C$10)/(0.3*SQRT(Assumptions!$C$10)))-0.3*SQRT(Assumptions!$C$10)))-1950*EXP(-Assumptions!$C$11*Assumptions!$C$10)*NORMSDIST(-((LN(1950/Assumptions!$C$7)+(Assumptions!$C$9-Assumptions!$C$11+0.3^2/2)*Assumptions!$C$10)/(0.3*SQRT(Assumptions!$C$10)))) -> 522.83784 | H45: =Assumptions!$C$7*EXP(-Assumptions!$C$9*Assumptions!$C$10)*NORMSDIST(-(((LN(1950/Assumptions!$C$7)+(Assumptions!$C$9-Assumptions!$C$11+0.35^2/2)*Assumptions!$C$10)/(0.35*SQRT(Assumptions!$C$10)))-0.35*SQRT(Assumptions!$C$10)))-1950*EXP(-Assumptions!$C$11*Assumptions!$C$10)*NORMSDIST(-((LN(1950/Assumptions!$C$7)+(Assumptions!$C$9-Assumptions!$C$11+0.35^2/2)*Assumptions!$C$10)/(0.35*SQRT(Assumptions!$C$10)))) -> 530.48481 | I45: =Assumptions!$C$7*EXP(-Assumptions!$C$9*Assumptions!$C$10)*NORMSDIST(-(((LN(1950/Assumptions!$C$7)+(Assumptions!$C$9-Assumptions!$C$11+0.4^2/2)*Assumptions!$C$10)/(0.4*SQRT(Assumptions!$C$10)))-0.4*SQRT(Assumptions!$C$10)))-1950*EXP(-Assumptions!$C$11*Assumptions!$C$10)*NORMSDIST(-((LN(1950/Assumptions!$C$7)+(Assumptions!$C$9-Assumptions!$C$11+0.4^2/2)*Assumptions!$C$10)/(0.4*SQRT(Assumptions!$C$10)))) -> 540.38988 | J45: =Assumptions!$C$7*EXP(-Assumptions!$C$9*Assumptions!$C$10)*NORMSDIST(-(((LN(1950/Assumptions!$C$7)+(Assumptions!$C$9-Assumptions!$C$11+0.45^2/2)*Assumptions!$C$10)/(0.45*SQRT(Assumptions!$C$10)))-0.45*SQRT(Assumptions!$C$10)))-1950*EXP(-Assumptions!$C$11*Assumptions!$C$10)*NORMSDIST(-((LN(1950/Assumptions!$C$7)+(Assumptions!$C$9-Assumptions!$C$11+0.45^2/2)*Assumptions!$C$10)/(0.45*SQRT(Assumptions!$C$10)))) -> 552.16179 | K45: =Assumptions!$C$7*EXP(-Assumptions!$C$9*Assumptions!$C$10)*NORMSDIST(-(((LN(1950/Assumptions!$C$7)+(Assumptions!$C$9-Assumptions!$C$11+0.5^2/2)*Assumptions!$C$10)/(0.5*SQRT(Assumptions!$C$10)))-0.5*SQRT(Assumptions!$C$10)))-1950*EXP(-Assumptions!$C$11*Assumptions!$C$10)*NORMSDIST(-((LN(1950/Assumptions!$C$7)+(Assumptions!$C$9-Assumptions!$C$11+0.5^2/2)*Assumptions!$C$10)/(0.5*SQRT(Assumptions!$C$10)))) -> 565.44249
B46: 2000 | C46: =Assumptions!$C$7*EXP(-Assumptions!$C$9*Assumptions!$C$10)*NORMSDIST(-(((LN(2000/Assumptions!$C$7)+(Assumptions!$C$9-Assumptions!$C$11+0.1^2/2)*Assumptions!$C$10)/(0.1*SQRT(Assumptions!$C$10)))-0.1*SQRT(Assumptions!$C$10)))-2000*EXP(-Assumptions!$C$11*Assumptions!$C$10)*NORMSDIST(-((LN(2000/Assumptions!$C$7)+(Assumptions!$C$9-Assumptions!$C$11+0.1^2/2)*Assumptions!$C$10)/(0.1*SQRT(Assumptions!$C$10)))) -> 464.69739 | D46: =Assumptions!$C$7*EXP(-Assumptions!$C$9*Assumptions!$C$10)*NORMSDIST(-(((LN(2000/Assumptions!$C$7)+(Assumptions!$C$9-Assumptions!$C$11+0.15^2/2)*Assumptions!$C$10)/(0.15*SQRT(Assumptions!$C$10)))-0.15*SQRT(Assumptions!$C$10)))-2000*EXP(-Assumptions!$C$11*Assumptions!$C$10)*NORMSDIST(-((LN(2000/Assumptions!$C$7)+(Assumptions!$C$9-Assumptions!$C$11+0.15^2/2)*Assumptions!$C$10)/(0.15*SQRT(Assumptions!$C$10)))) -> 464.8269 | E46: =Assumptions!$C$7*EXP(-Assumptions!$C$9*Assumptions!$C$10)*NORMSDIST(-(((LN(2000/Assumptions!$C$7)+(Assumptions!$C$9-Assumptions!$C$11+0.2^2/2)*Assumptions!$C$10)/(0.2*SQRT(Assumptions!$C$10)))-0.2*SQRT(Assumptions!$C$10)))-2000*EXP(-Assumptions!$C$11*Assumptions!$C$10)*NORMSDIST(-((LN(2000/Assumptions!$C$7)+(Assumptions!$C$9-Assumptions!$C$11+0.2^2/2)*Assumptions!$C$10)/(0.2*SQRT(Assumptions!$C$10)))) -> 466.15265 | F46: =Assumptions!$C$7*EXP(-Assumptions!$C$9*Assumptions!$C$10)*NORMSDIST(-(((LN(2000/Assumptions!$C$7)+(Assumptions!$C$9-Assumptions!$C$11+0.25^2/2)*Assumptions!$C$10)/(0.25*SQRT(Assumptions!$C$10)))-0.25*SQRT(Assumptions!$C$10)))-2000*EXP(-Assumptions!$C$11*Assumptions!$C$10)*NORMSDIST(-((LN(2000/Assumptions!$C$7)+(Assumptions!$C$9-Assumptions!$C$11+0.25^2/2)*Assumptions!$C$10)/(0.25*SQRT(Assumptions!$C$10)))) -> 470.06793 | G46: =Assumptions!$C$7*EXP(-Assumptions!$C$9*Assumptions!$C$10)*NORMSDIST(-(((LN(2000/Assumptions!$C$7)+(Assumptions!$C$9-Assumptions!$C$11+0.3^2/2)*Assumptions!$C$10)/(0.3*SQRT(Assumptions!$C$10)))-0.3*SQRT(Assumptions!$C$10)))-2000*EXP(-Assumptions!$C$11*Assumptions!$C$10)*NORMSDIST(-((LN(2000/Assumptions!$C$7)+(Assumptions!$C$9-Assumptions!$C$11+0.3^2/2)*Assumptions!$C$10)/(0.3*SQRT(Assumptions!$C$10)))) -> 476.96563 | H46: =Assumptions!$C$7*EXP(-Assumptions!$C$9*Assumptions!$C$10)*NORMSDIST(-(((LN(2000/Assumptions!$C$7)+(Assumptions!$C$9-Assumptions!$C$11+0.35^2/2)*Assumptions!$C$10)/(0.35*SQRT(Assumptions!$C$10)))-0.35*SQRT(Assumptions!$C$10)))-2000*EXP(-Assumptions!$C$11*Assumptions!$C$10)*NORMSDIST(-((LN(2000/Assumptions!$C$7)+(Assumptions!$C$9-Assumptions!$C$11+0.35^2/2)*Assumptions!$C$10)/(0.35*SQRT(Assumptions!$C$10)))) -> 486.54443 | I46: =Assumptions!$C$7*EXP(-Assumptions!$C$9*Assumptions!$C$10)*NORMSDIST(-(((LN(2000/Assumptions!$C$7)+(Assumptions!$C$9-Assumptions!$C$11+0.4^2/2)*Assumptions!$C$10)/(0.4*SQRT(Assumptions!$C$10)))-0.4*SQRT(Assumptions!$C$10)))-2000*EXP(-Assumptions!$C$11*Assumptions!$C$10)*NORMSDIST(-((LN(2000/Assumptions!$C$7)+(Assumptions!$C$9-Assumptions!$C$11+0.4^2/2)*Assumptions!$C$10)/(0.4*SQRT(Assumptions!$C$10)))) -> 498.31571 | J46: =Assumptions!$C$7*EXP(-Assumptions!$C$9*Assumptions!$C$10)*NORMSDIST(-(((LN(2000/Assumptions!$C$7)+(Assumptions!$C$9-Assumptions!$C$11+0.45^2/2)*Assumptions!$C$10)/(0.45*SQRT(Assumptions!$C$10)))-0.45*SQRT(Assumptions!$C$10)))-2000*EXP(-Assumptions!$C$11*Assumptions!$C$10)*NORMSDIST(-((LN(2000/Assumptions!$C$7)+(Assumptions!$C$9-Assumptions!$C$11+0.45^2/2)*Assumptions!$C$10)/(0.45*SQRT(Assumptions!$C$10)))) -> 511.81979 | K46: =Assumptions!$C$7*EXP(-Assumptions!$C$9*Assumptions!$C$10)*NORMSDIST(-(((LN(2000/Assumptions!$C$7)+(Assumptions!$C$9-Assumptions!$C$11+0.5^2/2)*Assumptions!$C$10)/(0.5*SQRT(Assumptions!$C$10)))-0.5*SQRT(Assumptions!$C$10)))-2000*EXP(-Assumptions!$C$11*Assumptions!$C$10)*NORMSDIST(-((LN(2000/Assumptions!$C$7)+(Assumptions!$C$9-Assumptions!$C$11+0.5^2/2)*Assumptions!$C$10)/(0.5*SQRT(Assumptions!$C$10)))) -> 526.68102
B47: 2050 | C47: =Assumptions!$C$7*EXP(-Assumptions!$C$9*Assumptions!$C$10)*NORMSDIST(-(((LN(2050/Assumptions!$C$7)+(Assumptions!$C$9-Assumptions!$C$11+0.1^2/2)*Assumptions!$C$10)/(0.1*SQRT(Assumptions!$C$10)))-0.1*SQRT(Assumptions!$C$10)))-2050*EXP(-Assumptions!$C$11*Assumptions!$C$10)*NORMSDIST(-((LN(2050/Assumptions!$C$7)+(Assumptions!$C$9-Assumptions!$C$11+0.1^2/2)*Assumptions!$C$10)/(0.1*SQRT(Assumptions!$C$10)))) -> 414.82488 | D47: =Assumptions!$C$7*EXP(-Assumptions!$C$9*Assumptions!$C$10)*NORMSDIST(-(((LN(2050/Assumptions!$C$7)+(Assumptions!$C$9-Assumptions!$C$11+0.15^2/2)*Assumptions!$C$10)/(0.15*SQRT(Assumptions!$C$10)))-0.15*SQRT(Assumptions!$C$10)))-2050*EXP(-Assumptions!$C$11*Assumptions!$C$10)*NORMSDIST(-((LN(2050/Assumptions!$C$7)+(Assumptions!$C$9-Assumptions!$C$11+0.15^2/2)*Assumptions!$C$10)/(0.15*SQRT(Assumptions!$C$10)))) -> 415.19988 | E47: =Assumptions!$C$7*EXP(-Assumptions!$C$9*Assumptions!$C$10)*NORMSDIST(-(((LN(2050/Assumptions!$C$7)+(Assumptions!$C$9-Assumptions!$C$11+0.2^2/2)*Assumptions!$C$10)/(0.2*SQRT(Assumptions!$C$10)))-0.2*SQRT(Assumptions!$C$10)))-2050*EXP(-Assumptions!$C$11*Assumptions!$C$10)*NORMSDIST(-((LN(2050/Assumptions!$C$7)+(Assumptions!$C$9-Assumptions!$C$11+0.2^2/2)*Assumptions!$C$10)/(0.2*SQRT(Assumptions!$C$10)))) -> 417.66099 | F47: =Assumptions!$C$7*EXP(-Assumptions!$C$9*Assumptions!$C$10)*NORMSDIST(-(((LN(2050/Assumptions!$C$7)+(Assumptions!$C$9-Assumptions!$C$11+0.25^2/2)*Assumptions!$C$10)/(0.25*SQRT(Assumptions!$C$10)))-0.25*SQRT(Assumptions!$C$10)))-2050*EXP(-Assumptions!$C$11*Assumptions!$C$10)*NORMSDIST(-((LN(2050/Assumptions!$C$7)+(Assumptions!$C$9-Assumptions!$C$11+0.25^2/2)*Assumptions!$C$10)/(0.25*SQRT(Assumptions!$C$10)))) -> 423.45422 | G47: =Assumptions!$C$7*EXP(-Assumptions!$C$9*Assumptions!$C$10)*NORMSDIST(-(((LN(2050/Assumptions!$C$7)+(Assumptions!$C$9-Assumptions!$C$11+0.3^2/2)*Assumptions!$C$10)/(0.3*SQRT(Assumptions!$C$10)))-0.3*SQRT(Assumptions!$C$10)))-2050*EXP(-Assumptions!$C$11*Assumptions!$C$10)*NORMSDIST(-((LN(2050/Assumptions!$C$7)+(Assumptions!$C$9-Assumptions!$C$11+0.3^2/2)*Assumptions!$C$10)/(0.3*SQRT(Assumptions!$C$10)))) -> 432.47997 | H47: =Assumptions!$C$7*EXP(-Assumptions!$C$9*Assumptions!$C$10)*NORMSDIST(-(((LN(2050/Assumptions!$C$7)+(Assumptions!$C$9-Assumptions!$C$11+0.35^2/2)*Assumptions!$C$10)/(0.35*SQRT(Assumptions!$C$10)))-0.35*SQRT(Assumptions!$C$10)))-2050*EXP(-Assumptions!$C$11*Assumptions!$C$10)*NORMSDIST(-((LN(2050/Assumptions!$C$7)+(Assumptions!$C$9-Assumptions!$C$11+0.35^2/2)*Assumptions!$C$10)/(0.35*SQRT(Assumptions!$C$10)))) -> 444.14009 | I47: =Assumptions!$C$7*EXP(-Assumptions!$C$9*Assumptions!$C$10)*NORMSDIST(-(((LN(2050/Assumptions!$C$7)+(Assumptions!$C$9-Assumptions!$C$11+0.4^2/2)*Assumptions!$C$10)/(0.4*SQRT(Assumptions!$C$10)))-0.4*SQRT(Assumptions!$C$10)))-2050*EXP(-Assumptions!$C$11*Assumptions!$C$10)*NORMSDIST(-((LN(2050/Assumptions!$C$7)+(Assumptions!$C$9-Assumptions!$C$11+0.4^2/2)*Assumptions!$C$10)/(0.4*SQRT(Assumptions!$C$10)))) -> 457.82878 | J47: =Assumptions!$C$7*EXP(-Assumptions!$C$9*Assumptions!$C$10)*NORMSDIST(-(((LN(2050/Assumptions!$C$7)+(Assumptions!$C$9-Assumptions!$C$11+0.45^2/2)*Assumptions!$C$10)/(0.45*SQRT(Assumptions!$C$10)))-0.45*SQRT(Assumptions!$C$10)))-2050*EXP(-Assumptions!$C$11*Assumptions!$C$10)*NORMSDIST(-((LN(2050/Assumptions!$C$7)+(Assumptions!$C$9-Assumptions!$C$11+0.45^2/2)*Assumptions!$C$10)/(0.45*SQRT(Assumptions!$C$10)))) -> 473.05852 | K47: =Assumptions!$C$7*EXP(-Assumptions!$C$9*Assumptions!$C$10)*NORMSDIST(-(((LN(2050/Assumptions!$C$7)+(Assumptions!$C$9-Assumptions!$C$11+0.5^2/2)*Assumptions!$C$10)/(0.5*SQRT(Assumptions!$C$10)))-0.5*SQRT(Assumptions!$C$10)))-2050*EXP(-Assumptions!$C$11*Assumptions!$C$10)*NORMSDIST(-((LN(2050/Assumptions!$C$7)+(Assumptions!$C$9-Assumptions!$C$11+0.5^2/2)*Assumptions!$C$10)/(0.5*SQRT(Assumptions!$C$10)))) -> 489.46199
B48: 2100 | C48: =Assumptions!$C$7*EXP(-Assumptions!$C$9*Assumptions!$C$10)*NORMSDIST(-(((LN(2100/Assumptions!$C$7)+(Assumptions!$C$9-Assumptions!$C$11+0.1^2/2)*Assumptions!$C$10)/(0.1*SQRT(Assumptions!$C$10)))-0.1*SQRT(Assumptions!$C$10)))-2100*EXP(-Assumptions!$C$11*Assumptions!$C$10)*NORMSDIST(-((LN(2100/Assumptions!$C$7)+(Assumptions!$C$9-Assumptions!$C$11+0.1^2/2)*Assumptions!$C$10)/(0.1*SQRT(Assumptions!$C$10)))) -> 364.96684 | D48: =Assumptions!$C$7*EXP(-Assumptions!$C$9*Assumptions!$C$10)*NORMSDIST(-(((LN(2100/Assumptions!$C$7)+(Assumptions!$C$9-Assumptions!$C$11+0.15^2/2)*Assumptions!$C$10)/(0.15*SQRT(Assumptions!$C$10)))-0.15*SQRT(Assumptions!$C$10)))-2100*EXP(-Assumptions!$C$11*Assumptions!$C$10)*NORMSDIST(-((LN(2100/Assumptions!$C$7)+(Assumptions!$C$9-Assumptions!$C$11+0.15^2/2)*Assumptions!$C$10)/(0.15*SQRT(Assumptions!$C$10)))) -> 365.92776 | E48: =Assumptions!$C$7*EXP(-Assumptions!$C$9*Assumptions!$C$10)*NORMSDIST(-(((LN(2100/Assumptions!$C$7)+(Assumptions!$C$9-Assumptions!$C$11+0.2^2/2)*Assumptions!$C$10)/(0.2*SQRT(Assumptions!$C$10)))-0.2*SQRT(Assumptions!$C$10)))-2100*EXP(-Assumptions!$C$11*Assumptions!$C$10)*NORMSDIST(-((LN(2100/Assumptions!$C$7)+(Assumptions!$C$9-Assumptions!$C$11+0.2^2/2)*Assumptions!$C$10)/(0.2*SQRT(Assumptions!$C$10)))) -> 370.14306 | F48: =Assumptions!$C$7*EXP(-Assumptions!$C$9*Assumptions!$C$10)*NORMSDIST(-(((LN(2100/Assumptions!$C$7)+(Assumptions!$C$9-Assumptions!$C$11+0.25^2/2)*Assumptions!$C$10)/(0.25*SQRT(Assumptions!$C$10)))-0.25*SQRT(Assumptions!$C$10)))-2100*EXP(-Assumptions!$C$11*Assumptions!$C$10)*NORMSDIST(-((LN(2100/Assumptions!$C$7)+(Assumptions!$C$9-Assumptions!$C$11+0.25^2/2)*Assumptions!$C$10)/(0.25*SQRT(Assumptions!$C$10)))) -> 378.26921 | G48: =Assumptions!$C$7*EXP(-Assumptions!$C$9*Assumptions!$C$10)*NORMSDIST(-(((LN(2100/Assumptions!$C$7)+(Assumptions!$C$9-Assumptions!$C$11+0.3^2/2)*Assumptions!$C$10)/(0.3*SQRT(Assumptions!$C$10)))-0.3*SQRT(Assumptions!$C$10)))-2100*EXP(-Assumptions!$C$11*Assumptions!$C$10)*NORMSDIST(-((LN(2100/Assumptions!$C$7)+(Assumptions!$C$9-Assumptions!$C$11+0.3^2/2)*Assumptions!$C$10)/(0.3*SQRT(Assumptions!$C$10)))) -> 389.65173 | H48: =Assumptions!$C$7*EXP(-Assumptions!$C$9*Assumptions!$C$10)*NORMSDIST(-(((LN(2100/Assumptions!$C$7)+(Assumptions!$C$9-Assumptions!$C$11+0.35^2/2)*Assumptions!$C$10)/(0.35*SQRT(Assumptions!$C$10)))-0.35*SQRT(Assumptions!$C$10)))-2100*EXP(-Assumptions!$C$11*Assumptions!$C$10)*NORMSDIST(-((LN(2100/Assumptions!$C$7)+(Assumptions!$C$9-Assumptions!$C$11+0.35^2/2)*Assumptions!$C$10)/(0.35*SQRT(Assumptions!$C$10)))) -> 403.47022 | I48: =Assumptions!$C$7*EXP(-Assumptions!$C$9*Assumptions!$C$10)*NORMSDIST(-(((LN(2100/Assumptions!$C$7)+(Assumptions!$C$9-Assumptions!$C$11+0.4^2/2)*Assumptions!$C$10)/(0.4*SQRT(Assumptions!$C$10)))-0.4*SQRT(Assumptions!$C$10)))-2100*EXP(-Assumptions!$C$11*Assumptions!$C$10)*NORMSDIST(-((LN(2100/Assumptions!$C$7)+(Assumptions!$C$9-Assumptions!$C$11+0.4^2/2)*Assumptions!$C$10)/(0.4*SQRT(Assumptions!$C$10)))) -> 419.06899 | J48: =Assumptions!$C$7*EXP(-Assumptions!$C$9*Assumptions!$C$10)*NORMSDIST(-(((LN(2100/Assumptions!$C$7)+(Assumptions!$C$9-Assumptions!$C$11+0.45^2/2)*Assumptions!$C$10)/(0.45*SQRT(Assumptions!$C$10)))-0.45*SQRT(Assumptions!$C$10)))-2100*EXP(-Assumptions!$C$11*Assumptions!$C$10)*NORMSDIST(-((LN(2100/Assumptions!$C$7)+(Assumptions!$C$9-Assumptions!$C$11+0.45^2/2)*Assumptions!$C$10)/(0.45*SQRT(Assumptions!$C$10)))) -> 435.97406 | K48: =Assumptions!$C$7*EXP(-Assumptions!$C$9*Assumptions!$C$10)*NORMSDIST(-(((LN(2100/Assumptions!$C$7)+(Assumptions!$C$9-Assumptions!$C$11+0.5^2/2)*Assumptions!$C$10)/(0.5*SQRT(Assumptions!$C$10)))-0.5*SQRT(Assumptions!$C$10)))-2100*EXP(-Assumptions!$C$11*Assumptions!$C$10)*NORMSDIST(-((LN(2100/Assumptions!$C$7)+(Assumptions!$C$9-Assumptions!$C$11+0.5^2/2)*Assumptions!$C$10)/(0.5*SQRT(Assumptions!$C$10)))) -> 453.84964
B49: 2150 | C49: =Assumptions!$C$7*EXP(-Assumptions!$C$9*Assumptions!$C$10)*NORMSDIST(-(((LN(2150/Assumptions!$C$7)+(Assumptions!$C$9-Assumptions!$C$11+0.1^2/2)*Assumptions!$C$10)/(0.1*SQRT(Assumptions!$C$10)))-0.1*SQRT(Assumptions!$C$10)))-2150*EXP(-Assumptions!$C$11*Assumptions!$C$10)*NORMSDIST(-((LN(2150/Assumptions!$C$7)+(Assumptions!$C$9-Assumptions!$C$11+0.1^2/2)*Assumptions!$C$10)/(0.1*SQRT(Assumptions!$C$10)))) -> 315.17778 | D49: =Assumptions!$C$7*EXP(-Assumptions!$C$9*Assumptions!$C$10)*NORMSDIST(-(((LN(2150/Assumptions!$C$7)+(Assumptions!$C$9-Assumptions!$C$11+0.15^2/2)*Assumptions!$C$10)/(0.15*SQRT(Assumptions!$C$10)))-0.15*SQRT(Assumptions!$C$10)))-2150*EXP(-Assumptions!$C$11*Assumptions!$C$10)*NORMSDIST(-((LN(2150/Assumptions!$C$7)+(Assumptions!$C$9-Assumptions!$C$11+0.15^2/2)*Assumptions!$C$10)/(0.15*SQRT(Assumptions!$C$10)))) -> 317.36348 | E49: =Assumptions!$C$7*EXP(-Assumptions!$C$9*Assumptions!$C$10)*NORMSDIST(-(((LN(2150/Assumptions!$C$7)+(Assumptions!$C$9-Assumptions!$C$11+0.2^2/2)*Assumptions!$C$10)/(0.2*SQRT(Assumptions!$C$10)))-0.2*SQRT(Assumptions!$C$10)))-2150*EXP(-Assumptions!$C$11*Assumptions!$C$10)*NORMSDIST(-((LN(2150/Assumptions!$C$7)+(Assumptions!$C$9-Assumptions!$C$11+0.2^2/2)*Assumptions!$C$10)/(0.2*SQRT(Assumptions!$C$10)))) -> 324.04338 | F49: =Assumptions!$C$7*EXP(-Assumptions!$C$9*Assumptions!$C$10)*NORMSDIST(-(((LN(2150/Assumptions!$C$7)+(Assumptions!$C$9-Assumptions!$C$11+0.25^2/2)*Assumptions!$C$10)/(0.25*SQRT(Assumptions!$C$10)))-0.25*SQRT(Assumptions!$C$10)))-2150*EXP(-Assumptions!$C$11*Assumptions!$C$10)*NORMSDIST(-((LN(2150/Assumptions!$C$7)+(Assumptions!$C$9-Assumptions!$C$11+0.25^2/2)*Assumptions!$C$10)/(0.25*SQRT(Assumptions!$C$10)))) -> 334.88012 | G49: =Assumptions!$C$7*EXP(-Assumptions!$C$9*Assumptions!$C$10)*NORMSDIST(-(((LN(2150/Assumptions!$C$7)+(Assumptions!$C$9-Assumptions!$C$11+0.3^2/2)*Assumptions!$C$10)/(0.3*SQRT(Assumptions!$C$10)))-0.3*SQRT(Assumptions!$C$10)))-2150*EXP(-Assumptions!$C$11*Assumptions!$C$10)*NORMSDIST(-((LN(2150/Assumptions!$C$7)+(Assumptions!$C$9-Assumptions!$C$11+0.3^2/2)*Assumptions!$C$10)/(0.3*SQRT(Assumptions!$C$10)))) -> 348.7457 | H49: =Assumptions!$C$7*EXP(-Assumptions!$C$9*Assumptions!$C$10)*NORMSDIST(-(((LN(2150/Assumptions!$C$7)+(Assumptions!$C$9-Assumptions!$C$11+0.35^2/2)*Assumptions!$C$10)/(0.35*SQRT(Assumptions!$C$10)))-0.35*SQRT(Assumptions!$C$10)))-2150*EXP(-Assumptions!$C$11*Assumptions!$C$10)*NORMSDIST(-((LN(2150/Assumptions!$C$7)+(Assumptions!$C$9-Assumptions!$C$11+0.35^2/2)*Assumptions!$C$10)/(0.35*SQRT(Assumptions!$C$10)))) -> 364.71626 | I49: =Assumptions!$C$7*EXP(-Assumptions!$C$9*Assumptions!$C$10)*NORMSDIST(-(((LN(2150/Assumptions!$C$7)+(Assumptions!$C$9-Assumptions!$C$11+0.4^2/2)*Assumptions!$C$10)/(0.4*SQRT(Assumptions!$C$10)))-0.4*SQRT(Assumptions!$C$10)))-2150*EXP(-Assumptions!$C$11*Assumptions!$C$10)*NORMSDIST(-((LN(2150/Assumptions!$C$7)+(Assumptions!$C$9-Assumptions!$C$11+0.4^2/2)*Assumptions!$C$10)/(0.4*SQRT(Assumptions!$C$10)))) -> 382.15743 | J49: =Assumptions!$C$7*EXP(-Assumptions!$C$9*Assumptions!$C$10)*NORMSDIST(-(((LN(2150/Assumptions!$C$7)+(Assumptions!$C$9-Assumptions!$C$11+0.45^2/2)*Assumptions!$C$10)/(0.45*SQRT(Assumptions!$C$10)))-0.45*SQRT(Assumptions!$C$10)))-2150*EXP(-Assumptions!$C$11*Assumptions!$C$10)*NORMSDIST(-((LN(2150/Assumptions!$C$7)+(Assumptions!$C$9-Assumptions!$C$11+0.45^2/2)*Assumptions!$C$10)/(0.45*SQRT(Assumptions!$C$10)))) -> 400.64539 | K49: =Assumptions!$C$7*EXP(-Assumptions!$C$9*Assumptions!$C$10)*NORMSDIST(-(((LN(2150/Assumptions!$C$7)+(Assumptions!$C$9-Assumptions!$C$11+0.5^2/2)*Assumptions!$C$10)/(0.5*SQRT(Assumptions!$C$10)))-0.5*SQRT(Assumptions!$C$10)))-2150*EXP(-Assumptions!$C$11*Assumptions!$C$10)*NORMSDIST(-((LN(2150/Assumptions!$C$7)+(Assumptions!$C$9-Assumptions!$C$11+0.5^2/2)*Assumptions!$C$10)/(0.5*SQRT(Assumptions!$C$10)))) -> 419.89361
B50: 2200 | C50: =Assumptions!$C$7*EXP(-Assumptions!$C$9*Assumptions!$C$10)*NORMSDIST(-(((LN(2200/Assumptions!$C$7)+(Assumptions!$C$9-Assumptions!$C$11+0.1^2/2)*Assumptions!$C$10)/(0.1*SQRT(Assumptions!$C$10)))-0.1*SQRT(Assumptions!$C$10)))-2200*EXP(-Assumptions!$C$11*Assumptions!$C$10)*NORMSDIST(-((LN(2200/Assumptions!$C$7)+(Assumptions!$C$9-Assumptions!$C$11+0.1^2/2)*Assumptions!$C$10)/(0.1*SQRT(Assumptions!$C$10)))) -> 265.64507 | D50: =Assumptions!$C$7*EXP(-Assumptions!$C$9*Assumptions!$C$10)*NORMSDIST(-(((LN(2200/Assumptions!$C$7)+(Assumptions!$C$9-Assumptions!$C$11+0.15^2/2)*Assumptions!$C$10)/(0.15*SQRT(Assumptions!$C$10)))-0.15*SQRT(Assumptions!$C$10)))-2200*EXP(-Assumptions!$C$11*Assumptions!$C$10)*NORMSDIST(-((LN(2200/Assumptions!$C$7)+(Assumptions!$C$9-Assumptions!$C$11+0.15^2/2)*Assumptions!$C$10)/(0.15*SQRT(Assumptions!$C$10)))) -> 270.05985 | E50: =Assumptions!$C$7*EXP(-Assumptions!$C$9*Assumptions!$C$10)*NORMSDIST(-(((LN(2200/Assumptions!$C$7)+(Assumptions!$C$9-Assumptions!$C$11+0.2^2/2)*Assumptions!$C$10)/(0.2*SQRT(Assumptions!$C$10)))-0.2*SQRT(Assumptions!$C$10)))-2200*EXP(-Assumptions!$C$11*Assumptions!$C$10)*NORMSDIST(-((LN(2200/Assumptions!$C$7)+(Assumptions!$C$9-Assumptions!$C$11+0.2^2/2)*Assumptions!$C$10)/(0.2*SQRT(Assumptions!$C$10)))) -> 279.8813 | F50: =Assumptions!$C$7*EXP(-Assumptions!$C$9*Assumptions!$C$10)*NORMSDIST(-(((LN(2200/Assumptions!$C$7)+(Assumptions!$C$9-Assumptions!$C$11+0.25^2/2)*Assumptions!$C$10)/(0.25*SQRT(Assumptions!$C$10)))-0.25*SQRT(Assumptions!$C$10)))-2200*EXP(-Assumptions!$C$11*Assumptions!$C$10)*NORMSDIST(-((LN(2200/Assumptions!$C$7)+(Assumptions!$C$9-Assumptions!$C$11+0.25^2/2)*Assumptions!$C$10)/(0.25*SQRT(Assumptions!$C$10)))) -> 293.65801 | G50: =Assumptions!$C$7*EXP(-Assumptions!$C$9*Assumptions!$C$10)*NORMSDIST(-(((LN(2200/Assumptions!$C$7)+(Assumptions!$C$9-Assumptions!$C$11+0.3^2/2)*Assumptions!$C$10)/(0.3*SQRT(Assumptions!$C$10)))-0.3*SQRT(Assumptions!$C$10)))-2200*EXP(-Assumptions!$C$11*Assumptions!$C$10)*NORMSDIST(-((LN(2200/Assumptions!$C$7)+(Assumptions!$C$9-Assumptions!$C$11+0.3^2/2)*Assumptions!$C$10)/(0.3*SQRT(Assumptions!$C$10)))) -> 310.00687 | H50: =Assumptions!$C$7*EXP(-Assumptions!$C$9*Assumptions!$C$10)*NORMSDIST(-(((LN(2200/Assumptions!$C$7)+(Assumptions!$C$9-Assumptions!$C$11+0.35^2/2)*Assumptions!$C$10)/(0.35*SQRT(Assumptions!$C$10)))-0.35*SQRT(Assumptions!$C$10)))-2200*EXP(-Assumptions!$C$11*Assumptions!$C$10)*NORMSDIST(-((LN(2200/Assumptions!$C$7)+(Assumptions!$C$9-Assumptions!$C$11+0.35^2/2)*Assumptions!$C$10)/(0.35*SQRT(Assumptions!$C$10)))) -> 328.0355 | I50: =Assumptions!$C$7*EXP(-Assumptions!$C$9*Assumptions!$C$10)*NORMSDIST(-(((LN(2200/Assumptions!$C$7)+(Assumptions!$C$9-Assumptions!$C$11+0.4^2/2)*Assumptions!$C$10)/(0.4*SQRT(Assumptions!$C$10)))-0.4*SQRT(Assumptions!$C$10)))-2200*EXP(-Assumptions!$C$11*Assumptions!$C$10)*NORMSDIST(-((LN(2200/Assumptions!$C$7)+(Assumptions!$C$9-Assumptions!$C$11+0.4^2/2)*Assumptions!$C$10)/(0.4*SQRT(Assumptions!$C$10)))) -> 347.19319 | J50: =Assumptions!$C$7*EXP(-Assumptions!$C$9*Assumptions!$C$10)*NORMSDIST(-(((LN(2200/Assumptions!$C$7)+(Assumptions!$C$9-Assumptions!$C$11+0.45^2/2)*Assumptions!$C$10)/(0.45*SQRT(Assumptions!$C$10)))-0.45*SQRT(Assumptions!$C$10)))-2200*EXP(-Assumptions!$C$11*Assumptions!$C$10)*NORMSDIST(-((LN(2200/Assumptions!$C$7)+(Assumptions!$C$9-Assumptions!$C$11+0.45^2/2)*Assumptions!$C$10)/(0.45*SQRT(Assumptions!$C$10)))) -> 367.13301 | K50: =Assumptions!$C$7*EXP(-Assumptions!$C$9*Assumptions!$C$10)*NORMSDIST(-(((LN(2200/Assumptions!$C$7)+(Assumptions!$C$9-Assumptions!$C$11+0.5^2/2)*Assumptions!$C$10)/(0.5*SQRT(Assumptions!$C$10)))-0.5*SQRT(Assumptions!$C$10)))-2200*EXP(-Assumptions!$C$11*Assumptions!$C$10)*NORMSDIST(-((LN(2200/Assumptions!$C$7)+(Assumptions!$C$9-Assumptions!$C$11+0.5^2/2)*Assumptions!$C$10)/(0.5*SQRT(Assumptions!$C$10)))) -> 387.62865
B51: 2250 | C51: =Assumptions!$C$7*EXP(-Assumptions!$C$9*Assumptions!$C$10)*NORMSDIST(-(((LN(2250/Assumptions!$C$7)+(Assumptions!$C$9-Assumptions!$C$11+0.1^2/2)*Assumptions!$C$10)/(0.1*SQRT(Assumptions!$C$10)))-0.1*SQRT(Assumptions!$C$10)))-2250*EXP(-Assumptions!$C$11*Assumptions!$C$10)*NORMSDIST(-((LN(2250/Assumptions!$C$7)+(Assumptions!$C$9-Assumptions!$C$11+0.1^2/2)*Assumptions!$C$10)/(0.1*SQRT(Assumptions!$C$10)))) -> 216.86674 | D51: =Assumptions!$C$7*EXP(-Assumptions!$C$9*Assumptions!$C$10)*NORMSDIST(-(((LN(2250/Assumptions!$C$7)+(Assumptions!$C$9-Assumptions!$C$11+0.15^2/2)*Assumptions!$C$10)/(0.15*SQRT(Assumptions!$C$10)))-0.15*SQRT(Assumptions!$C$10)))-2250*EXP(-Assumptions!$C$11*Assumptions!$C$10)*NORMSDIST(-((LN(2250/Assumptions!$C$7)+(Assumptions!$C$9-Assumptions!$C$11+0.15^2/2)*Assumptions!$C$10)/(0.15*SQRT(Assumptions!$C$10)))) -> 224.77544 | E51: =Assumptions!$C$7*EXP(-Assumptions!$C$9*Assumptions!$C$10)*NORMSDIST(-(((LN(2250/Assumptions!$C$7)+(Assumptions!$C$9-Assumptions!$C$11+0.2^2/2)*Assumptions!$C$10)/(0.2*SQRT(Assumptions!$C$10)))-0.2*SQRT(Assumptions!$C$10)))-2250*EXP(-Assumptions!$C$11*Assumptions!$C$10)*NORMSDIST(-((LN(2250/Assumptions!$C$7)+(Assumptions!$C$9-Assumptions!$C$11+0.2^2/2)*Assumptions!$C$10)/(0.2*SQRT(Assumptions!$C$10)))) -> 238.21227 | F51: =Assumptions!$C$7*EXP(-Assumptions!$C$9*Assumptions!$C$10)*NORMSDIST(-(((LN(2250/Assumptions!$C$7)+(Assumptions!$C$9-Assumptions!$C$11+0.25^2/2)*Assumptions!$C$10)/(0.25*SQRT(Assumptions!$C$10)))-0.25*SQRT(Assumptions!$C$10)))-2250*EXP(-Assumptions!$C$11*Assumptions!$C$10)*NORMSDIST(-((LN(2250/Assumptions!$C$7)+(Assumptions!$C$9-Assumptions!$C$11+0.25^2/2)*Assumptions!$C$10)/(0.25*SQRT(Assumptions!$C$10)))) -> 254.95245 | G51: =Assumptions!$C$7*EXP(-Assumptions!$C$9*Assumptions!$C$10)*NORMSDIST(-(((LN(2250/Assumptions!$C$7)+(Assumptions!$C$9-Assumptions!$C$11+0.3^2/2)*Assumptions!$C$10)/(0.3*SQRT(Assumptions!$C$10)))-0.3*SQRT(Assumptions!$C$10)))-2250*EXP(-Assumptions!$C$11*Assumptions!$C$10)*NORMSDIST(-((LN(2250/Assumptions!$C$7)+(Assumptions!$C$9-Assumptions!$C$11+0.3^2/2)*Assumptions!$C$10)/(0.3*SQRT(Assumptions!$C$10)))) -> 273.64781 | H51: =Assumptions!$C$7*EXP(-Assumptions!$C$9*Assumptions!$C$10)*NORMSDIST(-(((LN(2250/Assumptions!$C$7)+(Assumptions!$C$9-Assumptions!$C$11+0.35^2/2)*Assumptions!$C$10)/(0.35*SQRT(Assumptions!$C$10)))-0.35*SQRT(Assumptions!$C$10)))-2250*EXP(-Assumptions!$C$11*Assumptions!$C$10)*NORMSDIST(-((LN(2250/Assumptions!$C$7)+(Assumptions!$C$9-Assumptions!$C$11+0.35^2/2)*Assumptions!$C$10)/(0.35*SQRT(Assumptions!$C$10)))) -> 293.5555 | I51: =Assumptions!$C$7*EXP(-Assumptions!$C$9*Assumptions!$C$10)*NORMSDIST(-(((LN(2250/Assumptions!$C$7)+(Assumptions!$C$9-Assumptions!$C$11+0.4^2/2)*Assumptions!$C$10)/(0.4*SQRT(Assumptions!$C$10)))-0.4*SQRT(Assumptions!$C$10)))-2250*EXP(-Assumptions!$C$11*Assumptions!$C$10)*NORMSDIST(-((LN(2250/Assumptions!$C$7)+(Assumptions!$C$9-Assumptions!$C$11+0.4^2/2)*Assumptions!$C$10)/(0.4*SQRT(Assumptions!$C$10)))) -> 314.25105 | J51: =Assumptions!$C$7*EXP(-Assumptions!$C$9*Assumptions!$C$10)*NORMSDIST(-(((LN(2250/Assumptions!$C$7)+(Assumptions!$C$9-Assumptions!$C$11+0.45^2/2)*Assumptions!$C$10)/(0.45*SQRT(Assumptions!$C$10)))-0.45*SQRT(Assumptions!$C$10)))-2250*EXP(-Assumptions!$C$11*Assumptions!$C$10)*NORMSDIST(-((LN(2250/Assumptions!$C$7)+(Assumptions!$C$9-Assumptions!$C$11+0.45^2/2)*Assumptions!$C$10)/(0.45*SQRT(Assumptions!$C$10)))) -> 335.47838 | K51: =Assumptions!$C$7*EXP(-Assumptions!$C$9*Assumptions!$C$10)*NORMSDIST(-(((LN(2250/Assumptions!$C$7)+(Assumptions!$C$9-Assumptions!$C$11+0.5^2/2)*Assumptions!$C$10)/(0.5*SQRT(Assumptions!$C$10)))-0.5*SQRT(Assumptions!$C$10)))-2250*EXP(-Assumptions!$C$11*Assumptions!$C$10)*NORMSDIST(-((LN(2250/Assumptions!$C$7)+(Assumptions!$C$9-Assumptions!$C$11+0.5^2/2)*Assumptions!$C$10)/(0.5*SQRT(Assumptions!$C$10)))) -> 357.07472
B52: 2300 | C52: =Assumptions!$C$7*EXP(-Assumptions!$C$9*Assumptions!$C$10)*NORMSDIST(-(((LN(2300/Assumptions!$C$7)+(Assumptions!$C$9-Assumptions!$C$11+0.1^2/2)*Assumptions!$C$10)/(0.1*SQRT(Assumptions!$C$10)))-0.1*SQRT(Assumptions!$C$10)))-2300*EXP(-Assumptions!$C$11*Assumptions!$C$10)*NORMSDIST(-((LN(2300/Assumptions!$C$7)+(Assumptions!$C$9-Assumptions!$C$11+0.1^2/2)*Assumptions!$C$10)/(0.1*SQRT(Assumptions!$C$10)))) -> 169.87163 | D52: =Assumptions!$C$7*EXP(-Assumptions!$C$9*Assumptions!$C$10)*NORMSDIST(-(((LN(2300/Assumptions!$C$7)+(Assumptions!$C$9-Assumptions!$C$11+0.15^2/2)*Assumptions!$C$10)/(0.15*SQRT(Assumptions!$C$10)))-0.15*SQRT(Assumptions!$C$10)))-2300*EXP(-Assumptions!$C$11*Assumptions!$C$10)*NORMSDIST(-((LN(2300/Assumptions!$C$7)+(Assumptions!$C$9-Assumptions!$C$11+0.15^2/2)*Assumptions!$C$10)/(0.15*SQRT(Assumptions!$C$10)))) -> 182.41904 | E52: =Assumptions!$C$7*EXP(-Assumptions!$C$9*Assumptions!$C$10)*NORMSDIST(-(((LN(2300/Assumptions!$C$7)+(Assumptions!$C$9-Assumptions!$C$11+0.2^2/2)*Assumptions!$C$10)/(0.2*SQRT(Assumptions!$C$10)))-0.2*SQRT(Assumptions!$C$10)))-2300*EXP(-Assumptions!$C$11*Assumptions!$C$10)*NORMSDIST(-((LN(2300/Assumptions!$C$7)+(Assumptions!$C$9-Assumptions!$C$11+0.2^2/2)*Assumptions!$C$10)/(0.2*SQRT(Assumptions!$C$10)))) -> 199.57586 | F52: =Assumptions!$C$7*EXP(-Assumptions!$C$9*Assumptions!$C$10)*NORMSDIST(-(((LN(2300/Assumptions!$C$7)+(Assumptions!$C$9-Assumptions!$C$11+0.25^2/2)*Assumptions!$C$10)/(0.25*SQRT(Assumptions!$C$10)))-0.25*SQRT(Assumptions!$C$10)))-2300*EXP(-Assumptions!$C$11*Assumptions!$C$10)*NORMSDIST(-((LN(2300/Assumptions!$C$7)+(Assumptions!$C$9-Assumptions!$C$11+0.25^2/2)*Assumptions!$C$10)/(0.25*SQRT(Assumptions!$C$10)))) -> 219.0666 | G52: =Assumptions!$C$7*EXP(-Assumptions!$C$9*Assumptions!$C$10)*NORMSDIST(-(((LN(2300/Assumptions!$C$7)+(Assumptions!$C$9-Assumptions!$C$11+0.3^2/2)*Assumptions!$C$10)/(0.3*SQRT(Assumptions!$C$10)))-0.3*SQRT(Assumptions!$C$10)))-2300*EXP(-Assumptions!$C$11*Assumptions!$C$10)*NORMSDIST(-((LN(2300/Assumptions!$C$7)+(Assumptions!$C$9-Assumptions!$C$11+0.3^2/2)*Assumptions!$C$10)/(0.3*SQRT(Assumptions!$C$10)))) -> 239.8382 | H52: =Assumptions!$C$7*EXP(-Assumptions!$C$9*Assumptions!$C$10)*NORMSDIST(-(((LN(2300/Assumptions!$C$7)+(Assumptions!$C$9-Assumptions!$C$11+0.35^2/2)*Assumptions!$C$10)/(0.35*SQRT(Assumptions!$C$10)))-0.35*SQRT(Assumptions!$C$10)))-2300*EXP(-Assumptions!$C$11*Assumptions!$C$10)*NORMSDIST(-((LN(2300/Assumptions!$C$7)+(Assumptions!$C$9-Assumptions!$C$11+0.35^2/2)*Assumptions!$C$10)/(0.35*SQRT(Assumptions!$C$10)))) -> 261.37004 | I52: =Assumptions!$C$7*EXP(-Assumptions!$C$9*Assumptions!$C$10)*NORMSDIST(-(((LN(2300/Assumptions!$C$7)+(Assumptions!$C$9-Assumptions!$C$11+0.4^2/2)*Assumptions!$C$10)/(0.4*SQRT(Assumptions!$C$10)))-0.4*SQRT(Assumptions!$C$10)))-2300*EXP(-Assumptions!$C$11*Assumptions!$C$10)*NORMSDIST(-((LN(2300/Assumptions!$C$7)+(Assumptions!$C$9-Assumptions!$C$11+0.4^2/2)*Assumptions!$C$10)/(0.4*SQRT(Assumptions!$C$10)))) -> 283.3803 | J52: =Assumptions!$C$7*EXP(-Assumptions!$C$9*Assumptions!$C$10)*NORMSDIST(-(((LN(2300/Assumptions!$C$7)+(Assumptions!$C$9-Assumptions!$C$11+0.45^2/2)*Assumptions!$C$10)/(0.45*SQRT(Assumptions!$C$10)))-0.45*SQRT(Assumptions!$C$10)))-2300*EXP(-Assumptions!$C$11*Assumptions!$C$10)*NORMSDIST(-((LN(2300/Assumptions!$C$7)+(Assumptions!$C$9-Assumptions!$C$11+0.45^2/2)*Assumptions!$C$10)/(0.45*SQRT(Assumptions!$C$10)))) -> 305.70388 | K52: =Assumptions!$C$7*EXP(-Assumptions!$C$9*Assumptions!$C$10)*NORMSDIST(-(((LN(2300/Assumptions!$C$7)+(Assumptions!$C$9-Assumptions!$C$11+0.5^2/2)*Assumptions!$C$10)/(0.5*SQRT(Assumptions!$C$10)))-0.5*SQRT(Assumptions!$C$10)))-2300*EXP(-Assumptions!$C$11*Assumptions!$C$10)*NORMSDIST(-((LN(2300/Assumptions!$C$7)+(Assumptions!$C$9-Assumptions!$C$11+0.5^2/2)*Assumptions!$C$10)/(0.5*SQRT(Assumptions!$C$10)))) -> 328.23752
B53: 2350 | C53: =Assumptions!$C$7*EXP(-Assumptions!$C$9*Assumptions!$C$10)*NORMSDIST(-(((LN(2350/Assumptions!$C$7)+(Assumptions!$C$9-Assumptions!$C$11+0.1^2/2)*Assumptions!$C$10)/(0.1*SQRT(Assumptions!$C$10)))-0.1*SQRT(Assumptions!$C$10)))-2350*EXP(-Assumptions!$C$11*Assumptions!$C$10)*NORMSDIST(-((LN(2350/Assumptions!$C$7)+(Assumptions!$C$9-Assumptions!$C$11+0.1^2/2)*Assumptions!$C$10)/(0.1*SQRT(Assumptions!$C$10)))) -> 126.30664 | D53: =Assumptions!$C$7*EXP(-Assumptions!$C$9*Assumptions!$C$10)*NORMSDIST(-(((LN(2350/Assumptions!$C$7)+(Assumptions!$C$9-Assumptions!$C$11+0.15^2/2)*Assumptions!$C$10)/(0.15*SQRT(Assumptions!$C$10)))-0.15*SQRT(Assumptions!$C$10)))-2350*EXP(-Assumptions!$C$11*Assumptions!$C$10)*NORMSDIST(-((LN(2350/Assumptions!$C$7)+(Assumptions!$C$9-Assumptions!$C$11+0.15^2/2)*Assumptions!$C$10)/(0.15*SQRT(Assumptions!$C$10)))) -> 143.93001 | E53: =Assumptions!$C$7*EXP(-Assumptions!$C$9*Assumptions!$C$10)*NORMSDIST(-(((LN(2350/Assumptions!$C$7)+(Assumptions!$C$9-Assumptions!$C$11+0.2^2/2)*Assumptions!$C$10)/(0.2*SQRT(Assumptions!$C$10)))-0.2*SQRT(Assumptions!$C$10)))-2350*EXP(-Assumptions!$C$11*Assumptions!$C$10)*NORMSDIST(-((LN(2350/Assumptions!$C$7)+(Assumptions!$C$9-Assumptions!$C$11+0.2^2/2)*Assumptions!$C$10)/(0.2*SQRT(Assumptions!$C$10)))) -> 164.43922 | F53: =Assumptions!$C$7*EXP(-Assumptions!$C$9*Assumptions!$C$10)*NORMSDIST(-(((LN(2350/Assumptions!$C$7)+(Assumptions!$C$9-Assumptions!$C$11+0.25^2/2)*Assumptions!$C$10)/(0.25*SQRT(Assumptions!$C$10)))-0.25*SQRT(Assumptions!$C$10)))-2350*EXP(-Assumptions!$C$11*Assumptions!$C$10)*NORMSDIST(-((LN(2350/Assumptions!$C$7)+(Assumptions!$C$9-Assumptions!$C$11+0.25^2/2)*Assumptions!$C$10)/(0.25*SQRT(Assumptions!$C$10)))) -> 186.23582 | G53: =Assumptions!$C$7*EXP(-Assumptions!$C$9*Assumptions!$C$10)*NORMSDIST(-(((LN(2350/Assumptions!$C$7)+(Assumptions!$C$9-Assumptions!$C$11+0.3^2/2)*Assumptions!$C$10)/(0.3*SQRT(Assumptions!$C$10)))-0.3*SQRT(Assumptions!$C$10)))-2350*EXP(-Assumptions!$C$11*Assumptions!$C$10)*NORMSDIST(-((LN(2350/Assumptions!$C$7)+(Assumptions!$C$9-Assumptions!$C$11+0.3^2/2)*Assumptions!$C$10)/(0.3*SQRT(Assumptions!$C$10)))) -> 208.69734 | H53: =Assumptions!$C$7*EXP(-Assumptions!$C$9*Assumptions!$C$10)*NORMSDIST(-(((LN(2350/Assumptions!$C$7)+(Assumptions!$C$9-Assumptions!$C$11+0.35^2/2)*Assumptions!$C$10)/(0.35*SQRT(Assumptions!$C$10)))-0.35*SQRT(Assumptions!$C$10)))-2350*EXP(-Assumptions!$C$11*Assumptions!$C$10)*NORMSDIST(-((LN(2350/Assumptions!$C$7)+(Assumptions!$C$9-Assumptions!$C$11+0.35^2/2)*Assumptions!$C$10)/(0.35*SQRT(Assumptions!$C$10)))) -> 231.53702 | I53: =Assumptions!$C$7*EXP(-Assumptions!$C$9*Assumptions!$C$10)*NORMSDIST(-(((LN(2350/Assumptions!$C$7)+(Assumptions!$C$9-Assumptions!$C$11+0.4^2/2)*Assumptions!$C$10)/(0.4*SQRT(Assumptions!$C$10)))-0.4*SQRT(Assumptions!$C$10)))-2350*EXP(-Assumptions!$C$11*Assumptions!$C$10)*NORMSDIST(-((LN(2350/Assumptions!$C$7)+(Assumptions!$C$9-Assumptions!$C$11+0.4^2/2)*Assumptions!$C$10)/(0.4*SQRT(Assumptions!$C$10)))) -> 254.60465 | J53: =Assumptions!$C$7*EXP(-Assumptions!$C$9*Assumptions!$C$10)*NORMSDIST(-(((LN(2350/Assumptions!$C$7)+(Assumptions!$C$9-Assumptions!$C$11+0.45^2/2)*Assumptions!$C$10)/(0.45*SQRT(Assumptions!$C$10)))-0.45*SQRT(Assumptions!$C$10)))-2350*EXP(-Assumptions!$C$11*Assumptions!$C$10)*NORMSDIST(-((LN(2350/Assumptions!$C$7)+(Assumptions!$C$9-Assumptions!$C$11+0.45^2/2)*Assumptions!$C$10)/(0.45*SQRT(Assumptions!$C$10)))) -> 277.81344 | K53: =Assumptions!$C$7*EXP(-Assumptions!$C$9*Assumptions!$C$10)*NORMSDIST(-(((LN(2350/Assumptions!$C$7)+(Assumptions!$C$9-Assumptions!$C$11+0.5^2/2)*Assumptions!$C$10)/(0.5*SQRT(Assumptions!$C$10)))-0.5*SQRT(Assumptions!$C$10)))-2350*EXP(-Assumptions!$C$11*Assumptions!$C$10)*NORMSDIST(-((LN(2350/Assumptions!$C$7)+(Assumptions!$C$9-Assumptions!$C$11+0.5^2/2)*Assumptions!$C$10)/(0.5*SQRT(Assumptions!$C$10)))) -> 301.1092
B54: 2400 | C54: =Assumptions!$C$7*EXP(-Assumptions!$C$9*Assumptions!$C$10)*NORMSDIST(-(((LN(2400/Assumptions!$C$7)+(Assumptions!$C$9-Assumptions!$C$11+0.1^2/2)*Assumptions!$C$10)/(0.1*SQRT(Assumptions!$C$10)))-0.1*SQRT(Assumptions!$C$10)))-2400*EXP(-Assumptions!$C$11*Assumptions!$C$10)*NORMSDIST(-((LN(2400/Assumptions!$C$7)+(Assumptions!$C$9-Assumptions!$C$11+0.1^2/2)*Assumptions!$C$10)/(0.1*SQRT(Assumptions!$C$10)))) -> 88.176223 | D54: =Assumptions!$C$7*EXP(-Assumptions!$C$9*Assumptions!$C$10)*NORMSDIST(-(((LN(2400/Assumptions!$C$7)+(Assumptions!$C$9-Assumptions!$C$11+0.15^2/2)*Assumptions!$C$10)/(0.15*SQRT(Assumptions!$C$10)))-0.15*SQRT(Assumptions!$C$10)))-2400*EXP(-Assumptions!$C$11*Assumptions!$C$10)*NORMSDIST(-((LN(2400/Assumptions!$C$7)+(Assumptions!$C$9-Assumptions!$C$11+0.15^2/2)*Assumptions!$C$10)/(0.15*SQRT(Assumptions!$C$10)))) -> 110.12014 | E54: =Assumptions!$C$7*EXP(-Assumptions!$C$9*Assumptions!$C$10)*NORMSDIST(-(((LN(2400/Assumptions!$C$7)+(Assumptions!$C$9-Assumptions!$C$11+0.2^2/2)*Assumptions!$C$10)/(0.2*SQRT(Assumptions!$C$10)))-0.2*SQRT(Assumptions!$C$10)))-2400*EXP(-Assumptions!$C$11*Assumptions!$C$10)*NORMSDIST(-((LN(2400/Assumptions!$C$7)+(Assumptions!$C$9-Assumptions!$C$11+0.2^2/2)*Assumptions!$C$10)/(0.2*SQRT(Assumptions!$C$10)))) -> 133.14676 | F54: =Assumptions!$C$7*EXP(-Assumptions!$C$9*Assumptions!$C$10)*NORMSDIST(-(((LN(2400/Assumptions!$C$7)+(Assumptions!$C$9-Assumptions!$C$11+0.25^2/2)*Assumptions!$C$10)/(0.25*SQRT(Assumptions!$C$10)))-0.25*SQRT(Assumptions!$C$10)))-2400*EXP(-Assumptions!$C$11*Assumptions!$C$10)*NORMSDIST(-((LN(2400/Assumptions!$C$7)+(Assumptions!$C$9-Assumptions!$C$11+0.25^2/2)*Assumptions!$C$10)/(0.25*SQRT(Assumptions!$C$10)))) -> 156.61256 | G54: =Assumptions!$C$7*EXP(-Assumptions!$C$9*Assumptions!$C$10)*NORMSDIST(-(((LN(2400/Assumptions!$C$7)+(Assumptions!$C$9-Assumptions!$C$11+0.3^2/2)*Assumptions!$C$10)/(0.3*SQRT(Assumptions!$C$10)))-0.3*SQRT(Assumptions!$C$10)))-2400*EXP(-Assumptions!$C$11*Assumptions!$C$10)*NORMSDIST(-((LN(2400/Assumptions!$C$7)+(Assumptions!$C$9-Assumptions!$C$11+0.3^2/2)*Assumptions!$C$10)/(0.3*SQRT(Assumptions!$C$10)))) -> 180.29018 | H54: =Assumptions!$C$7*EXP(-Assumptions!$C$9*Assumptions!$C$10)*NORMSDIST(-(((LN(2400/Assumptions!$C$7)+(Assumptions!$C$9-Assumptions!$C$11+0.35^2/2)*Assumptions!$C$10)/(0.35*SQRT(Assumptions!$C$10)))-0.35*SQRT(Assumptions!$C$10)))-2400*EXP(-Assumptions!$C$11*Assumptions!$C$10)*NORMSDIST(-((LN(2400/Assumptions!$C$7)+(Assumptions!$C$9-Assumptions!$C$11+0.35^2/2)*Assumptions!$C$10)/(0.35*SQRT(Assumptions!$C$10)))) -> 204.07804 | I54: =Assumptions!$C$7*EXP(-Assumptions!$C$9*Assumptions!$C$10)*NORMSDIST(-(((LN(2400/Assumptions!$C$7)+(Assumptions!$C$9-Assumptions!$C$11+0.4^2/2)*Assumptions!$C$10)/(0.4*SQRT(Assumptions!$C$10)))-0.4*SQRT(Assumptions!$C$10)))-2400*EXP(-Assumptions!$C$11*Assumptions!$C$10)*NORMSDIST(-((LN(2400/Assumptions!$C$7)+(Assumptions!$C$9-Assumptions!$C$11+0.4^2/2)*Assumptions!$C$10)/(0.4*SQRT(Assumptions!$C$10)))) -> 227.92296 | J54: =Assumptions!$C$7*EXP(-Assumptions!$C$9*Assumptions!$C$10)*NORMSDIST(-(((LN(2400/Assumptions!$C$7)+(Assumptions!$C$9-Assumptions!$C$11+0.45^2/2)*Assumptions!$C$10)/(0.45*SQRT(Assumptions!$C$10)))-0.45*SQRT(Assumptions!$C$10)))-2400*EXP(-Assumptions!$C$11*Assumptions!$C$10)*NORMSDIST(-((LN(2400/Assumptions!$C$7)+(Assumptions!$C$9-Assumptions!$C$11+0.45^2/2)*Assumptions!$C$10)/(0.45*SQRT(Assumptions!$C$10)))) -> 251.79356 | K54: =Assumptions!$C$7*EXP(-Assumptions!$C$9*Assumptions!$C$10)*NORMSDIST(-(((LN(2400/Assumptions!$C$7)+(Assumptions!$C$9-Assumptions!$C$11+0.5^2/2)*Assumptions!$C$10)/(0.5*SQRT(Assumptions!$C$10)))-0.5*SQRT(Assumptions!$C$10)))-2400*EXP(-Assumptions!$C$11*Assumptions!$C$10)*NORMSDIST(-((LN(2400/Assumptions!$C$7)+(Assumptions!$C$9-Assumptions!$C$11+0.5^2/2)*Assumptions!$C$10)/(0.5*SQRT(Assumptions!$C$10)))) -> 275.66947
B55: 2450 | C55: =Assumptions!$C$7*EXP(-Assumptions!$C$9*Assumptions!$C$10)*NORMSDIST(-(((LN(2450/Assumptions!$C$7)+(Assumptions!$C$9-Assumptions!$C$11+0.1^2/2)*Assumptions!$C$10)/(0.1*SQRT(Assumptions!$C$10)))-0.1*SQRT(Assumptions!$C$10)))-2450*EXP(-Assumptions!$C$11*Assumptions!$C$10)*NORMSDIST(-((LN(2450/Assumptions!$C$7)+(Assumptions!$C$9-Assumptions!$C$11+0.1^2/2)*Assumptions!$C$10)/(0.1*SQRT(Assumptions!$C$10)))) -> 57.217996 | D55: =Assumptions!$C$7*EXP(-Assumptions!$C$9*Assumptions!$C$10)*NORMSDIST(-(((LN(2450/Assumptions!$C$7)+(Assumptions!$C$9-Assumptions!$C$11+0.15^2/2)*Assumptions!$C$10)/(0.15*SQRT(Assumptions!$C$10)))-0.15*SQRT(Assumptions!$C$10)))-2450*EXP(-Assumptions!$C$11*Assumptions!$C$10)*NORMSDIST(-((LN(2450/Assumptions!$C$7)+(Assumptions!$C$9-Assumptions!$C$11+0.15^2/2)*Assumptions!$C$10)/(0.15*SQRT(Assumptions!$C$10)))) -> 81.523576 | E55: =Assumptions!$C$7*EXP(-Assumptions!$C$9*Assumptions!$C$10)*NORMSDIST(-(((LN(2450/Assumptions!$C$7)+(Assumptions!$C$9-Assumptions!$C$11+0.2^2/2)*Assumptions!$C$10)/(0.2*SQRT(Assumptions!$C$10)))-0.2*SQRT(Assumptions!$C$10)))-2450*EXP(-Assumptions!$C$11*Assumptions!$C$10)*NORMSDIST(-((LN(2450/Assumptions!$C$7)+(Assumptions!$C$9-Assumptions!$C$11+0.2^2/2)*Assumptions!$C$10)/(0.2*SQRT(Assumptions!$C$10)))) -> 105.88528 | F55: =Assumptions!$C$7*EXP(-Assumptions!$C$9*Assumptions!$C$10)*NORMSDIST(-(((LN(2450/Assumptions!$C$7)+(Assumptions!$C$9-Assumptions!$C$11+0.25^2/2)*Assumptions!$C$10)/(0.25*SQRT(Assumptions!$C$10)))-0.25*SQRT(Assumptions!$C$10)))-2450*EXP(-Assumptions!$C$11*Assumptions!$C$10)*NORMSDIST(-((LN(2450/Assumptions!$C$7)+(Assumptions!$C$9-Assumptions!$C$11+0.25^2/2)*Assumptions!$C$10)/(0.25*SQRT(Assumptions!$C$10)))) -> 130.25881 | G55: =Assumptions!$C$7*EXP(-Assumptions!$C$9*Assumptions!$C$10)*NORMSDIST(-(((LN(2450/Assumptions!$C$7)+(Assumptions!$C$9-Assumptions!$C$11+0.3^2/2)*Assumptions!$C$10)/(0.3*SQRT(Assumptions!$C$10)))-0.3*SQRT(Assumptions!$C$10)))-2450*EXP(-Assumptions!$C$11*Assumptions!$C$10)*NORMSDIST(-((LN(2450/Assumptions!$C$7)+(Assumptions!$C$9-Assumptions!$C$11+0.3^2/2)*Assumptions!$C$10)/(0.3*SQRT(Assumptions!$C$10)))) -> 154.62683 | H55: =Assumptions!$C$7*EXP(-Assumptions!$C$9*Assumptions!$C$10)*NORMSDIST(-(((LN(2450/Assumptions!$C$7)+(Assumptions!$C$9-Assumptions!$C$11+0.35^2/2)*Assumptions!$C$10)/(0.35*SQRT(Assumptions!$C$10)))-0.35*SQRT(Assumptions!$C$10)))-2450*EXP(-Assumptions!$C$11*Assumptions!$C$10)*NORMSDIST(-((LN(2450/Assumptions!$C$7)+(Assumptions!$C$9-Assumptions!$C$11+0.35^2/2)*Assumptions!$C$10)/(0.35*SQRT(Assumptions!$C$10)))) -> 178.97973 | I55: =Assumptions!$C$7*EXP(-Assumptions!$C$9*Assumptions!$C$10)*NORMSDIST(-(((LN(2450/Assumptions!$C$7)+(Assumptions!$C$9-Assumptions!$C$11+0.4^2/2)*Assumptions!$C$10)/(0.4*SQRT(Assumptions!$C$10)))-0.4*SQRT(Assumptions!$C$10)))-2450*EXP(-Assumptions!$C$11*Assumptions!$C$10)*NORMSDIST(-((LN(2450/Assumptions!$C$7)+(Assumptions!$C$9-Assumptions!$C$11+0.4^2/2)*Assumptions!$C$10)/(0.4*SQRT(Assumptions!$C$10)))) -> 203.31085 | J55: =Assumptions!$C$7*EXP(-Assumptions!$C$9*Assumptions!$C$10)*NORMSDIST(-(((LN(2450/Assumptions!$C$7)+(Assumptions!$C$9-Assumptions!$C$11+0.45^2/2)*Assumptions!$C$10)/(0.45*SQRT(Assumptions!$C$10)))-0.45*SQRT(Assumptions!$C$10)))-2450*EXP(-Assumptions!$C$11*Assumptions!$C$10)*NORMSDIST(-((LN(2450/Assumptions!$C$7)+(Assumptions!$C$9-Assumptions!$C$11+0.45^2/2)*Assumptions!$C$10)/(0.45*SQRT(Assumptions!$C$10)))) -> 227.61478 | K55: =Assumptions!$C$7*EXP(-Assumptions!$C$9*Assumptions!$C$10)*NORMSDIST(-(((LN(2450/Assumptions!$C$7)+(Assumptions!$C$9-Assumptions!$C$11+0.5^2/2)*Assumptions!$C$10)/(0.5*SQRT(Assumptions!$C$10)))-0.5*SQRT(Assumptions!$C$10)))-2450*EXP(-Assumptions!$C$11*Assumptions!$C$10)*NORMSDIST(-((LN(2450/Assumptions!$C$7)+(Assumptions!$C$9-Assumptions!$C$11+0.5^2/2)*Assumptions!$C$10)/(0.5*SQRT(Assumptions!$C$10)))) -> 251.8868
B56: 2500 | C56: =Assumptions!$C$7*EXP(-Assumptions!$C$9*Assumptions!$C$10)*NORMSDIST(-(((LN(2500/Assumptions!$C$7)+(Assumptions!$C$9-Assumptions!$C$11+0.1^2/2)*Assumptions!$C$10)/(0.1*SQRT(Assumptions!$C$10)))-0.1*SQRT(Assumptions!$C$10)))-2500*EXP(-Assumptions!$C$11*Assumptions!$C$10)*NORMSDIST(-((LN(2500/Assumptions!$C$7)+(Assumptions!$C$9-Assumptions!$C$11+0.1^2/2)*Assumptions!$C$10)/(0.1*SQRT(Assumptions!$C$10)))) -> 34.227 | D56: =Assumptions!$C$7*EXP(-Assumptions!$C$9*Assumptions!$C$10)*NORMSDIST(-(((LN(2500/Assumptions!$C$7)+(Assumptions!$C$9-Assumptions!$C$11+0.15^2/2)*Assumptions!$C$10)/(0.15*SQRT(Assumptions!$C$10)))-0.15*SQRT(Assumptions!$C$10)))-2500*EXP(-Assumptions!$C$11*Assumptions!$C$10)*NORMSDIST(-((LN(2500/Assumptions!$C$7)+(Assumptions!$C$9-Assumptions!$C$11+0.15^2/2)*Assumptions!$C$10)/(0.15*SQRT(Assumptions!$C$10)))) -> 58.30183 | E56: =Assumptions!$C$7*EXP(-Assumptions!$C$9*Assumptions!$C$10)*NORMSDIST(-(((LN(2500/Assumptions!$C$7)+(Assumptions!$C$9-Assumptions!$C$11+0.2^2/2)*Assumptions!$C$10)/(0.2*SQRT(Assumptions!$C$10)))-0.2*SQRT(Assumptions!$C$10)))-2500*EXP(-Assumptions!$C$11*Assumptions!$C$10)*NORMSDIST(-((LN(2500/Assumptions!$C$7)+(Assumptions!$C$9-Assumptions!$C$11+0.2^2/2)*Assumptions!$C$10)/(0.2*SQRT(Assumptions!$C$10)))) -> 82.67023 | F56: =Assumptions!$C$7*EXP(-Assumptions!$C$9*Assumptions!$C$10)*NORMSDIST(-(((LN(2500/Assumptions!$C$7)+(Assumptions!$C$9-Assumptions!$C$11+0.25^2/2)*Assumptions!$C$10)/(0.25*SQRT(Assumptions!$C$10)))-0.25*SQRT(Assumptions!$C$10)))-2500*EXP(-Assumptions!$C$11*Assumptions!$C$10)*NORMSDIST(-((LN(2500/Assumptions!$C$7)+(Assumptions!$C$9-Assumptions!$C$11+0.25^2/2)*Assumptions!$C$10)/(0.25*SQRT(Assumptions!$C$10)))) -> 107.14646 | G56: =Assumptions!$C$7*EXP(-Assumptions!$C$9*Assumptions!$C$10)*NORMSDIST(-(((LN(2500/Assumptions!$C$7)+(Assumptions!$C$9-Assumptions!$C$11+0.3^2/2)*Assumptions!$C$10)/(0.3*SQRT(Assumptions!$C$10)))-0.3*SQRT(Assumptions!$C$10)))-2500*EXP(-Assumptions!$C$11*Assumptions!$C$10)*NORMSDIST(-((LN(2500/Assumptions!$C$7)+(Assumptions!$C$9-Assumptions!$C$11+0.3^2/2)*Assumptions!$C$10)/(0.3*SQRT(Assumptions!$C$10)))) -> 131.66529 | H56: =Assumptions!$C$7*EXP(-Assumptions!$C$9*Assumptions!$C$10)*NORMSDIST(-(((LN(2500/Assumptions!$C$7)+(Assumptions!$C$9-Assumptions!$C$11+0.35^2/2)*Assumptions!$C$10)/(0.35*SQRT(Assumptions!$C$10)))-0.35*SQRT(Assumptions!$C$10)))-2500*EXP(-Assumptions!$C$11*Assumptions!$C$10)*NORMSDIST(-((LN(2500/Assumptions!$C$7)+(Assumptions!$C$9-Assumptions!$C$11+0.35^2/2)*Assumptions!$C$10)/(0.35*SQRT(Assumptions!$C$10)))) -> 156.19646 | I56: =Assumptions!$C$7*EXP(-Assumptions!$C$9*Assumptions!$C$10)*NORMSDIST(-(((LN(2500/Assumptions!$C$7)+(Assumptions!$C$9-Assumptions!$C$11+0.4^2/2)*Assumptions!$C$10)/(0.4*SQRT(Assumptions!$C$10)))-0.4*SQRT(Assumptions!$C$10)))-2500*EXP(-Assumptions!$C$11*Assumptions!$C$10)*NORMSDIST(-((LN(2500/Assumptions!$C$7)+(Assumptions!$C$9-Assumptions!$C$11+0.4^2/2)*Assumptions!$C$10)/(0.4*SQRT(Assumptions!$C$10)))) -> 180.72289 | J56: =Assumptions!$C$7*EXP(-Assumptions!$C$9*Assumptions!$C$10)*NORMSDIST(-(((LN(2500/Assumptions!$C$7)+(Assumptions!$C$9-Assumptions!$C$11+0.45^2/2)*Assumptions!$C$10)/(0.45*SQRT(Assumptions!$C$10)))-0.45*SQRT(Assumptions!$C$10)))-2500*EXP(-Assumptions!$C$11*Assumptions!$C$10)*NORMSDIST(-((LN(2500/Assumptions!$C$7)+(Assumptions!$C$9-Assumptions!$C$11+0.45^2/2)*Assumptions!$C$10)/(0.45*SQRT(Assumptions!$C$10)))) -> 205.23338 | K56: =Assumptions!$C$7*EXP(-Assumptions!$C$9*Assumptions!$C$10)*NORMSDIST(-(((LN(2500/Assumptions!$C$7)+(Assumptions!$C$9-Assumptions!$C$11+0.5^2/2)*Assumptions!$C$10)/(0.5*SQRT(Assumptions!$C$10)))-0.5*SQRT(Assumptions!$C$10)))-2500*EXP(-Assumptions!$C$11*Assumptions!$C$10)*NORMSDIST(-((LN(2500/Assumptions!$C$7)+(Assumptions!$C$9-Assumptions!$C$11+0.5^2/2)*Assumptions!$C$10)/(0.5*SQRT(Assumptions!$C$10)))) -> 229.71971
B57: 2550 | C57: =Assumptions!$C$7*EXP(-Assumptions!$C$9*Assumptions!$C$10)*NORMSDIST(-(((LN(2550/Assumptions!$C$7)+(Assumptions!$C$9-Assumptions!$C$11+0.1^2/2)*Assumptions!$C$10)/(0.1*SQRT(Assumptions!$C$10)))-0.1*SQRT(Assumptions!$C$10)))-2550*EXP(-Assumptions!$C$11*Assumptions!$C$10)*NORMSDIST(-((LN(2550/Assumptions!$C$7)+(Assumptions!$C$9-Assumptions!$C$11+0.1^2/2)*Assumptions!$C$10)/(0.1*SQRT(Assumptions!$C$10)))) -> 18.758517 | D57: =Assumptions!$C$7*EXP(-Assumptions!$C$9*Assumptions!$C$10)*NORMSDIST(-(((LN(2550/Assumptions!$C$7)+(Assumptions!$C$9-Assumptions!$C$11+0.15^2/2)*Assumptions!$C$10)/(0.15*SQRT(Assumptions!$C$10)))-0.15*SQRT(Assumptions!$C$10)))-2550*EXP(-Assumptions!$C$11*Assumptions!$C$10)*NORMSDIST(-((LN(2550/Assumptions!$C$7)+(Assumptions!$C$9-Assumptions!$C$11+0.15^2/2)*Assumptions!$C$10)/(0.15*SQRT(Assumptions!$C$10)))) -> 40.231048 | E57: =Assumptions!$C$7*EXP(-Assumptions!$C$9*Assumptions!$C$10)*NORMSDIST(-(((LN(2550/Assumptions!$C$7)+(Assumptions!$C$9-Assumptions!$C$11+0.2^2/2)*Assumptions!$C$10)/(0.2*SQRT(Assumptions!$C$10)))-0.2*SQRT(Assumptions!$C$10)))-2550*EXP(-Assumptions!$C$11*Assumptions!$C$10)*NORMSDIST(-((LN(2550/Assumptions!$C$7)+(Assumptions!$C$9-Assumptions!$C$11+0.2^2/2)*Assumptions!$C$10)/(0.2*SQRT(Assumptions!$C$10)))) -> 63.353754 | F57: =Assumptions!$C$7*EXP(-Assumptions!$C$9*Assumptions!$C$10)*NORMSDIST(-(((LN(2550/Assumptions!$C$7)+(Assumptions!$C$9-Assumptions!$C$11+0.25^2/2)*Assumptions!$C$10)/(0.25*SQRT(Assumptions!$C$10)))-0.25*SQRT(Assumptions!$C$10)))-2550*EXP(-Assumptions!$C$11*Assumptions!$C$10)*NORMSDIST(-((LN(2550/Assumptions!$C$7)+(Assumptions!$C$9-Assumptions!$C$11+0.25^2/2)*Assumptions!$C$10)/(0.25*SQRT(Assumptions!$C$10)))) -> 87.164819 | G57: =Assumptions!$C$7*EXP(-Assumptions!$C$9*Assumptions!$C$10)*NORMSDIST(-(((LN(2550/Assumptions!$C$7)+(Assumptions!$C$9-Assumptions!$C$11+0.3^2/2)*Assumptions!$C$10)/(0.3*SQRT(Assumptions!$C$10)))-0.3*SQRT(Assumptions!$C$10)))-2550*EXP(-Assumptions!$C$11*Assumptions!$C$10)*NORMSDIST(-((LN(2550/Assumptions!$C$7)+(Assumptions!$C$9-Assumptions!$C$11+0.3^2/2)*Assumptions!$C$10)/(0.3*SQRT(Assumptions!$C$10)))) -> 111.31684 | H57: =Assumptions!$C$7*EXP(-Assumptions!$C$9*Assumptions!$C$10)*NORMSDIST(-(((LN(2550/Assumptions!$C$7)+(Assumptions!$C$9-Assumptions!$C$11+0.35^2/2)*Assumptions!$C$10)/(0.35*SQRT(Assumptions!$C$10)))-0.35*SQRT(Assumptions!$C$10)))-2550*EXP(-Assumptions!$C$11*Assumptions!$C$10)*NORMSDIST(-((LN(2550/Assumptions!$C$7)+(Assumptions!$C$9-Assumptions!$C$11+0.35^2/2)*Assumptions!$C$10)/(0.35*SQRT(Assumptions!$C$10)))) -> 135.65401 | I57: =Assumptions!$C$7*EXP(-Assumptions!$C$9*Assumptions!$C$10)*NORMSDIST(-(((LN(2550/Assumptions!$C$7)+(Assumptions!$C$9-Assumptions!$C$11+0.4^2/2)*Assumptions!$C$10)/(0.4*SQRT(Assumptions!$C$10)))-0.4*SQRT(Assumptions!$C$10)))-2550*EXP(-Assumptions!$C$11*Assumptions!$C$10)*NORMSDIST(-((LN(2550/Assumptions!$C$7)+(Assumptions!$C$9-Assumptions!$C$11+0.4^2/2)*Assumptions!$C$10)/(0.4*SQRT(Assumptions!$C$10)))) -> 160.09523 | J57: =Assumptions!$C$7*EXP(-Assumptions!$C$9*Assumptions!$C$10)*NORMSDIST(-(((LN(2550/Assumptions!$C$7)+(Assumptions!$C$9-Assumptions!$C$11+0.45^2/2)*Assumptions!$C$10)/(0.45*SQRT(Assumptions!$C$10)))-0.45*SQRT(Assumptions!$C$10)))-2550*EXP(-Assumptions!$C$11*Assumptions!$C$10)*NORMSDIST(-((LN(2550/Assumptions!$C$7)+(Assumptions!$C$9-Assumptions!$C$11+0.45^2/2)*Assumptions!$C$10)/(0.45*SQRT(Assumptions!$C$10)))) -> 184.59332 | K57: =Assumptions!$C$7*EXP(-Assumptions!$C$9*Assumptions!$C$10)*NORMSDIST(-(((LN(2550/Assumptions!$C$7)+(Assumptions!$C$9-Assumptions!$C$11+0.5^2/2)*Assumptions!$C$10)/(0.5*SQRT(Assumptions!$C$10)))-0.5*SQRT(Assumptions!$C$10)))-2550*EXP(-Assumptions!$C$11*Assumptions!$C$10)*NORMSDIST(-((LN(2550/Assumptions!$C$7)+(Assumptions!$C$9-Assumptions!$C$11+0.5^2/2)*Assumptions!$C$10)/(0.5*SQRT(Assumptions!$C$10)))) -> 209.11824
B58: 2600 | C58: =Assumptions!$C$7*EXP(-Assumptions!$C$9*Assumptions!$C$10)*NORMSDIST(-(((LN(2600/Assumptions!$C$7)+(Assumptions!$C$9-Assumptions!$C$11+0.1^2/2)*Assumptions!$C$10)/(0.1*SQRT(Assumptions!$C$10)))-0.1*SQRT(Assumptions!$C$10)))-2600*EXP(-Assumptions!$C$11*Assumptions!$C$10)*NORMSDIST(-((LN(2600/Assumptions!$C$7)+(Assumptions!$C$9-Assumptions!$C$11+0.1^2/2)*Assumptions!$C$10)/(0.1*SQRT(Assumptions!$C$10)))) -> 9.3821265 | D58: =Assumptions!$C$7*EXP(-Assumptions!$C$9*Assumptions!$C$10)*NORMSDIST(-(((LN(2600/Assumptions!$C$7)+(Assumptions!$C$9-Assumptions!$C$11+0.15^2/2)*Assumptions!$C$10)/(0.15*SQRT(Assumptions!$C$10)))-0.15*SQRT(Assumptions!$C$10)))-2600*EXP(-Assumptions!$C$11*Assumptions!$C$10)*NORMSDIST(-((LN(2600/Assumptions!$C$7)+(Assumptions!$C$9-Assumptions!$C$11+0.15^2/2)*Assumptions!$C$10)/(0.15*SQRT(Assumptions!$C$10)))) -> 26.768322 | E58: =Assumptions!$C$7*EXP(-Assumptions!$C$9*Assumptions!$C$10)*NORMSDIST(-(((LN(2600/Assumptions!$C$7)+(Assumptions!$C$9-Assumptions!$C$11+0.2^2/2)*Assumptions!$C$10)/(0.2*SQRT(Assumptions!$C$10)))-0.2*SQRT(Assumptions!$C$10)))-2600*EXP(-Assumptions!$C$11*Assumptions!$C$10)*NORMSDIST(-((LN(2600/Assumptions!$C$7)+(Assumptions!$C$9-Assumptions!$C$11+0.2^2/2)*Assumptions!$C$10)/(0.2*SQRT(Assumptions!$C$10)))) -> 47.650992 | F58: =Assumptions!$C$7*EXP(-Assumptions!$C$9*Assumptions!$C$10)*NORMSDIST(-(((LN(2600/Assumptions!$C$7)+(Assumptions!$C$9-Assumptions!$C$11+0.25^2/2)*Assumptions!$C$10)/(0.25*SQRT(Assumptions!$C$10)))-0.25*SQRT(Assumptions!$C$10)))-2600*EXP(-Assumptions!$C$11*Assumptions!$C$10)*NORMSDIST(-((LN(2600/Assumptions!$C$7)+(Assumptions!$C$9-Assumptions!$C$11+0.25^2/2)*Assumptions!$C$10)/(0.25*SQRT(Assumptions!$C$10)))) -> 70.133576 | G58: =Assumptions!$C$7*EXP(-Assumptions!$C$9*Assumptions!$C$10)*NORMSDIST(-(((LN(2600/Assumptions!$C$7)+(Assumptions!$C$9-Assumptions!$C$11+0.3^2/2)*Assumptions!$C$10)/(0.3*SQRT(Assumptions!$C$10)))-0.3*SQRT(Assumptions!$C$10)))-2600*EXP(-Assumptions!$C$11*Assumptions!$C$10)*NORMSDIST(-((LN(2600/Assumptions!$C$7)+(Assumptions!$C$9-Assumptions!$C$11+0.3^2/2)*Assumptions!$C$10)/(0.3*SQRT(Assumptions!$C$10)))) -> 93.453284 | H58: =Assumptions!$C$7*EXP(-Assumptions!$C$9*Assumptions!$C$10)*NORMSDIST(-(((LN(2600/Assumptions!$C$7)+(Assumptions!$C$9-Assumptions!$C$11+0.35^2/2)*Assumptions!$C$10)/(0.35*SQRT(Assumptions!$C$10)))-0.35*SQRT(Assumptions!$C$10)))-2600*EXP(-Assumptions!$C$11*Assumptions!$C$10)*NORMSDIST(-((LN(2600/Assumptions!$C$7)+(Assumptions!$C$9-Assumptions!$C$11+0.35^2/2)*Assumptions!$C$10)/(0.35*SQRT(Assumptions!$C$10)))) -> 117.25411 | I58: =Assumptions!$C$7*EXP(-Assumptions!$C$9*Assumptions!$C$10)*NORMSDIST(-(((LN(2600/Assumptions!$C$7)+(Assumptions!$C$9-Assumptions!$C$11+0.4^2/2)*Assumptions!$C$10)/(0.4*SQRT(Assumptions!$C$10)))-0.4*SQRT(Assumptions!$C$10)))-2600*EXP(-Assumptions!$C$11*Assumptions!$C$10)*NORMSDIST(-((LN(2600/Assumptions!$C$7)+(Assumptions!$C$9-Assumptions!$C$11+0.4^2/2)*Assumptions!$C$10)/(0.4*SQRT(Assumptions!$C$10)))) -> 141.34857 | J58: =Assumptions!$C$7*EXP(-Assumptions!$C$9*Assumptions!$C$10)*NORMSDIST(-(((LN(2600/Assumptions!$C$7)+(Assumptions!$C$9-Assumptions!$C$11+0.45^2/2)*Assumptions!$C$10)/(0.45*SQRT(Assumptions!$C$10)))-0.45*SQRT(Assumptions!$C$10)))-2600*EXP(-Assumptions!$C$11*Assumptions!$C$10)*NORMSDIST(-((LN(2600/Assumptions!$C$7)+(Assumptions!$C$9-Assumptions!$C$11+0.45^2/2)*Assumptions!$C$10)/(0.45*SQRT(Assumptions!$C$10)))) -> 165.62819 | K58: =Assumptions!$C$7*EXP(-Assumptions!$C$9*Assumptions!$C$10)*NORMSDIST(-(((LN(2600/Assumptions!$C$7)+(Assumptions!$C$9-Assumptions!$C$11+0.5^2/2)*Assumptions!$C$10)/(0.5*SQRT(Assumptions!$C$10)))-0.5*SQRT(Assumptions!$C$10)))-2600*EXP(-Assumptions!$C$11*Assumptions!$C$10)*NORMSDIST(-((LN(2600/Assumptions!$C$7)+(Assumptions!$C$9-Assumptions!$C$11+0.5^2/2)*Assumptions!$C$10)/(0.5*SQRT(Assumptions!$C$10)))) -> 190.02532
B59: 2650 | C59: =Assumptions!$C$7*EXP(-Assumptions!$C$9*Assumptions!$C$10)*NORMSDIST(-(((LN(2650/Assumptions!$C$7)+(Assumptions!$C$9-Assumptions!$C$11+0.1^2/2)*Assumptions!$C$10)/(0.1*SQRT(Assumptions!$C$10)))-0.1*SQRT(Assumptions!$C$10)))-2650*EXP(-Assumptions!$C$11*Assumptions!$C$10)*NORMSDIST(-((LN(2650/Assumptions!$C$7)+(Assumptions!$C$9-Assumptions!$C$11+0.1^2/2)*Assumptions!$C$10)/(0.1*SQRT(Assumptions!$C$10)))) -> 4.2735683 | D59: =Assumptions!$C$7*EXP(-Assumptions!$C$9*Assumptions!$C$10)*NORMSDIST(-(((LN(2650/Assumptions!$C$7)+(Assumptions!$C$9-Assumptions!$C$11+0.15^2/2)*Assumptions!$C$10)/(0.15*SQRT(Assumptions!$C$10)))-0.15*SQRT(Assumptions!$C$10)))-2650*EXP(-Assumptions!$C$11*Assumptions!$C$10)*NORMSDIST(-((LN(2650/Assumptions!$C$7)+(Assumptions!$C$9-Assumptions!$C$11+0.15^2/2)*Assumptions!$C$10)/(0.15*SQRT(Assumptions!$C$10)))) -> 17.168883 | E59: =Assumptions!$C$7*EXP(-Assumptions!$C$9*Assumptions!$C$10)*NORMSDIST(-(((LN(2650/Assumptions!$C$7)+(Assumptions!$C$9-Assumptions!$C$11+0.2^2/2)*Assumptions!$C$10)/(0.2*SQRT(Assumptions!$C$10)))-0.2*SQRT(Assumptions!$C$10)))-2650*EXP(-Assumptions!$C$11*Assumptions!$C$10)*NORMSDIST(-((LN(2650/Assumptions!$C$7)+(Assumptions!$C$9-Assumptions!$C$11+0.2^2/2)*Assumptions!$C$10)/(0.2*SQRT(Assumptions!$C$10)))) -> 35.178106 | F59: =Assumptions!$C$7*EXP(-Assumptions!$C$9*Assumptions!$C$10)*NORMSDIST(-(((LN(2650/Assumptions!$C$7)+(Assumptions!$C$9-Assumptions!$C$11+0.25^2/2)*Assumptions!$C$10)/(0.25*SQRT(Assumptions!$C$10)))-0.25*SQRT(Assumptions!$C$10)))-2650*EXP(-Assumptions!$C$11*Assumptions!$C$10)*NORMSDIST(-((LN(2650/Assumptions!$C$7)+(Assumptions!$C$9-Assumptions!$C$11+0.25^2/2)*Assumptions!$C$10)/(0.25*SQRT(Assumptions!$C$10)))) -> 55.819172 | G59: =Assumptions!$C$7*EXP(-Assumptions!$C$9*Assumptions!$C$10)*NORMSDIST(-(((LN(2650/Assumptions!$C$7)+(Assumptions!$C$9-Assumptions!$C$11+0.3^2/2)*Assumptions!$C$10)/(0.3*SQRT(Assumptions!$C$10)))-0.3*SQRT(Assumptions!$C$10)))-2650*EXP(-Assumptions!$C$11*Assumptions!$C$10)*NORMSDIST(-((LN(2650/Assumptions!$C$7)+(Assumptions!$C$9-Assumptions!$C$11+0.3^2/2)*Assumptions!$C$10)/(0.3*SQRT(Assumptions!$C$10)))) -> 77.915417 | H59: =Assumptions!$C$7*EXP(-Assumptions!$C$9*Assumptions!$C$10)*NORMSDIST(-(((LN(2650/Assumptions!$C$7)+(Assumptions!$C$9-Assumptions!$C$11+0.35^2/2)*Assumptions!$C$10)/(0.35*SQRT(Assumptions!$C$10)))-0.35*SQRT(Assumptions!$C$10)))-2650*EXP(-Assumptions!$C$11*Assumptions!$C$10)*NORMSDIST(-((LN(2650/Assumptions!$C$7)+(Assumptions!$C$9-Assumptions!$C$11+0.35^2/2)*Assumptions!$C$10)/(0.35*SQRT(Assumptions!$C$10)))) -> 100.87928 | I59: =Assumptions!$C$7*EXP(-Assumptions!$C$9*Assumptions!$C$10)*NORMSDIST(-(((LN(2650/Assumptions!$C$7)+(Assumptions!$C$9-Assumptions!$C$11+0.4^2/2)*Assumptions!$C$10)/(0.4*SQRT(Assumptions!$C$10)))-0.4*SQRT(Assumptions!$C$10)))-2650*EXP(-Assumptions!$C$11*Assumptions!$C$10)*NORMSDIST(-((LN(2650/Assumptions!$C$7)+(Assumptions!$C$9-Assumptions!$C$11+0.4^2/2)*Assumptions!$C$10)/(0.4*SQRT(Assumptions!$C$10)))) -> 124.39113 | J59: =Assumptions!$C$7*EXP(-Assumptions!$C$9*Assumptions!$C$10)*NORMSDIST(-(((LN(2650/Assumptions!$C$7)+(Assumptions!$C$9-Assumptions!$C$11+0.45^2/2)*Assumptions!$C$10)/(0.45*SQRT(Assumptions!$C$10)))-0.45*SQRT(Assumptions!$C$10)))-2650*EXP(-Assumptions!$C$11*Assumptions!$C$10)*NORMSDIST(-((LN(2650/Assumptions!$C$7)+(Assumptions!$C$9-Assumptions!$C$11+0.45^2/2)*Assumptions!$C$10)/(0.45*SQRT(Assumptions!$C$10)))) -> 148.26328 | K59: =Assumptions!$C$7*EXP(-Assumptions!$C$9*Assumptions!$C$10)*NORMSDIST(-(((LN(2650/Assumptions!$C$7)+(Assumptions!$C$9-Assumptions!$C$11+0.5^2/2)*Assumptions!$C$10)/(0.5*SQRT(Assumptions!$C$10)))-0.5*SQRT(Assumptions!$C$10)))-2650*EXP(-Assumptions!$C$11*Assumptions!$C$10)*NORMSDIST(-((LN(2650/Assumptions!$C$7)+(Assumptions!$C$9-Assumptions!$C$11+0.5^2/2)*Assumptions!$C$10)/(0.5*SQRT(Assumptions!$C$10)))) -> 172.37815
